Workbook
Name a: #REF!
Name ABAP: #REF!
Name ABAP: #REF!
Name ABAP: #REF!
Name Administrator: 'Role Selection'!$O$12:$O$38
Name Administrator: #REF!
Name Administrator: #REF!
Name AdministratorBIDW: 'Role Selection'!$DZ$12:$DZ$38
Name AdministratorBIDW: #REF!
Name AdministratorBIDW: #REF!
Name AdministratorMiddleware: 'Role Selection'!$AO$12:$AO$38
Name AdministratorMiddleware: #REF!
Name AdministratorMiddleware: #REF!
Name AdministratorNetwork: 'Role Selection'!$AQ$12:$AQ$38
Name AdministratorNetwork: #REF!
Name AdministratorNetwork: #REF!
Name AdministratorSecurity: 'Role Selection'!$AS$12:$AS$38
Name AdministratorSecurity: #REF!
Name AdministratorSecurity: #REF!
Name AdministratorSharepoint: 'Role Selection'!$V$12:$V$38
Name AdministratorSharepoint: #REF!
Name AdministratorSharepoint: #REF!
Name AdministratorStorage: 'Role Selection'!$AU$12:$AU$38
Name AdministratorStorage: #REF!
Name AdministratorStorage: #REF!
Name AdministratorSystems: 'Role Selection'!$BA$12:$BA$38
Name AdministratorSystems: #REF!
Name AdministratorSystems: #REF!
Name AdministratorSystemsMSSQLOracle: 'Role Selection'!$AY$12:$AY$38
Name AdministratorSystemsMSSQLOracle: #REF!
Name AdministratorSystemsMSSQLOracle: #REF!
Name AdministratorSystemsSolaris: 'Role Selection'!$AW$12:$AW$38
Name AdministratorSystemsSolaris: #REF!
Name AdministratorSystemsSolaris: #REF!
Name AdministratorSystemsSybase: 'Role Selection'!$AZ$12:$AZ$38
Name AdministratorSystemsSybase: #REF!
Name AdministratorSystemsSybase: #REF!
Name AdministratorSystemsVMWareSCCMCitrix: 'Role Selection'!$AX$12:$AX$38
Name AdministratorSystemsVMWareSCCMCitrix: #REF!
Name AdministratorSystemsVMWareSCCMCitrix: #REF!
Name ADS: 'Role Selection'!$BR$12:$BR$17
Name ADS: #REF!
Name ADS: #REF!
Name Amdocs: 'Role Selection'!$CU$12:$CU$38
Name Amdocs: #REF!
Name Amdocs: #REF!
Name AnalystBusinessRules: 'Role Selection'!$EO$12:$EO$38
Name AnalystBusinessRules: #REF!
Name AnalystBusinessRules: #REF!
Name ApplicationArchitect: 'Role Selection'!$DV$30:$DV$33
Name ApplicationArchitect: #REF!
Name ApplicationArchitect: #REF!
Name Architect: 'Role Selection'!$P$12:$P$36
Name Architect: #REF!
Name Architect: #REF!
Name ArchitectAIMS: 'Role Selection'!$AD$12:$AD$36
Name ArchitectAIMS: #REF!
Name ArchitectAIMS: #REF!
Name ArchitectASG: 'Role Selection'!$DX$12:$DX$38
Name ArchitectASG: #REF!

Sheet CheckList
A1: Checklist for Costing & Pricing of Other Countries Projects | P1: Select | Q1: Select | R1: Select
P2: Client facility | Q2: Pune -GDC | R2: YES
A3: =IF(P18=46,"MESSAGE - Okay to upload this file in CRM.","ERROR MESSAGE - It is mandatory to fill in all the cells coloured in yellow. Please fill in NA if not required") -> ERROR MESSAGE - It is mandatory to fill in all the cells coloured in yellow. Please fill in NA if not required | P3: Syntel facility | Q3: Pune Other | R3: NO
P4: Not Applicable | Q4: Mumbai
A5: Client Name: | M5: =IF(G5="",0,1) -> 0 | Q5: Chennai | R5: Select
A6: Names of Solution & Sales SPOC: | M6: =IF(G6="",0,1) -> 0 | Q6: Delhi | R6: Fixed Price - Development
A7: Contact numbers: | M7: =IF(G7="",0,1) -> 0 | Q7: Hyderabad | R7: Fixed Price - Maintenance
A8: Opportunity ID in CRM: | M8: =IF(G8="",0,1) -> 0 | Q8: Other | R8: Time & Material
A9: Staffing Plan ID in CRM: | M9: =IF(G9="",0,1) -> 0 | U9: Added
Q10: Not Applicable | R10: Managed T & M
A11: 1. What is the Technology involved ?
A12: 1 (a). Generic Technology Skill % (as per staffing plan) | G12: 1
A13: 1 (b). SOG / Niche Technology Skill % (as per staffing plan) | G13: =1-G12 -> 0
A14: 1 (b) i. Provide names & employee ids of SOG / Niche resources if identified (as per staffing plan) | G14: NO
A15: Name with visa status | G15: NA
A16: Employee id | G16: NA
A18: 1. Onsite location: | M18: =IF(G18="",0,1) -> 0 | P18: =SUM(M5:M112) -> 29
A19: Onsite Facility: | G19: Select | M19: =IF(G19="Select",0,1) -> 0
A20: Offshore location: | G20: Select | M20: =IF(G20="Select",0,1) -> 0
A22: 2. Is the staffing for a New deal / Renewal / Change Request (Scope Increase / Extension) ? | G22: Select | M22: =IF(G22="Select",0,1) -> 0
A24: 3. If the answer to above question is other than 'New Deal', pls provide the Original Deal id? | G24: 0 | M24: =IF(G22="New Deal",1,IF(G24="",0,1)) -> 1
A26: 4. If the staffing is for Renewal / Change Request (Scope Increase / Extension), please provide Old PID | G26: 0
A28: 5. If there are employees onsite (Local resources), how many of them will be relocated ? | G28: 0 | M28: =IF(G28="",0,1) -> 1
A30: 6. Onsite travels : No. of Long Term deputed travels | G30: 0 | M30: =IF(G30="",0,1) -> 1
A31: No. of Short Term deputed travels | G31: 0 | M31: =IF(G31="",0,1) -> 1
M32: =IF(G32="",0,1) -> 0
A34: 7. Will there be any additional travel /rotation and if so the number of trips and duration of each trip ? | G34: 0 | M34: =IF(G34="",0,1) -> 1
A36: 8. Is there any additional HW/SW/Connectivity/other costs specifically for this project ? If yes, pls fill in the details in Hardware Software Cost tab. | G36: =+'Hardware Software Cost'!F42 -> 0 | M36: =IF(G36="",0,1) -> 1
A38: 9. Will there be any specialized training required for the project and if so what is the cost of training ? | G38: 0 | M38: =IF(G38="",0,1) -> 1
A40: 10. No. of Offshore resources working in second shift & their duration | G40: 0 | M40: =IF(G40="",0,1) -> 1
A41: No. of offshore resources working in night shift & their duration | G41: 0 | M41: =IF(G41="",0,1) -> 1
A43: 11 (a). Deal Type? | G43: Fixed Price - Development | M43: =IF(G43="Select",0,1) -> 1
A44: 11 (b). Is there any target price that we are looking to quote ? | G44: NO | M44: =IF(G44="Select",0,1) -> 1
A45: 11 (c). Target price? | G45: 0 | M45: =IF(G44="NO",1,IF(G45>0,1,0)) -> 1
A47: 12. FP Scope? | G47: Select | M47: =IF(G47="Select",0,1) -> 0
A49: 13. Who controls the Staffing, On/Off Mix, Role Mix? | G49: Select | M49: =IF(G49="Select",0,1) -> 0
A50: (The expectation is that staffing, On/Off Mix, Role Mix for FP should be controlled by Syntel)
A52: 14. Details of contractor’s resources involved (Onsite), if any. | G52: NO | M52: =IF(G52="Select",0,1) -> 1
A53: Name | G53: 0 | M53: =IF(G52="NO",1,IF(G53="",0,1)) -> 1
A54: Employee id | G54: 0 | M54: =IF(G52="NO",1,IF(G54="",0,1)) -> 1
A55: Cost/Hr | G55: 0 | M55: =IF(G52="NO",1,IF(G55="",0,1)) -> 1
A56: Bill rate/Hr | G56: 0 | M56: =IF(G52="NO",1,IF(G56="",0,1)) -> 1
A58: 15. Details of contractor’s resources involved (Offshore), if any. | G58: NO | M58: =IF(G58="Select",0,1) -> 1
A59: Name | G59: 0 | M59: =IF(G58="NO",1,IF(G59="",0,1)) -> 1
A60: Employee id | G60: 0 | M60: =IF(G58="NO",1,IF(G60="",0,1)) -> 1
A61: Cost/Hr | G61: 0 | M61: =IF(G58="NO",1,IF(G61="",0,1)) -> 1
A62: Bill rate/Hr | G62: 0 | M62: =IF(G58="NO",1,IF(G62="",0,1)) -> 1
A64: 16. If use of Sub-Contractor, why? What plans of rotation? | G64: 0 | U64: Added
A66: 17. Does this Staffing Plan include Transition efforts? | G66: Select
A68: 18. If the staffing includes transition, please mention the Total Transition efforts (in person months) | G68: 0
A70: 19. If the staffing includes any Warranty efforts, please mention the Total Warranty efforts (in person months) | G70: 0
A72: 20. Is this staffing plan/ project Agile based? | G72: NO | M72: =IF(G72="Select",0,1) -> 1
M73: =+M75+'Campus Hires %'!B42 -> 0
A74: 21. Reason for not complying with threshold campus hires. | G74: =IF('Campus Hires %'!B42=0,"Pls insert comments below","NA") -> Pls insert comments below | M74: =IF(G74="NA",1,0) -> 0
M75: =IF(G75="",0,1) -> 0
G76: Practice
A77: As Per Project
A78: 22. Onsite Hours/Day | G78: 8
A79: Offshore Hours/Day | G79: 8.5
A81: As Per MSA | G81: Pls enter monthly hrs below
A82: 23. Onsite Hours/Months | G82: =8*21 -> 168 | M82: =IF(G82>1,1,0) -> 1
A83: Offshore Hours/Months | G83: =8.5*21 -> 178.5 | M83: =IF(G83>1,1,0) -> 1
A85: 24. Has the T&M TCV Calculation tab been updated? | G85: Select | M85: =IF(G85="Select",0,1) -> 0 | U85: Added
A86: If not, why? | G86: =IF(G85="NO","Insert Comment here","NA") -> NA | M86: =IF(G86="",0,1) -> 1 | U86: Added
A88: 25. Whether Syntbots deployed on the project? | G88: Select | M88: =IF(G88="Select",0,1) -> 0
A89: If yes, estimated TCO reduction % for customer, attributed to SyntBots | G89: =(IF(G88="Yes",0%,"0")) -> 0 | M89: =IF(G89="",0,1) -> 1 | U89: Added
A90: Syntel's share of the estimated reduction of TCO, that will be added to Syntel's price (amount) | G90: =(IF(G88="Yes",0,"0")) -> 0 | M90: =IF(G90="",0,1) -> 1 | U90: Added
A91: (please refer cell T51 in T&M TCV Calculation tab)
A93: 26. Is the Deal TCV signed / confirmed to the customer? | G93: Select | M93: =IF(G93="Select",0,1) -> 0 | U93: Added
A94: If yes, why? Who approved? | G94: =IF(G93="Yes","Insert Comment here","NA") -> NA | M94: =IF(G94="",0,1) -> 1 | U94: Added
A96: 27. Any other information relating to the staffing plan / project. | G96: 0
A98: 28. Have you updated Onsite,Offshore rates and Client roles columns (I, J and HO) in "Role Selection" tab. | G98: Select | M98: =IF(G98="Select",0,1) -> 0
A101: 28. If Role Selection tab does not have the role you are looking for, please add them below. Add rows, if needed.
A102: Practice | B102: Sub - Practice | C102: Role | D102: Skill | E102: Yrs of Experience | G102: Proficiency Level
A115: Instructions for filling in the "Staffing-Roles" tab:
A117: A) If SyntBots is NOT deployed in the Project
A118: i) Fill in the "Staffing-Roles" tab with the number of resources required for delivering on the project
A119: ii) Please leave the SyntBots rows (rows 139 and 171) blank for both Onsite and Offshore sections in the "Staffing-Roles" tab
A121: B) If SyntBots is deployed in the Project
A122: i) Fill in the "Staffing-Roles" tab with the net number of resources required for delivering on the project considering efficienicies from SyntBots
A123: ii) Resources required for implementing SyntBots should be considered in staffing in B(i) above
A124: iii) In Rows 139 and 171, please fill in the savings in FTE efforts as a result of using SyntBots in the project
A125: Example for point B above : Consider a scenario where Syntbots is deployed in the project and the net estimated resources are 8 onsite and 20 offshore with savings of 3 onsite and 7 offshore FTEs because of use of Syntbots. There are 1 onsite and 3 offshore FTE's required to implement Syntbots. Hence the staffing for point B above is to done as 1) net staffing of 9 (8+1) onsite and 23 (20+3) Offshore including FTEs for Syntbots implementation. 2) in rows 139 and 171 the savings in FTEs will be 3 and 7 resp.
A129: The following table is for use by the Pricing & Costing team only: | BB129: Finance TCV Calclation | BN129: Calculation as per MSA
A130: Date | B130: Customer | C130: Project Description | D130: Opp. ID | E130: Plan ID | G130: Proj.Type | K130: Curr | L130: Rev | V130: Cost | W130: GM % (Gross) | X130: Volume Discount | Y130: Net GM % | Z130: Start Dt | AA130: End Dt | AB130: Local HC | AC130: Deputed HC | AD130: Offshore HC | AE130: Skillbay Onsite | AF130: Skillbay Offshore | AG130: Total HC | AH130: L1 Efforts | AI130: Onsite % | AJ130: On B2 | AK130: Off B2% | AL130: On B2 % | AM130: B2 % | AN130: Ap1/AP2% | AO130: New L1% | AP130: New/ Renewal | AQ130: Old Deal ID | AR130: Old PID | AS130: Old sold margin | AT130: Achieved margin | AU130: Operating metrics | AV130: Status | AW130: Remarks | AX130: Reason for approval | AY130: Rate as per Rate card | AZ130: Offsite | BA130: Offsite Premium | BB130: On Hrs per month | BC130: Off Hrs per month | BD130: Onsite Hrs | BE130: Off Hrs | BF130: Total Hrs | BG130: Onsite TCV | BH130: Off TCV | BI130: Total TCV | BJ130: Addn (Discount)/ Premium | BK130: Requestor Name | BL130: DU Owner | BM130: As per Finance | BN130: On Hrs per month | BO130: Off Hrs per month | BP130: Onsite Hrs | BQ130: Off Hrs | BR130: Total Hrs_MSA | BS130: Onsite TCV | BT130: Off TCV | BU130: Total TCV_MSA | BV130: Addn (Discount)/ Premium
B131: =+G5 -> 0 | D131: =+G8 -> 0 | K131: USD | L131: =+G45 -> 0 | W131: =IFERROR((L131-V131)/L131,0) -> 0 | Y131: =W131-X131 -> 0 | AB131: =+#REF! -> #REF! | AC131: =+#REF! -> #REF! | AD131: =+#REF! -> #REF! | AE131: =#REF! -> #REF! | AF131: =#REF! -> #REF! | AG131: =SUM(AB131:AF131) -> #REF! | AI131: =+IFERROR((AB131+AC131+AE131)/AG131,0) -> 0 | AN131: ='Campus Hires %'!B8 -> 0 | AP131: =+G22 -> Select | AQ131: =+G24 -> 0 | BB131: =+G78*21.67 -> 173.36 | BC131: =+G79*21.67 -> 184.195 | BD131: =IFERROR((AB131+AC131+AE131)*$BB$131,0) -> 0 | BE131: =IFERROR((AD131+AF131)*$BC$131,0) -> 0 | BF131: =SUM(BD131:BE131) -> 0 | BG131: =+'Role Selection'!HT181 -> 0 | BH131: =+'Role Selection'!HU181 -> 0 | BI131: =SUM(BG131:BH131) -> 0 | BJ131: =IFERROR((L131-BI131)/BI131,0) -> 0 | BM131: =+BI131 -> 0 | BN131: =+CheckList!$G$82 -> 168 | BO131: =+$G$83 -> 178.5 | BP131: =IFERROR((AB131+AC131+AE131)*$BN$131,0) -> 0 | BQ131: =IFERROR((AD131+AF131)*$BO$131,0) -> 0 | BR131: =SUM(BP131:BQ131) -> 0 | BS131: =+'Role Selection'!HX181 -> 0 | BT131: =+'Role Selection'!HY181 -> 0 | BU131: =SUM(BS131:BT131) -> 0 | BV131: =IFERROR((L131-BU131)/BU131,0) -> 0

Sheet Role Selection
A1: Instructions:
A2: 1. Please go by the following path for Role Selection: Practice --> Sub-Practice --> Role --> Proficiency Level. If you wish to make any changes to the selected role, please follow the same path mentioned above. | HR2: =+CheckList!G78 -> 8 | HS2: =+CheckList!G79 -> 8.5
A3: 2. When selecting roles, please ensure that usage of roles with campus hires (B2 AP1) at offshore is at least 8% of the total offshore utlization | HR3: =+HR2*21.67 -> 173.36 | HS3: =+HS2*21.67 -> 184.195 | HX3: =+CheckList!G82 -> 168 | HY3: =+CheckList!G83 -> 178.5
A4: 3. In absence of customer ratecard, please use GRC recommended rates in columns I and J. | HP4: Total Efforts | HR4: Hrs as per Finance | HT4: Total TCV as per Finance | HX4: Total TCV as per MSA
A5: Sr. No. | B5: Practice | C5: Sub - Practice | D5: Role | E5: Proficiency Level | F5: Combination of Role | G5: Role Code | H5: Band & Grade | I5: Onsite Rates | J5: Offshore Rates | HO5: Client Roles | HP5: Onsite | HQ5: Offshore | HR5: Onsite | HS5: Offshore | HT5: Onsite | HU5: Offshore | HV5: Total | HX5: Onsite | HY5: Offshore | HZ5: Total
A6: 1 | B6: IT | C6: JavaNetColdFusionIT | D6: DeveloperJavaNetColdFusion | E6: Junior | F6: =+B6&"/"&C6&"/"&D6&"/"&E6 -> IT/JavaNetColdFusionIT/DeveloperJavaNetColdFusion/Junior | G6: =VLOOKUP($F6,$Q$101:$T$1500,3,0) -> IT_23 | H6: =+IFERROR(VLOOKUP($G6,$C$505:$O$1001,13,0),0) -> B2 AP1 / B2 AP2 (0.6 to 3 yrs) | HP6: =+'Staffing-Roles'!DS114 -> 0 | HQ6: =+'Staffing-Roles'!DS141 -> 0 | HR6: =+HP6*$HR$3 -> 0 | HS6: =+HQ6*$HS$3 -> 0 | HT6: =+HR6*I6 -> 0 | HU6: =+HS6*J6 -> 0 | HV6: =+HT6+HU6 -> 0 | HX6: =+(HP6*$HX$3)*I6 -> 0 | HY6: =+(HQ6*$HY$3)*J6 -> 0 | HZ6: =+HX6+HY6 -> 0
A7: =+A6+1 -> 2 | F7: =+B7&"/"&C7&"/"&D7&"/"&E7 -> /// | G7: =VLOOKUP($F7,$Q$101:$T$1500,3,0) -> 0 | H7: =+IFERROR(VLOOKUP($G7,$C$505:$O$1001,13,0),0) -> 0 | HP7: =+'Staffing-Roles'!DS115 -> 0 | HQ7: =+'Staffing-Roles'!DS142 -> 0 | HR7: =+HP7*$HR$3 -> 0 | HS7: =+HQ7*$HS$3 -> 0 | HT7: =+HR7*I7 -> 0 | HU7: =+HS7*J7 -> 0 | HV7: =+HT7+HU7 -> 0 | HX7: =+(HP7*$HX$3)*I7 -> 0 | HY7: =+(HQ7*$HY$3)*J7 -> 0 | HZ7: =+HX7+HY7 -> 0
A8: =+A7+1 -> 3 | F8: =+B8&"/"&C8&"/"&D8&"/"&E8 -> /// | G8: =VLOOKUP($F8,$Q$101:$T$1500,3,0) -> 0 | H8: =+IFERROR(VLOOKUP($G8,$C$505:$O$1001,13,0),0) -> 0 | HP8: =+'Staffing-Roles'!DS116 -> 0 | HQ8: =+'Staffing-Roles'!DS143 -> 0 | HR8: =+HP8*$HR$3 -> 0 | HS8: =+HQ8*$HS$3 -> 0 | HT8: =+HR8*I8 -> 0 | HU8: =+HS8*J8 -> 0 | HV8: =+HT8+HU8 -> 0 | HX8: =+(HP8*$HX$3)*I8 -> 0 | HY8: =+(HQ8*$HY$3)*J8 -> 0 | HZ8: =+HX8+HY8 -> 0
A9: =+A8+1 -> 4 | F9: =+B9&"/"&C9&"/"&D9&"/"&E9 -> /// | G9: =VLOOKUP($F9,$Q$101:$T$1500,3,0) -> 0 | H9: =+IFERROR(VLOOKUP($G9,$C$505:$O$1001,13,0),0) -> 0 | K9: Master Data :- | HP9: =+'Staffing-Roles'!DS117 -> 0 | HQ9: =+'Staffing-Roles'!DS144 -> 0 | HR9: =+HP9*$HR$3 -> 0 | HS9: =+HQ9*$HS$3 -> 0 | HT9: =+HR9*I9 -> 0 | HU9: =+HS9*J9 -> 0 | HV9: =+HT9+HU9 -> 0 | HX9: =+(HP9*$HX$3)*I9 -> 0 | HY9: =+(HQ9*$HY$3)*J9 -> 0 | HZ9: =+HX9+HY9 -> 0
A10: =+A9+1 -> 5 | F10: =+B10&"/"&C10&"/"&D10&"/"&E10 -> /// | G10: =VLOOKUP($F10,$Q$101:$T$1500,3,0) -> 0 | H10: =+IFERROR(VLOOKUP($G10,$C$505:$O$1001,13,0),0) -> 0 | HP10: =+'Staffing-Roles'!DS118 -> 0 | HQ10: =+'Staffing-Roles'!DS145 -> 0 | HR10: =+HP10*$HR$3 -> 0 | HS10: =+HQ10*$HS$3 -> 0 | HT10: =+HR10*I10 -> 0 | HU10: =+HS10*J10 -> 0 | HV10: =+HT10+HU10 -> 0 | HX10: =+(HP10*$HX$3)*I10 -> 0 | HY10: =+(HQ10*$HY$3)*J10 -> 0 | HZ10: =+HX10+HY10 -> 0
A11: =+A10+1 -> 6 | F11: =+B11&"/"&C11&"/"&D11&"/"&E11 -> /// | G11: =VLOOKUP($F11,$Q$101:$T$1500,3,0) -> 0 | H11: =+IFERROR(VLOOKUP($G11,$C$505:$O$1001,13,0),0) -> 0 | K11: Practice | L11: Cloud | M11: Consulting | N11: PvtPubCloud | O11: Administrator | P11: Architect | Q11: Developer | R11: TechnicalLead | S11: ConsultantCloud | T11: ECM | U11: SharePoint | V11: AdministratorSharepoint | W11: ArchitectSharepoint | X11: DeveloperSharepoint | Y11: TechnicalLeadSharepoint | Z11: TestLeadShaerpoint | AA11: TesterSharepoint | AB11: IMS | AC11: ArchitectIMS | AD11: IMSArchitect | AE11: BuildandReleaseManagement | AF11: BuildManager | AG11: InfoSecurity | AH11: ConsultantInfoSec | AI11: ITSM | AJ11: ConsultantITSM | AK11: Management | AL11: ProgramManagerManagement | AM11: ProjectManagerManagement | AN11: Middleware | AO11: AdministratorMiddleware | AP11: Network | AQ11: AdministratorNetwork | AR11: Security | AS11: AdministratorSecurity | AT11: Storage | AU11: AdministratorStorage | AV11: Systems | AW11: AdministratorSystemsSolaris | AX11: AdministratorSystemsVMWareSCCMCitrix | AY11: AdministratorSystemsMSSQLOracle | AZ11: AdministratorSystemsSybase | BA11: AdministratorSystems | BB11: IMSBASIC | BC11: DataCentre | BD11: DataCenterOperations | BE11: Desktop | BF11: DesktopEngineer | BG11: HelpDesk | BH11: HelpDeskAnalyst | BI11: MailSetup | BJ11: Configurator | BK11: NOCDesktop | BL11: DesktopEngineerNOC | BM11: OpsSupport | BN11: OpnSupportIMSBASIC | BO11: Telecom | BP11: Technician | BQ11: IT | BR11: ADS | BS11: BusinessSystemsAnalyst | BT11: Domain | BU11: BusinessAnalyst | BV11: DuckCreek | BW11: ArchitectDuckCreek | BX11: ProjectManagerDuckCreek | BY11: Generic | BZ11: DatabaseAdministratorIMSGeneric | CA11: DeveloperGoldenSource | CB11: Intergration | CC11: ConsultantITIL | CD11: JavaNet | CE11: ArchitectJavaNet | CF11: JavaNetColdFusion | CG11: DeveloperJavaNetColdFusion | CH11: Lotus Notes | CI11: DeveloperLotusNotes | CJ11: Mainframe | CK11: DeveloperMainframe | CL11: ManagementIT | CM11: ProjectManagerIT | CN11: Operation | CO11: Others | CP11: TechnicalWriter | CQ11: TumbleWeed | CR11: DeveloperTumbleWeed | CS11: Vermillion | CT11: DeveloperVermillion | CU11: Amdocs | CV11: DeveloperAmdocs | CW11: ProjectManagerAmdocs | CX11: JavaNetColdFusionIT | CY11: TechnicalLeadJavaNetColdFusion | CZ11: Remedy | DA11: DeveloperRemedy | DB11: SQL | DC11: DeveloperSQL | DD11: LatentZero | DE11: DeveloperLatentZero | DF11: DomainIT | DG11: ConsultantDomain | DH11: Mobility | DI11: MobilityE | DJ11: ArchitectMobility | DK11: DeveloperMobility | DL11: TechnicalLeadMobility | DM11: SAP | DN11: SAPABAP | DO11: TechnicalABAP | DP11: SAPBasis | DQ11: TechnicalBasis | DR11: SAPDomain | DS11: FunctionalDomain | DT11: SAPManagement | DU11: ProjectManagerSAPManagement | DV11: SOG | DW11: ASG | DX11: ArchitectASG | DY11: BIDW | DZ11: AdministratorBIDW | EA11: ArchitectBIDW | EB11: DeveloperBIDWCognos | EC11: DeveloperBIDW | ED11: DeveloperBIDWETL | EE11: DeveloperBIDWInformatica | EF11: DeveloperBIDWReporting | EG11: ProjectManagerBIDW | EH11: TechnicalLeadAbinitioInformaticaDatastage | EI11: TechnicalLeadActuateCrystal | EJ11: TechnicalLeadMicrostrategyAbinitioTeradata | EK11: TechnicalLeadCognosBO | EL11: TechnicalLeadReporting | EM11: TesterBIDW | EN11: EAI | EO11: AnalystBusinessRules | EP11: ArchitectTIBCO | EQ11: ArchitectEAI | ER11: ArchitectBusinessRules | ES11: ArchitectProcess | ET11: ConfiguratorMercatorMQ | EU11: ConsultantTIBCO | EV11: DeveloperEAI | EW11: DeveloperIBMWebSphereProcessServer | EX11: DeveloperIBMWebSphereMessageBroker | EY11: DeveloperTibco | EZ11: DeveloperWebApplicationIntegrationMiddlewareInfrastructure | FA11: DeveloperWebMethods | FB11: DeveloperBusinessRules | FC11: ProjectManagerEAI | FD11: TechnicalLeadEAI | FE11: Oracle | FF11: DatabaseAdministratorOracle | FG11: DeveloperOracle | FH11: FunctionalOracle | FI11: ProjectManagerOracle | FJ11: TechnicalOracle | FK11: Peoplesoft | FL11: FunctionalPeoplesoft | FM11: ProjectManagerPeoplesoft | FN11: TechnicalPeoplesoft | FO11: ConsultantPeoplesoft | FP11: SOGTWO | FQ11: Varicent | FR11: DeveloperVaricent | FS11: Testing | FT11: Automation | FU11: DomainTesting | FV11: ManualTesting | FW11: Performance | FX11: TestingTwo | FY11: ProductBased | FZ11: AutomationTester | GA11: AutomationTestLead | GB11: AutomationTestManager | GC11: DomainTestBusinessAnalyst | GD11: ManualTestingTester | GE11: ManualTestingTestLead | GF11: ManualTestingTestManager | GG11: PerformanceTester | GH11: PerformanceTestLead | GI11: PerformanceTestManager | GJ11: ProductBasedTester | GK11: ProductBasedTestLead | GL11: ProductBasedTestManager | GM11: PLMEnggServices | GN11: PLM | GO11: PLMDeveloper | GP11: PLMTechnicalLead | GQ11: PLMAdministrator | GR11: PLMDesigner | GS11: PLMProjectManager | GT11: PLMEnggServices | GU11: EnggServices | GV11: EnggServicesAnalyst | GW11: EnggServicesProject Lead | GX11: EnggServicesDeveloper | GY11: EnggServicesDesigner | GZ11: EnggServicesProjectManager | HA11: SAPone | HB11: SAPArchitect | HC11: IMSGeneric | HD11: Integrator | HE11: DeveloperEDI | HF11: EDI | HG11: PEGA | HH11: PEGAEAI | HI11: PEGALeadSystemArchitect | HJ11: PEGAProjectManager | HK11: PEGASeniorArchitect | HL11: PEGAArchitect | HM11: PEGADeveloper | HP11: =+'Staffing-Roles'!DS119 -> 0 | HQ11: =+'Staffing-Roles'!DS146 -> 0 | HR11: =+HP11*$HR$3 -> 0 | HS11: =+HQ11*$HS$3 -> 0 | HT11: =+HR11*I11 -> 0 | HU11: =+HS11*J11 -> 0 | HV11: =+HT11+HU11 -> 0 | HX11: =+(HP11*$HX$3)*I11 -> 0 | HY11: =+(HQ11*$HY$3)*J11 -> 0 | HZ11: =+HX11+HY11 -> 0
A12: =+A11+1 -> 7 | F12: =+B12&"/"&C12&"/"&D12&"/"&E12 -> /// | G12: =VLOOKUP($F12,$Q$101:$T$1500,3,0) -> 0 | H12: =+IFERROR(VLOOKUP($G12,$C$505:$O$1001,13,0),0) -> 0 | BQ12: Domain | FK12: DatabaseAdministratorPeoplesoft | GN12: PLMDeveloper | GU12: EnggServicesAnalyst | HP12: =+'Staffing-Roles'!DS120 -> 0 | HQ12: =+'Staffing-Roles'!DS147 -> 0 | HR12: =+HP12*$HR$3 -> 0 | HS12: =+HQ12*$HS$3 -> 0 | HT12: =+HR12*I12 -> 0 | HU12: =+HS12*J12 -> 0 | HV12: =+HT12+HU12 -> 0 | HX12: =+(HP12*$HX$3)*I12 -> 0 | HY12: =+(HQ12*$HY$3)*J12 -> 0 | HZ12: =+HX12+HY12 -> 0
A13: =+A12+1 -> 8 | F13: =+B13&"/"&C13&"/"&D13&"/"&E13 -> /// | G13: =VLOOKUP($F13,$Q$101:$T$1500,3,0) -> 0 | H13: =+IFERROR(VLOOKUP($G13,$C$505:$O$1001,13,0),0) -> 0 | K13: Cloud | L13: Consulting | M13: ConsultantCloud | N13: Administrator | O13: Junior | P13: Junior | Q13: Junior | R13: Junior | S13: Junior | T13: SharePoint | U13: AdministratorSharepoint | V13: Junior | W13: Junior | X13: Junior | Y13: Junior | Z13: Junior | AA13: Junior | AB13: ArchitectIMS | AC13: IMSArchitect | AD13: Junior | AE13: BuildManager | AF13: Junior | AG13: ConsultantInfoSec | AH13: Junior | AI13: ConsultantITSM | AJ13: Junior | AK13: ProgramManagerManagement | AL13: Junior | AM13: Junior | AN13: AdministratorMiddleware | AO13: Junior | AP13: AdministratorNetwork | AQ13: Junior | AR13: AdministratorSecurity | AS13: Junior | AT13: AdministratorStorage | AU13: Junior | AV13: AdministratorSystemsSolaris | AW13: Junior | AX13: Junior | AY13: Junior | AZ13: Junior | BA13: Junior | BB13: DataCentre | BC13: DataCenterOperations | BD13: Junior | BE13: DesktopEngineer | BF13: Junior | BG13: HelpDeskAnalyst | BH13: Junior | BI13: Configurator | BJ13: Junior | BK13: DesktopEngineerNOC | BL13: Junior | BM13: OpnSupportIMSBASIC | BN13: Junior | BO13: Technician | BP13: Junior | BQ13: ADS | BR13: BusinessSystemsAnalyst | BS13: Junior | BT13: BusinessAnalyst | BU13: Junior | BV13: ArchitectDuckCreek | BW13: Junior | BX13: Junior | BY13: ContentEntryAnalyst | BZ13: Junior | CA13: Junior | CB13: IntegrationEngineer | CC13: Junior | CD13: ArchitectJavaNet | CE13: Junior | CF13: DeveloperJavaNetColdFusion | CG13: Junior | CH13: DeveloperLotusNotes | CI13: Junior | CJ13: DeveloperMainframe | CK13: Junior | CL13: EngagementManagerAccount ManagerProject DirectorProgramController | CM13: Junior | CN13: OperationsAnalyst | CO13: GraphicsDesigner | CP13: Junior | CQ13: DeveloperTumbleWeed | CR13: Junior | CS13: DeveloperVermillion | CT13: Junior | CU13: DeveloperAmdocs | CV13: Junior | CW13: Junior | CX13: TechnicalLeadJavaNetColdFusion | CY13: Junior | CZ13: DeveloperRemedy | DA13: Junior | DB13: DeveloperSQL | DC13: Junior | DD13: DeveloperLatentZero | DE13: Junior | DF13: ConsultantDomain | DG13: Junior | DH13: MobilityE | DI13: ArchitectMobility | DJ13: Junior | DK13: Junior | DL13: Junior | DM13: SAPABAP | DN13: TechnicalABAP | DO13: Junior | DP13: TechnicalBasis | DQ13: Junior | DR13: FunctionalDomain | DS13: Junior | DT13: ProjectManagerSAPManagement | DU13: Junior | DV13: ASG | DW13: ApplicationArchitect | DX13: ApplicationArchitect | DY13: AdministratorBIDW | DZ13: Junior | EA13: Junior | EB13: Junior | EC13: Junior | ED13: Junior | EE13: Junior | EF13: Junior | EG13: Junior | EH13: Junior | EI13: Junior | EJ13: Junior | EK13: Junior | EL13: Junior | EM13: Junior | EN13: AnalystBusinessRules | EO13: Junior | EP13: Junior | EQ13: Junior | ER13: Junior | ES13: Junior | ET13: Junior | EU13: Junior | EV13: Junior | EW13: Junior | EX13: Junior | EY13: Junior | EZ13: Junior | FA13: Junior | FB13: Junior | FC13: Junior | FD13: Junior | FE13: DatabaseAdministratorOracle | FF13: Junior | FG13: Junior | FH13: Junior | FI13: Junior | FJ13: Junior | FK13: FunctionalPeoplesoft | FL13: Junior | FM13: Junior | FN13: Junior | FO13: Junior | FP13: ConsultantUsabilitySpecialist | FQ13: DeveloperVaricent | FR13: Junior | FS13: Automation | FT13: AutomationTester | FU13: DomainTestBusinessAnalyst | FV13: ManualTestingTester | FW13: PerformanceTester | FX13: TestingTestDirector | FY13: ProductBasedTester | FZ13: Junior | GA13: Junior | GB13: Junior | GC13: Junior | GD13: Junior | GE13: Junior | GF13: Junior | GG13: Junior | GH13: Junior | GI13: Junior | GJ13: Junior | GK13: Junior | GL13: Junior | GM13: PLM | GN13: PLMTechnicalLead | GO13: Junior | GP13: Junior | GQ13: Junior | GR13: Junior | GS13: Junior | GT13: EnggServices | GU13: EnggServicesProject Lead | GV13: Junior | GW13: Junior | GX13: Junior | GY13: Junior | GZ13: Junior | HA13: SAPArchitect | HB13: Junior | HC13: DatabaseAdministratorIMSGeneric | HD13: Junior | HE13: Junior | HF13: DeveloperEDI | HG13: PEGAEAI | HH13: PEGALeadSystemArchitect | HI13: Senior | HJ13: Junior | HK13: Junior | HL13: Senior | HM13: Junior | HP13: =+'Staffing-Roles'!DS121 -> 0 | HQ13: =+'Staffing-Roles'!DS148 -> 0 | HR13: =+HP13*$HR$3 -> 0 | HS13: =+HQ13*$HS$3 -> 0 | HT13: =+HR13*I13 -> 0 | HU13: =+HS13*J13 -> 0 | HV13: =+HT13+HU13 -> 0 | HX13: =+(HP13*$HX$3)*I13 -> 0 | HY13: =+(HQ13*$HY$3)*J13 -> 0 | HZ13: =+HX13+HY13 -> 0
A14: =+A13+1 -> 9 | F14: =+B14&"/"&C14&"/"&D14&"/"&E14 -> /// | G14: =VLOOKUP($F14,$Q$101:$T$1500,3,0) -> 0 | H14: =+IFERROR(VLOOKUP($G14,$C$505:$O$1001,13,0),0) -> 0 | K14: ECM | L14: PvtPubCloud | N14: Architect | O14: MidLevel | P14: MidLevel | Q14: MidLevel | R14: Senior | S14: MidLevel | T14: Collaboration | U14: ArchitectSharepoint | V14: MidLevel | W14: MidLevel | X14: MidLevel | Y14: Senior | Z14: Senior | AA14: Senior | AB14: BuildandReleaseManagement | AD14: Midlevel | AF14: MidLevel | AH14: MidLevel | AJ14: MidLevel | AK14: ProjectManagerManagement | AL14: MidLevel | AM14: MidLevel | AO14: MidLevel | AQ14: MidLevel | AS14: MidLevel | AU14: MidLevel | AV14: AdministratorSystemsVMWareSCCMCitrix | AW14: MidLevel | AX14: MidLevel | AY14: MidLevel | AZ14: MidLevel | BA14: MidLevel | BB14: Desktop | BD14: MidLevel | BF14: MidLevel | BH14: Senior | BJ14: MidLevel | BL14: MidLevel | BN14: Senior | BP14: MidLevel | BQ14: DuckCreek | BS14: MidLevel | BU14: MidLevel | BV14: Configurator | BW14: MidLevel | BX14: MidLevel | BZ14: MidLevel | CA14: MidLevel | CB14: IntegrationSpecialist | CC14: MidLevel | CE14: MidLevel | CF14: TechnicalLeadJavaNetColdFusion | CG14: MidLevel | CI14: MidLevel | CK14: MidLevel | CL14: ProjectManagerIT | CM14: MidLevel | CN14: ProcessLeader | CO14: TechnicalWriter | CP14: MidLevel | CR14: MidLevel | CT14: MidLevel | CU14: ProjectManagerAmdocs | CV14: MidLevel | CW14: MidLevel | CY14: Senior | DA14: MidLevel | DC14: MidLevel | DE14: MidLevel | DG14: MidLevel | DI14: DeveloperMobility | DJ14: MidLevel | DK14: MidLevel | DL14: Senior | DM14: SAPBasis | DO14: MidLevel | DQ14: MidLevel | DS14: MidLevel | DU14: MidLevel | DV14: BIDW | DW14: SolutionArchitect | DX14: SolutionArchitect | DY14: ArchitectBIDW | DZ14: MidLevel | EA14: MidLevel | EB14: MidLevel | EC14: MidLevel | ED14: MidLevel | EE14: MidLevel | EF14: MidLevel | EG14: MidLevel | EH14: Senior | EI14: Senior | EJ14: Senior | EK14: Senior | EL14: Senior | EM14: Senior | EN14: ArchitectTIBCO | EO14: MidLevel | EP14: MidLevel | EQ14: MidLevel | ER14: MidLevel | ES14: MidLevel | ET14: MidLevel | EU14: MidLevel | EW14: MidLevel | EX14: MidLevel | EY14: MidLevel | EZ14: MidLevel | FA14: MidLevel | FB14: MidLevel | FC14: MidLevel | FD14: Senior | FE14: DeveloperOracle | FF14: MidLevel | FG14: MidLevel | FH14: MidLevel | FI14: MidLevel | FJ14: MidLevel | FK14: ProjectManagerPeoplesoft | FL14: MidLevel | FM14: MidLevel | FN14: MidLevel | FO14: MidLevel | FP14: DataAdministratorProcess AnalystSOG | FR14: MidLevel | FS14: DomainTesting | FT14: AutomationTestLead | FV14: ManualTestingTestLead | FW14: PerformanceTestLead | FX14: TestingTestProcessConsultant | FY14: ProductBasedTestLead | FZ14: MidLevel | GA14: Senior | GB14: MidLevel | GC14: Senior | GD14: MidLevel | GE14: Senior | GF14: MidLevel | GG14: MidLevel | GH14: Senior | GI14: MidLevel | GJ14: Senior | GK14: Senior | GL14: MidLevel | GM14: EnggServices | GN14: PLMAdministrator | GO14: MidLevel | GP14: Senior | GQ14: MidLevel | GR14: Senior | GS14: MidLevel | GU14: EnggServicesDeveloper | GV14: MidLevel | GW14: Senior | GX14: MidLevel | GY14: Senior | GZ14: MidLevel | HB14: MidLevel | HD14: MidLevel | HE14: MidLevel | HH14: PEGAProjectManager | HJ14: MidLevel | HK14: MidLevel | HL14: Junior | HP14: =+'Staffing-Roles'!DS122 -> 0 | HQ14: =+'Staffing-Roles'!DS149 -> 0 | HR14: =+HP14*$HR$3 -> 0 | HS14: =+HQ14*$HS$3 -> 0 | HT14: =+HR14*I14 -> 0 | HU14: =+HS14*J14 -> 0 | HV14: =+HT14+HU14 -> 0 | HX14: =+(HP14*$HX$3)*I14 -> 0 | HY14: =+(HQ14*$HY$3)*J14 -> 0 | HZ14: =+HX14+HY14 -> 0
A15: =+A14+1 -> 10 | F15: =+B15&"/"&C15&"/"&D15&"/"&E15 -> /// | G15: =VLOOKUP($F15,$Q$101:$T$1500,3,0) -> 0 | H15: =+IFERROR(VLOOKUP($G15,$C$505:$O$1001,13,0),0) -> 0 | K15: IMS | N15: Developer | O15: Senior | P15: Senior | Q15: Senior | S15: Senior | T15: Customer_Communication_Management | U15: DeveloperSharepoint | V15: Senior | W15: Senior | X15: Senior | AB15: InfoSecurity | AD15: Senior | AF15: Senior | AH15: Senior | AJ15: Senior | AK15: ProgramLeadManagement | AL15: Senior | AM15: Senior | AO15: Senior | AQ15: Senior | AS15: Senior | AU15: Senior | AV15: AdministratorSystemsMSSQLOracle | AW15: Senior | AX15: Senior | AY15: Senior | AZ15: Senior | BA15: Senior | BB15: HelpDesk | BD15: Senior | BF15: Senior | BJ15: Senior | BL15: Senior | BP15: Senior | BQ15: Generic | BS15: Senior | BU15: Senior | BV15: Integrator | BW15: Senior | BX15: Senior | BZ15: Senior | CA15: Senior | CB15: InterfaceDesigner | CC15: Senior | CE15: Senior | CG15: Senior | CI15: Senior | CK15: Senior | CM15: Senior | CO15: TemplateDeveloper | CP15: Senior | CR15: Senior | CT15: Senior | CV15: Senior | CW15: Senior | DA15: Senior | DC15: Senior | DE15: Senior | DG15: Senior | DI15: TechnicalLeadMobility | DJ15: Senior | DK15: Senior | DM15: SAPDomain | DO15: Senior | DQ15: Senior | DS15: Senior | DU15: Senior | DV15: EAI | DW15: EnterpriseArchitect | DX15: EnterpriseArchitect | DY15: DataModelerBIDW | DZ15: Senior | EA15: Senior | EB15: Senior | EC15: Senior | ED15: Senior | EE15: Senior | EF15: Senior | EG15: Senior | EN15: ArchitectEAI | EO15: Senior | EP15: Senior | EQ15: Senior | ER15: Senior | ES15: Senior | ET15: Senior | EU15: Senior | EW15: Senior | EX15: Senior | EY15: Senior | EZ15: Senior | FA15: Senior | FB15: Senior | FC15: Senior | FE15: FunctionalOracle | FF15: Senior | FG15: Senior | FH15: Senior | FI15: Senior | FJ15: Senior | FK15: TechnicalPeoplesoft | FL15: Senior | FM15: Senior | FN15: Senior | FO15: Senior | FR15: Senior | FS15: ManualTesting | FT15: AutomationTestManager | FV15: ManualTestingTestManager | FW15: PerformanceTestManager | FY15: ProductBasedTestManager | FZ15: Senior | GB15: Senior | GD15: Senior | GF15: Senior | GG15: Senior | GI15: Senior | GL15: Senior | GN15: PLMDesigner | GO15: Senior | GQ15: Senior | GS15: Senior | GU15: EnggServicesDesigner | GV15: Senior | GX15: Senior | GZ15: Senior | HB15: Senior | HD15: Senior | HE15: Senior | HH15: PEGASeniorArchitect | HJ15: Senior | HK15: Senior | HP15: =+'Staffing-Roles'!DS123 -> 0 | HQ15: =+'Staffing-Roles'!DS150 -> 0 | HR15: =+HP15*$HR$3 -> 0 | HS15: =+HQ15*$HS$3 -> 0 | HT15: =+HR15*I15 -> 0 | HU15: =+HS15*J15 -> 0 | HV15: =+HT15+HU15 -> 0 | HX15: =+(HP15*$HX$3)*I15 -> 0 | HY15: =+(HQ15*$HY$3)*J15 -> 0 | HZ15: =+HX15+HY15 -> 0
A16: =+A15+1 -> 11 | F16: =+B16&"/"&C16&"/"&D16&"/"&E16 -> /// | G16: =VLOOKUP($F16,$Q$101:$T$1500,3,0) -> 0 | H16: =+IFERROR(VLOOKUP($G16,$C$505:$O$1001,13,0),0) -> 0 | K16: IMSBASIC | N16: TechnicalLead | T16: Document_Management | U16: TechnicalLeadSharepoint | AB16: ITSM | AV16: AdministratorSystems | BB16: MailSetup | BQ16: GoldenSource | BV16: ProjectManagerDuckCreek | DM16: SAPManagement | DV16: EDI | DY16: DeveloperBIDWCognos | EN16: ArchitectBusinessRules | FE16: ProjectManagerOracle | FK16: ConsultantPeoplesoft | FS16: Performance | GN16: PLMProjectManager | GU16: EnggServicesProjectManager | HH16: PEGAArchitect | HP16: =+'Staffing-Roles'!DS124 -> 0 | HQ16: =+'Staffing-Roles'!DS151 -> 0 | HR16: =+HP16*$HR$3 -> 0 | HS16: =+HQ16*$HS$3 -> 0 | HT16: =+HR16*I16 -> 0 | HU16: =+HS16*J16 -> 0 | HV16: =+HT16+HU16 -> 0 | HX16: =+(HP16*$HX$3)*I16 -> 0 | HY16: =+(HQ16*$HY$3)*J16 -> 0 | HZ16: =+HX16+HY16 -> 0
A17: =+A16+1 -> 12 | F17: =+B17&"/"&C17&"/"&D17&"/"&E17 -> /// | G17: =VLOOKUP($F17,$Q$101:$T$1500,3,0) -> 0 | H17: =+IFERROR(VLOOKUP($G17,$C$505:$O$1001,13,0),0) -> 0 | K17: IT | T17: Imaging_and_Scanning | U17: TestLeadShaerpoint | AB17: Management | AV17: AdministratorSystemsSybase | BB17: NOCDesktop | BQ17: ITIL | DM17: SAPone | DV17: Oracle | DY17: DeveloperBIDW | EN17: ArchitectProcess | FE17: TechnicalOracle | FS17: ProductBased | HH17: PEGADeveloper | HP17: =+'Staffing-Roles'!DS125 -> 0 | HQ17: =+'Staffing-Roles'!DS152 -> 0 | HR17: =+HP17*$HR$3 -> 0 | HS17: =+HQ17*$HS$3 -> 0 | HT17: =+HR17*I17 -> 0 | HU17: =+HS17*J17 -> 0 | HV17: =+HT17+HU17 -> 0 | HX17: =+(HP17*$HX$3)*I17 -> 0 | HY17: =+(HQ17*$HY$3)*J17 -> 0 | HZ17: =+HX17+HY17 -> 0
A18: =+A17+1 -> 13 | F18: =+B18&"/"&C18&"/"&D18&"/"&E18 -> /// | G18: =VLOOKUP($F18,$Q$101:$T$1500,3,0) -> 0 | H18: =+IFERROR(VLOOKUP($G18,$C$505:$O$1001,13,0),0) -> 0 | K18: SOG | T18: Web_Content_Management | U18: TesterSharepoint | AB18: Middleware | BB18: OpsSupport | BQ18: JavaNet | DV18: Peoplesoft | DY18: DeveloperBIDWETL | EN18: ConfiguratorMercatorMQ | FS18: TestingTwo | HP18: =+'Staffing-Roles'!DS126 -> 0 | HQ18: =+'Staffing-Roles'!DS153 -> 0 | HR18: =+HP18*$HR$3 -> 0 | HS18: =+HQ18*$HS$3 -> 0 | HT18: =+HR18*I18 -> 0 | HU18: =+HS18*J18 -> 0 | HV18: =+HT18+HU18 -> 0 | HX18: =+(HP18*$HX$3)*I18 -> 0 | HY18: =+(HQ18*$HY$3)*J18 -> 0 | HZ18: =+HX18+HY18 -> 0
A19: =+A18+1 -> 14 | F19: =+B19&"/"&C19&"/"&D19&"/"&E19 -> /// | G19: =VLOOKUP($F19,$Q$101:$T$1500,3,0) -> 0 | H19: =+IFERROR(VLOOKUP($G19,$C$505:$O$1001,13,0),0) -> 0 | K19: Testing | AB19: Network | BB19: Telecom | BQ19: JavaNetColdFusionIT | DV19: SOGTWO | DY19: DeveloperBIDWInformatica | EN19: ConsultantTIBCO | HP19: =+'Staffing-Roles'!DS127 -> 0 | HQ19: =+'Staffing-Roles'!DS154 -> 0 | HR19: =+HP19*$HR$3 -> 0 | HS19: =+HQ19*$HS$3 -> 0 | HT19: =+HR19*I19 -> 0 | HU19: =+HS19*J19 -> 0 | HV19: =+HT19+HU19 -> 0 | HX19: =+(HP19*$HX$3)*I19 -> 0 | HY19: =+(HQ19*$HY$3)*J19 -> 0 | HZ19: =+HX19+HY19 -> 0
A20: =+A19+1 -> 15 | F20: =+B20&"/"&C20&"/"&D20&"/"&E20 -> /// | G20: =VLOOKUP($F20,$Q$101:$T$1500,3,0) -> 0 | H20: =+IFERROR(VLOOKUP($G20,$C$505:$O$1001,13,0),0) -> 0 | K20: Mobility | AB20: Security | BQ20: LotusNotes | DV20: SAPABAP | DY20: DeveloperBIDWReporting | EN20: DeliveryManagerEIS | HP20: =+'Staffing-Roles'!DS128 -> 0 | HQ20: =+'Staffing-Roles'!DS155 -> 0 | HR20: =+HP20*$HR$3 -> 0 | HS20: =+HQ20*$HS$3 -> 0 | HT20: =+HR20*I20 -> 0 | HU20: =+HS20*J20 -> 0 | HV20: =+HT20+HU20 -> 0 | HX20: =+(HP20*$HX$3)*I20 -> 0 | HY20: =+(HQ20*$HY$3)*J20 -> 0 | HZ20: =+HX20+HY20 -> 0
A21: =+A20+1 -> 16 | F21: =+B21&"/"&C21&"/"&D21&"/"&E21 -> /// | G21: =VLOOKUP($F21,$Q$101:$T$1500,3,0) -> 0 | H21: =+IFERROR(VLOOKUP($G21,$C$505:$O$1001,13,0),0) -> 0 | K21: PLMEnggServices | AB21: Storage | BQ21: Mainframe | DV21: SAPBasis | DY21: ProjectManagerBIDW | EN21: DeveloperIBMWebSphereProcessServer | HP21: =+'Staffing-Roles'!DS129 -> 0 | HQ21: =+'Staffing-Roles'!DS156 -> 0 | HR21: =+HP21*$HR$3 -> 0 | HS21: =+HQ21*$HS$3 -> 0 | HT21: =+HR21*I21 -> 0 | HU21: =+HS21*J21 -> 0 | HV21: =+HT21+HU21 -> 0 | HX21: =+(HP21*$HX$3)*I21 -> 0 | HY21: =+(HQ21*$HY$3)*J21 -> 0 | HZ21: =+HX21+HY21 -> 0
A22: =+A21+1 -> 17 | F22: =+B22&"/"&C22&"/"&D22&"/"&E22 -> /// | G22: =VLOOKUP($F22,$Q$101:$T$1500,3,0) -> 0 | H22: =+IFERROR(VLOOKUP($G22,$C$505:$O$1001,13,0),0) -> 0 | K22: PEGA | AB22: Systems | BQ22: ManagementIT | DV22: SAPDomain | DY22: TechnicalLeadAbinitioInformaticaDatastage | EN22: DeveloperIBMWebSphereMessageBroker | HP22: =+'Staffing-Roles'!DS130 -> 0 | HQ22: =+'Staffing-Roles'!DS157 -> 0 | HR22: =+HP22*$HR$3 -> 0 | HS22: =+HQ22*$HS$3 -> 0 | HT22: =+HR22*I22 -> 0 | HU22: =+HS22*J22 -> 0 | HV22: =+HT22+HU22 -> 0 | HX22: =+(HP22*$HX$3)*I22 -> 0 | HY22: =+(HQ22*$HY$3)*J22 -> 0 | HZ22: =+HX22+HY22 -> 0
A23: =+A22+1 -> 18 | F23: =+B23&"/"&C23&"/"&D23&"/"&E23 -> /// | G23: =VLOOKUP($F23,$Q$101:$T$1500,3,0) -> 0 | H23: =+IFERROR(VLOOKUP($G23,$C$505:$O$1001,13,0),0) -> 0 | AB23: IMSGeneric | BQ23: Operation | DV23: SAPManagement | DY23: TechnicalLeadActuateCrystal | EN23: DeveloperTibco | HP23: =+'Staffing-Roles'!DS131 -> 0 | HQ23: =+'Staffing-Roles'!DS158 -> 0 | HR23: =+HP23*$HR$3 -> 0 | HS23: =+HQ23*$HS$3 -> 0 | HT23: =+HR23*I23 -> 0 | HU23: =+HS23*J23 -> 0 | HV23: =+HT23+HU23 -> 0 | HX23: =+(HP23*$HX$3)*I23 -> 0 | HY23: =+(HQ23*$HY$3)*J23 -> 0 | HZ23: =+HX23+HY23 -> 0
A24: =+A23+1 -> 19 | F24: =+B24&"/"&C24&"/"&D24&"/"&E24 -> /// | G24: =VLOOKUP($F24,$Q$101:$T$1500,3,0) -> 0 | H24: =+IFERROR(VLOOKUP($G24,$C$505:$O$1001,13,0),0) -> 0 | BQ24: Others | DV24: SAPone | DY24: TechnicalLeadMicrostrategyAbinitioTeradata | EN24: DeveloperWebApplicationIntegrationMiddlewareInfrastructure | HP24: =+'Staffing-Roles'!DS132 -> 0 | HQ24: =+'Staffing-Roles'!DS159 -> 0 | HR24: =+HP24*$HR$3 -> 0 | HS24: =+HQ24*$HS$3 -> 0 | HT24: =+HR24*I24 -> 0 | HU24: =+HS24*J24 -> 0 | HV24: =+HT24+HU24 -> 0 | HX24: =+(HP24*$HX$3)*I24 -> 0 | HY24: =+(HQ24*$HY$3)*J24 -> 0 | HZ24: =+HX24+HY24 -> 0
A25: =+A24+1 -> 20 | F25: =+B25&"/"&C25&"/"&D25&"/"&E25 -> /// | G25: =VLOOKUP($F25,$Q$101:$T$1500,3,0) -> 0 | H25: =+IFERROR(VLOOKUP($G25,$C$505:$O$1001,13,0),0) -> 0 | BQ25: TumbleWeed | DV25: Intergration | DY25: TechnicalLeadCognosBO | EN25: DeveloperWebMethods | HP25: =+'Staffing-Roles'!DS133 -> 0 | HQ25: =+'Staffing-Roles'!DS160 -> 0 | HR25: =+HP25*$HR$3 -> 0 | HS25: =+HQ25*$HS$3 -> 0 | HT25: =+HR25*I25 -> 0 | HU25: =+HS25*J25 -> 0 | HV25: =+HT25+HU25 -> 0 | HX25: =+(HP25*$HX$3)*I25 -> 0 | HY25: =+(HQ25*$HY$3)*J25 -> 0 | HZ25: =+HX25+HY25 -> 0
A26: =+A25+1 -> 21 | F26: =+B26&"/"&C26&"/"&D26&"/"&E26 -> /// | G26: =VLOOKUP($F26,$Q$101:$T$1500,3,0) -> 0 | H26: =+IFERROR(VLOOKUP($G26,$C$505:$O$1001,13,0),0) -> 0 | BQ26: Vermillion | DV26: EDI | DY26: TechnicalLeadReporting | EN26: DeveloperBusinessRules | HP26: =+'Staffing-Roles'!DS134 -> 0 | HQ26: =+'Staffing-Roles'!DS161 -> 0 | HR26: =+HP26*$HR$3 -> 0 | HS26: =+HQ26*$HS$3 -> 0 | HT26: =+HR26*I26 -> 0 | HU26: =+HS26*J26 -> 0 | HV26: =+HT26+HU26 -> 0 | HX26: =+(HP26*$HX$3)*I26 -> 0 | HY26: =+(HQ26*$HY$3)*J26 -> 0 | HZ26: =+HX26+HY26 -> 0
A27: =+A26+1 -> 22 | F27: =+B27&"/"&C27&"/"&D27&"/"&E27 -> /// | G27: =VLOOKUP($F27,$Q$101:$T$1500,3,0) -> 0 | H27: =+IFERROR(VLOOKUP($G27,$C$505:$O$1001,13,0),0) -> 0 | BQ27: Amdocs | DY27: TesterBIDW | EN27: ModelerBusinessRules
A28: =+A27+1 -> 23 | F28: =+B28&"/"&C28&"/"&D28&"/"&E28 -> /// | G28: =VLOOKUP($F28,$Q$101:$T$1500,3,0) -> 0 | H28: =+IFERROR(VLOOKUP($G28,$C$505:$O$1001,13,0),0) -> 0 | BQ28: Remedy | EN28: ProcessLeadModeler
A29: =+A28+1 -> 24 | F29: =+B29&"/"&C29&"/"&D29&"/"&E29 -> /// | G29: =VLOOKUP($F29,$Q$101:$T$1500,3,0) -> 0 | H29: =+IFERROR(VLOOKUP($G29,$C$505:$O$1001,13,0),0) -> 0 | BQ29: SQL | EN29: ProgramManagerEIS
A30: =+A29+1 -> 25 | F30: =+B30&"/"&C30&"/"&D30&"/"&E30 -> /// | G30: =VLOOKUP($F30,$Q$101:$T$1500,3,0) -> 0 | H30: =+IFERROR(VLOOKUP($G30,$C$505:$O$1001,13,0),0) -> 0 | BQ30: LatentZero | EN30: ProjectManagerEAI
A31: =+A30+1 -> 26 | F31: =+B31&"/"&C31&"/"&D31&"/"&E31 -> /// | G31: =VLOOKUP($F31,$Q$101:$T$1500,3,0) -> 0 | H31: =+IFERROR(VLOOKUP($G31,$C$505:$O$1001,13,0),0) -> 0 | BQ31: DomainIT | EN31: TechnicalLeadEAI
A32: =+A31+1 -> 27 | F32: =+B32&"/"&C32&"/"&D32&"/"&E32 -> /// | G32: =VLOOKUP($F32,$Q$101:$T$1500,3,0) -> 0 | H32: =+IFERROR(VLOOKUP($G32,$C$505:$O$1001,13,0),0) -> 0 | BQ32: Varicent
A33: =+A32+1 -> 28 | F33: =+B33&"/"&C33&"/"&D33&"/"&E33 -> /// | G33: =VLOOKUP($F33,$Q$101:$T$1500,3,0) -> 0 | H33: =+IFERROR(VLOOKUP($G33,$C$505:$O$1001,13,0),0) -> 0
A34: =+A33+1 -> 29 | F34: =+B34&"/"&C34&"/"&D34&"/"&E34 -> /// | G34: =VLOOKUP($F34,$Q$101:$T$1500,3,0) -> 0 | H34: =+IFERROR(VLOOKUP($G34,$C$505:$O$1001,13,0),0) -> 0
A35: =+A34+1 -> 30 | F35: =+B35&"/"&C35&"/"&D35&"/"&E35 -> /// | G35: =VLOOKUP($F35,$Q$101:$T$1500,3,0) -> 0 | H35: =+IFERROR(VLOOKUP($G35,$C$505:$O$1001,13,0),0) -> 0
A36: =+A35+1 -> 31 | F36: =+B36&"/"&C36&"/"&D36&"/"&E36 -> /// | G36: =VLOOKUP($F36,$Q$101:$T$1500,3,0) -> 0 | H36: =+IFERROR(VLOOKUP($G36,$C$505:$O$1001,13,0),0) -> 0
A37: =+A36+1 -> 32 | F37: =+B37&"/"&C37&"/"&D37&"/"&E37 -> /// | G37: =VLOOKUP($F37,$Q$101:$T$1500,3,0) -> 0 | H37: =+IFERROR(VLOOKUP($G37,$C$505:$O$1001,13,0),0) -> 0 | L37: Web_Content_Management | M37: Web_Content_Management_TechnicalArchitect | N37: Web_Content_Management_TechnicalLead | O37: Web_Content_Management_Developer | P37: Document_Management | Q37: Document_Management_TechnicalArchitect | R37: Document_Management_TechnicalLead | S37: Document_Management_Developer | T37: Customer_Communication_Management | U37: Customer_Communication_Management_TechnicalArchitect | V37: Customer_Communication_Management_TechnicalLead | W37: Customer_Communication_Management_Developer | X37: Imaging_and_Scanning | Y37: Imaging_and_Scanning_TechnicalArchitect | Z37: Imaging_and_Scanning_TechnicalLead | AA37: Imaging_and_Scanning_Developer | AB37: Collaboration | AC37: Collaboration_TechnicalArchitect | AD37: Collaboration_TechnicalLead | AE37: Collaboration_Developer
A38: =+A37+1 -> 33 | F38: =+B38&"/"&C38&"/"&D38&"/"&E38 -> /// | G38: =VLOOKUP($F38,$Q$101:$T$1500,3,0) -> 0 | H38: =+IFERROR(VLOOKUP($G38,$C$505:$O$1001,13,0),0) -> 0 | L38: Web_Content_Management_TechnicalArchitect | M38: Junior | N38: Junior | O38: Senior | P38: Document_Management_TechnicalArchitect | Q38: Junior | R38: Junior | S38: Senior | T38: Customer_Communication_Management_TechnicalArchitect | U38: Junior | V38: Junior | W38: Senior | X38: Imaging_and_Scanning_TechnicalArchitect | Y38: Junior | Z38: Junior | AA38: Senior | AB38: Collaboration_TechnicalArchitect | AC38: Junior | AD38: Junior | AE38: Senior
A39: =+A38+1 -> 34 | F39: =+B39&"/"&C39&"/"&D39&"/"&E39 -> /// | G39: =VLOOKUP($F39,$Q$101:$T$1500,3,0) -> 0 | H39: =+IFERROR(VLOOKUP($G39,$C$505:$O$1001,13,0),0) -> 0 | L39: Web_Content_Management_TechnicalLead | M39: Senior | N39: Senior | O39: MidLevel | P39: Document_Management_TechnicalLead | Q39: Senior | R39: Senior | S39: MidLevel | T39: Customer_Communication_Management_TechnicalLead | U39: Senior | V39: Senior | W39: MidLevel | X39: Imaging_and_Scanning_TechnicalLead | Y39: Senior | Z39: Senior | AA39: MidLevel | AB39: Collaboration_TechnicalLead | AC39: Senior | AD39: Senior | AE39: MidLevel
A40: =+A39+1 -> 35 | F40: =+B40&"/"&C40&"/"&D40&"/"&E40 -> /// | G40: =VLOOKUP($F40,$Q$101:$T$1500,3,0) -> 0 | H40: =+IFERROR(VLOOKUP($G40,$C$505:$O$1001,13,0),0) -> 0 | L40: Web_Content_Management_Developer | M40: MidLevel | N40: MidLevel | P40: Document_Management_Developer | Q40: MidLevel | R40: MidLevel | T40: Customer_Communication_Management_Developer | U40: MidLevel | V40: MidLevel | X40: Imaging_and_Scanning_Developer | Y40: MidLevel | Z40: MidLevel | AB40: Collaboration_Developer | AC40: MidLevel | AD40: MidLevel
A41: =+A40+1 -> 36 | F41: =+B41&"/"&C41&"/"&D41&"/"&E41 -> /// | G41: =VLOOKUP($F41,$Q$101:$T$1500,3,0) -> 0 | H41: =+IFERROR(VLOOKUP($G41,$C$505:$O$1001,13,0),0) -> 0
A42: =+A41+1 -> 37 | F42: =+B42&"/"&C42&"/"&D42&"/"&E42 -> /// | G42: =VLOOKUP($F42,$Q$101:$T$1500,3,0) -> 0 | H42: =+IFERROR(VLOOKUP($G42,$C$505:$O$1001,13,0),0) -> 0
A43: =+A42+1 -> 38 | F43: =+B43&"/"&C43&"/"&D43&"/"&E43 -> /// | G43: =VLOOKUP($F43,$Q$101:$T$1500,3,0) -> 0 | H43: =+IFERROR(VLOOKUP($G43,$C$505:$O$1001,13,0),0) -> 0
A44: =+A43+1 -> 39 | F44: =+B44&"/"&C44&"/"&D44&"/"&E44 -> /// | G44: =VLOOKUP($F44,$Q$101:$T$1500,3,0) -> 0 | H44: =+IFERROR(VLOOKUP($G44,$C$505:$O$1001,13,0),0) -> 0
A45: =+A44+1 -> 40 | F45: =+B45&"/"&C45&"/"&D45&"/"&E45 -> /// | G45: =VLOOKUP($F45,$Q$101:$T$1500,3,0) -> 0 | H45: =+IFERROR(VLOOKUP($G45,$C$505:$O$1001,13,0),0) -> 0
A46: =+A45+1 -> 41 | F46: =+B46&"/"&C46&"/"&D46&"/"&E46 -> /// | G46: =VLOOKUP($F46,$Q$101:$T$1500,3,0) -> 0 | H46: =+IFERROR(VLOOKUP($G46,$C$505:$O$1001,13,0),0) -> 0
A47: =+A46+1 -> 42 | F47: =+B47&"/"&C47&"/"&D47&"/"&E47 -> /// | G47: =VLOOKUP($F47,$Q$101:$T$1500,3,0) -> 0 | H47: =+IFERROR(VLOOKUP($G47,$C$505:$O$1001,13,0),0) -> 0
A48: =+A47+1 -> 43 | F48: =+B48&"/"&C48&"/"&D48&"/"&E48 -> /// | G48: =VLOOKUP($F48,$Q$101:$T$1500,3,0) -> 0 | H48: =+IFERROR(VLOOKUP($G48,$C$505:$O$1001,13,0),0) -> 0
A49: =+A48+1 -> 44 | F49: =+B49&"/"&C49&"/"&D49&"/"&E49 -> /// | G49: =VLOOKUP($F49,$Q$101:$T$1500,3,0) -> 0 | H49: =+IFERROR(VLOOKUP($G49,$C$505:$O$1001,13,0),0) -> 0
A50: =+A49+1 -> 45 | F50: =+B50&"/"&C50&"/"&D50&"/"&E50 -> /// | G50: =VLOOKUP($F50,$Q$101:$T$1500,3,0) -> 0 | H50: =+IFERROR(VLOOKUP($G50,$C$505:$O$1001,13,0),0) -> 0
A51: =+A50+1 -> 46 | F51: =+B51&"/"&C51&"/"&D51&"/"&E51 -> /// | G51: =VLOOKUP($F51,$Q$101:$T$1500,3,0) -> 0 | H51: =+IFERROR(VLOOKUP($G51,$C$505:$O$1001,13,0),0) -> 0
A52: =+A51+1 -> 47 | F52: =+B52&"/"&C52&"/"&D52&"/"&E52 -> /// | G52: =VLOOKUP($F52,$Q$101:$T$1500,3,0) -> 0 | H52: =+IFERROR(VLOOKUP($G52,$C$505:$O$1001,13,0),0) -> 0
... A180: =+A179+1 -> 175 | F180: =+B180&"/"&C180&"/"&D180&"/"&E180 -> /// | G180: =VLOOKUP($F180,$Q$101:$T$1500,3,0) -> 0 | H180: =+IFERROR(VLOOKUP($G180,$C$505:$O$1001,13,0),0) -> 0
HT181: =SUM(HT6:HT26) -> 0 | HU181: =SUM(HU6:HU26) -> 0 | HV181: =SUM(HV6:HV26) -> 0 | HX181: =SUM(HX6:HX26) -> 0 | HY181: =SUM(HY6:HY26) -> 0 | HZ181: =SUM(HZ6:HZ26) -> 0
A503: SR.NO | B503: Ref.
C504: Role Code | D504: Category | E504: Practice | F504: Sub - Practice | G504: Role | H504: Skills | I504: Proficiency Level | J504: Years of Experience | K504: Band Grade Mapping 1 | L504: Band Grade Mapping 2 | M504: Band Grade Mapping 3 | N504: Skills Category | O504: Band & Grade | Q504: Combination of Band & Grade | S504: Role Code
A505: 1 | B505: Cloud_1 - Consulting/ConsultantCloud//Junior | C505: Cloud_1 | D505: =+[7]GRC!D3 -> Cloud | E505: Cloud | F505: Consulting | G505: ConsultantCloud | I505: Junior | J505: 9 - 12 | K505: B4 PM1 (9 to 12 yrs) | L505: None | M505: None | N505: Premium | O505: =+K505&" / " &L505 -> B4 PM1 (9 to 12 yrs) / None | Q505: =+E505&"/"&F505&"/"&G505&"/"&I505 -> Cloud/Consulting/ConsultantCloud/Junior | R505: =+O505 -> B4 PM1 (9 to 12 yrs) / None | S505: =+C505 -> Cloud_1 | T505: FALSE | U505: =+VLOOKUP($C505,[8]GRC!$B$3:$L$350,9,0) -> B4 PM1 (9 to 12 yrs) | V505: =+VLOOKUP($C505,[8]GRC!$B$3:$L$350,10,0) -> None | W505: =+U505=K505 -> TRUE | X505: =+V505=L505 -> TRUE
A506: 2 | B506: Cloud_11 - Consulting/ConsultantCloud//MidLevel | C506: Cloud_11 | D506: =+[7]GRC!D4 -> Cloud | E506: Cloud | F506: Consulting | G506: ConsultantCloud | I506: MidLevel | J506: 12 - 14 | K506: B4 PM2 (10 to 14 yrs) | L506: B4 PM3 (12 to 15 yrs) | M506: None | N506: Premium | O506: =+K506&" / " &L506 -> B4 PM2 (10 to 14 yrs) / B4 PM3 (12 to 15 yrs) | Q506: =+E506&"/"&F506&"/"&G506&"/"&I506 -> Cloud/Consulting/ConsultantCloud/MidLevel | R506: =+O506 -> B4 PM2 (10 to 14 yrs) / B4 PM3 (12 to 15 yrs) | S506: =+C506 -> Cloud_11 | T506: FALSE | U506: =+VLOOKUP($C506,[8]GRC!$B$3:$L$350,9,0) -> B4 PM2 (10 to 14 yrs) | V506: =+VLOOKUP($C506,[8]GRC!$B$3:$L$350,10,0) -> B4 PM3 (12 to 15 yrs) | W506: =+U506=K506 -> TRUE | X506: =+V506=L506 -> TRUE
A507: 3 | B507: Cloud_2 - Consulting/ConsultantCloud//Senior | C507: Cloud_2 | D507: =+[7]GRC!D5 -> Cloud | E507: Cloud | F507: Consulting | G507: ConsultantCloud | I507: Senior | J507: 14+ | K507: B4 PM3 (12 to 15 yrs) | L507: B5 (min 8 yrs) | M507: None | N507: Premium | O507: =+K507&" / " &L507 -> B4 PM3 (12 to 15 yrs) / B5 (min 8 yrs) | Q507: =+E507&"/"&F507&"/"&G507&"/"&I507 -> Cloud/Consulting/ConsultantCloud/Senior | R507: =+O507 -> B4 PM3 (12 to 15 yrs) / B5 (min 8 yrs) | S507: =+C507 -> Cloud_2 | T507: FALSE | U507: =+VLOOKUP($C507,[8]GRC!$B$3:$L$350,9,0) -> B4 PM3 (12 to 15 yrs) | V507: =+VLOOKUP($C507,[8]GRC!$B$3:$L$350,10,0) -> B5 (min 8 yrs) | W507: =+U507=K507 -> TRUE | X507: =+V507=L507 -> TRUE
A508: 4 | B508: Cloud_15 - PvtPubCloud/Administrator/Salesforce/ Azure/Junior | C508: Cloud_15 | D508: =+[7]GRC!D6 -> Cloud | E508: Cloud | F508: PvtPubCloud | G508: Administrator | H508: Salesforce/ Azure | I508: Junior | J508: 3 - 5 | K508: B2 AP3 (3 to 5 yrs) | L508: None | M508: None | N508: Premium | O508: =+K508&" / " &L508 -> B2 AP3 (3 to 5 yrs) / None | Q508: =+E508&"/"&F508&"/"&G508&"/"&I508 -> Cloud/PvtPubCloud/Administrator/Junior | R508: =+O508 -> B2 AP3 (3 to 5 yrs) / None | S508: =+C508 -> Cloud_15 | T508: FALSE | U508: =+VLOOKUP($C508,[8]GRC!$B$3:$L$350,9,0) -> B2 AP3 (3 to 5 yrs) | V508: =+VLOOKUP($C508,[8]GRC!$B$3:$L$350,10,0) -> None | W508: =+U508=K508 -> TRUE | X508: =+V508=L508 -> TRUE
A509: 5 | B509: Cloud_16 - PvtPubCloud/Administrator/Salesforce/ Azure/MidLevel | C509: Cloud_16 | D509: =+[7]GRC!D7 -> Cloud | E509: Cloud | F509: PvtPubCloud | G509: Administrator | H509: Salesforce/ Azure | I509: MidLevel | J509: 5 - 7 | K509: B3 PL1 (5 to 7 yrs) | L509: B3 PL2 (6 to 8 yrs) | M509: None | N509: Premium | O509: =+K509&" / " &L509 -> B3 PL1 (5 to 7 yrs) / B3 PL2 (6 to 8 yrs) | Q509: =+E509&"/"&F509&"/"&G509&"/"&I509 -> Cloud/PvtPubCloud/Administrator/MidLevel | R509: =+O509 -> B3 PL1 (5 to 7 yrs) / B3 PL2 (6 to 8 yrs) | S509: =+C509 -> Cloud_16 | T509: FALSE | U509: =+VLOOKUP($C509,[8]GRC!$B$3:$L$350,9,0) -> B3 PL1 (5 to 7 yrs) | V509: =+VLOOKUP($C509,[8]GRC!$B$3:$L$350,10,0) -> B3 PL2 (6 to 8 yrs) | W509: =+U509=K509 -> TRUE | X509: =+V509=L509 -> TRUE
A510: 6 | B510: Cloud_17 - PvtPubCloud/Administrator/Salesforce/ Azure/Senior | C510: Cloud_17 | D510: =+[7]GRC!D8 -> Cloud | E510: Cloud | F510: PvtPubCloud | G510: Administrator | H510: Salesforce/ Azure | I510: Senior | J510: 7 - 9 | K510: B3 PL2 (6 to 8 yrs) | L510: B3 PL3 (7 to 10 yrs) | M510: None | N510: Premium | O510: =+K510&" / " &L510 -> B3 PL2 (6 to 8 yrs) / B3 PL3 (7 to 10 yrs) | Q510: =+E510&"/"&F510&"/"&G510&"/"&I510 -> Cloud/PvtPubCloud/Administrator/Senior | R510: =+O510 -> B3 PL2 (6 to 8 yrs) / B3 PL3 (7 to 10 yrs) | S510: =+C510 -> Cloud_17 | T510: FALSE | U510: =+VLOOKUP($C510,[8]GRC!$B$3:$L$350,9,0) -> B3 PL2 (6 to 8 yrs) | V510: =+VLOOKUP($C510,[8]GRC!$B$3:$L$350,10,0) -> B3 PL3 (7 to 10 yrs) | W510: =+U510=K510 -> TRUE | X510: =+V510=L510 -> TRUE
A511: 7 | B511: Cloud_4 - PvtPubCloud/Architect/Salesforce/ Azure/Junior | C511: Cloud_4 | D511: =+[7]GRC!D9 -> Cloud | E511: Cloud | F511: PvtPubCloud | G511: Architect | H511: Salesforce/ Azure | I511: Junior | J511: 9 - 12 | K511: B4 PM1 (9 to 12 yrs) | L511: None | M511: None | N511: Premium | O511: =+K511&" / " &L511 -> B4 PM1 (9 to 12 yrs) / None | Q511: =+E511&"/"&F511&"/"&G511&"/"&I511 -> Cloud/PvtPubCloud/Architect/Junior | R511: =+O511 -> B4 PM1 (9 to 12 yrs) / None | S511: =+C511 -> Cloud_4 | T511: FALSE | U511: =+VLOOKUP($C511,[8]GRC!$B$3:$L$350,9,0) -> B4 PM1 (9 to 12 yrs) | V511: =+VLOOKUP($C511,[8]GRC!$B$3:$L$350,10,0) -> None | W511: =+U511=K511 -> TRUE | X511: =+V511=L511 -> TRUE
A512: 8 | B512: Cloud_12 - PvtPubCloud/Architect/Salesforce/ Azure/MidLevel | C512: Cloud_12 | D512: =+[7]GRC!D10 -> Cloud | E512: Cloud | F512: PvtPubCloud | G512: Architect | H512: Salesforce/ Azure | I512: MidLevel | J512: 12 - 14 | K512: B4 PM2 (10 to 14 yrs) | L512: B4 PM3 (12 to 15 yrs) | M512: None | N512: Premium | O512: =+K512&" / " &L512 -> B4 PM2 (10 to 14 yrs) / B4 PM3 (12 to 15 yrs) | Q512: =+E512&"/"&F512&"/"&G512&"/"&I512 -> Cloud/PvtPubCloud/Architect/MidLevel | R512: =+O512 -> B4 PM2 (10 to 14 yrs) / B4 PM3 (12 to 15 yrs) | S512: =+C512 -> Cloud_12 | T512: FALSE | U512: =+VLOOKUP($C512,[8]GRC!$B$3:$L$350,9,0) -> B4 PM2 (10 to 14 yrs) | V512: =+VLOOKUP($C512,[8]GRC!$B$3:$L$350,10,0) -> B4 PM3 (12 to 15 yrs) | W512: =+U512=K512 -> TRUE | X512: =+V512=L512 -> TRUE
A513: 9 | B513: Cloud_5 - PvtPubCloud/Architect/Salesforce/ Azure/Senior | C513: Cloud_5 | D513: =+[7]GRC!D11 -> Cloud | E513: Cloud | F513: PvtPubCloud | G513: Architect | H513: Salesforce/ Azure | I513: Senior | J513: 14+ | K513: B4 PM3 (12 to 15 yrs) | L513: B5 (min 8 yrs) | M513: None | N513: Premium | O513: =+K513&" / " &L513 -> B4 PM3 (12 to 15 yrs) / B5 (min 8 yrs) | Q513: =+E513&"/"&F513&"/"&G513&"/"&I513 -> Cloud/PvtPubCloud/Architect/Senior | R513: =+O513 -> B4 PM3 (12 to 15 yrs) / B5 (min 8 yrs) | S513: =+C513 -> Cloud_5 | T513: FALSE | U513: =+VLOOKUP($C513,[8]GRC!$B$3:$L$350,9,0) -> B4 PM3 (12 to 15 yrs) | V513: =+VLOOKUP($C513,[8]GRC!$B$3:$L$350,10,0) -> B5 (min 8 yrs) | W513: =+U513=K513 -> TRUE | X513: =+V513=L513 -> TRUE
A514: 10 | B514: Cloud_8 - PvtPubCloud/Developer/Salesforce/ Azure/Junior | C514: Cloud_8 | D514: =+[7]GRC!D12 -> Cloud | E514: Cloud | F514: PvtPubCloud | G514: Developer | H514: Salesforce/ Azure | I514: Junior | J514: 0 - 3 | K514: B2 AP1 | L514: B2 AP2 (0.6 to 3 yrs) | M514: None | N514: Premium | O514: =+K514&" / " &L514 -> B2 AP1 / B2 AP2 (0.6 to 3 yrs) | Q514: =+E514&"/"&F514&"/"&G514&"/"&I514 -> Cloud/PvtPubCloud/Developer/Junior | R514: =+O514 -> B2 AP1 / B2 AP2 (0.6 to 3 yrs) | S514: =+C514 -> Cloud_8 | T514: FALSE | U514: =+VLOOKUP($C514,[8]GRC!$B$3:$L$350,9,0) -> B2 AP1 | V514: =+VLOOKUP($C514,[8]GRC!$B$3:$L$350,10,0) -> B2 AP2 (0.6 to 3 yrs) | W514: =+U514=K514 -> TRUE | X514: =+V514=L514 -> TRUE
A515: 11 | B515: Cloud_9 - PvtPubCloud/Developer/Salesforce/ Azure/MidLevel | C515: Cloud_9 | D515: =+[7]GRC!D13 -> Cloud | E515: Cloud | F515: PvtPubCloud | G515: Developer | H515: Salesforce/ Azure | I515: MidLevel | J515: 3 - 5 | K515: B2 AP2 (0.6 to 3 yrs) | L515: B2 AP3 (3 to 5 yrs) | M515: None | N515: Premium | O515: =+K515&" / " &L515 -> B2 AP2 (0.6 to 3 yrs) / B2 AP3 (3 to 5 yrs) | Q515: =+E515&"/"&F515&"/"&G515&"/"&I515 -> Cloud/PvtPubCloud/Developer/MidLevel | R515: =+O515 -> B2 AP2 (0.6 to 3 yrs) / B2 AP3 (3 to 5 yrs) | S515: =+C515 -> Cloud_9 | T515: FALSE | U515: =+VLOOKUP($C515,[8]GRC!$B$3:$L$350,9,0) -> B2 AP2 (0.6 to 3 yrs) | V515: =+VLOOKUP($C515,[8]GRC!$B$3:$L$350,10,0) -> B2 AP3 (3 to 5 yrs) | W515: =+U515=K515 -> TRUE | X515: =+V515=L515 -> TRUE
A516: 12 | B516: Cloud_10 - PvtPubCloud/Developer/Salesforce/ Azure/Senior | C516: Cloud_10 | D516: =+[7]GRC!D14 -> Cloud | E516: Cloud | F516: PvtPubCloud | G516: Developer | H516: Salesforce/ Azure | I516: Senior | J516: 5 - 7 | K516: B2 AP3 (3 to 5 yrs) | L516: B3 PL1 (5 to 7 yrs) | M516: None | N516: Premium | O516: =+K516&" / " &L516 -> B2 AP3 (3 to 5 yrs) / B3 PL1 (5 to 7 yrs) | Q516: =+E516&"/"&F516&"/"&G516&"/"&I516 -> Cloud/PvtPubCloud/Developer/Senior | R516: =+O516 -> B2 AP3 (3 to 5 yrs) / B3 PL1 (5 to 7 yrs) | S516: =+C516 -> Cloud_10 | T516: FALSE | U516: =+VLOOKUP($C516,[8]GRC!$B$3:$L$350,9,0) -> B2 AP3 (3 to 5 yrs) | V516: =+VLOOKUP($C516,[8]GRC!$B$3:$L$350,10,0) -> B3 PL1 (5 to 7 yrs) | W516: =+U516=K516 -> TRUE | X516: =+V516=L516 -> TRUE
A517: 13 | B517: Cloud_13 - PvtPubCloud/TechnicalLead/Salesforce/ Azure/Junior | C517: Cloud_13 | D517: =+[7]GRC!D15 -> Cloud | E517: Cloud | F517: PvtPubCloud | G517: TechnicalLead | H517: Salesforce/ Azure | I517: Junior | J517: 5 - 7 | K517: B3 PL1 (5 to 7 yrs) | L517: B3 PL2 (6 to 8 yrs) | M517: None | N517: Premium | O517: =+K517&" / " &L517 -> B3 PL1 (5 to 7 yrs) / B3 PL2 (6 to 8 yrs) | Q517: =+E517&"/"&F517&"/"&G517&"/"&I517 -> Cloud/PvtPubCloud/TechnicalLead/Junior | R517: =+O517 -> B3 PL1 (5 to 7 yrs) / B3 PL2 (6 to 8 yrs) | S517: =+C517 -> Cloud_13 | T517: FALSE | U517: =+VLOOKUP($C517,[8]GRC!$B$3:$L$350,9,0) -> B3 PL1 (5 to 7 yrs) | V517: =+VLOOKUP($C517,[8]GRC!$B$3:$L$350,10,0) -> B3 PL2 (6 to 8 yrs) | W517: =+U517=K517 -> TRUE | X517: =+V517=L517 -> TRUE
A518: 14 | B518: Cloud_14 - PvtPubCloud/TechnicalLead/Salesforce/ Azure/Senior | C518: Cloud_14 | D518: =+[7]GRC!D16 -> Cloud | E518: Cloud | F518: PvtPubCloud | G518: TechnicalLead | H518: Salesforce/ Azure | I518: Senior | J518: 7 - 9 | K518: B3 PL3 (7 to 10 yrs) | L518: None | M518: None | N518: Premium | O518: =+K518&" / " &L518 -> B3 PL3 (7 to 10 yrs) / None | Q518: =+E518&"/"&F518&"/"&G518&"/"&I518 -> Cloud/PvtPubCloud/TechnicalLead/Senior | R518: =+O518 -> B3 PL3 (7 to 10 yrs) / None | S518: =+C518 -> Cloud_14 | T518: FALSE | U518: =+VLOOKUP($C518,[8]GRC!$B$3:$L$350,9,0) -> B3 PL3 (7 to 10 yrs) | V518: =+VLOOKUP($C518,[8]GRC!$B$3:$L$350,10,0) -> None | W518: =+U518=K518 -> TRUE | X518: =+V518=L518 -> TRUE
A519: 15 | B519: ECM_1 - SharePoint/AdministratorSharepoint//Junior | C519: ECM_1 | D519: =+[7]GRC!D17 -> ECM | E519: ECM | F519: SharePoint | G519: AdministratorSharepoint | I519: Junior | J519: 3 - 5 | K519: B2 AP3 (3 to 5 yrs) | L519: None | M519: None | N519: Premium | O519: =+K519&" / " &L519 -> B2 AP3 (3 to 5 yrs) / None | Q519: =+E519&"/"&F519&"/"&G519&"/"&I519 -> ECM/SharePoint/AdministratorSharepoint/Junior | R519: =+O519 -> B2 AP3 (3 to 5 yrs) / None | S519: =+C519 -> ECM_1 | T519: FALSE | U519: =+VLOOKUP($C519,[8]GRC!$B$3:$L$350,9,0) -> B2 AP3 (3 to 5 yrs) | V519: =+VLOOKUP($C519,[8]GRC!$B$3:$L$350,10,0) -> None | W519: =+U519=K519 -> TRUE | X519: =+V519=L519 -> TRUE
A520: 16 | B520: ECM_20 - SharePoint/AdministratorSharepoint//MidLevel | C520: ECM_20 | D520: =+[7]GRC!D18 -> ECM | E520: ECM | F520: SharePoint | G520: AdministratorSharepoint | I520: MidLevel | J520: 5 - 7 | K520: B3 PL1 (5 to 7 yrs) | L520: B3 PL2 (6 to 8 yrs) | M520: None | N520: Premium | O520: =+K520&" / " &L520 -> B3 PL1 (5 to 7 yrs) / B3 PL2 (6 to 8 yrs) | Q520: =+E520&"/"&F520&"/"&G520&"/"&I520 -> ECM/SharePoint/AdministratorSharepoint/MidLevel | R520: =+O520 -> B3 PL1 (5 to 7 yrs) / B3 PL2 (6 to 8 yrs) | S520: =+C520 -> ECM_20 | T520: FALSE | U520: =+VLOOKUP($C520,[8]GRC!$B$3:$L$350,9,0) -> B3 PL1 (5 to 7 yrs) | V520: =+VLOOKUP($C520,[8]GRC!$B$3:$L$350,10,0) -> B3 PL2 (6 to 8 yrs) | W520: =+U520=K520 -> TRUE | X520: =+V520=L520 -> TRUE
A521: 17 | B521: ECM_2 - SharePoint/AdministratorSharepoint//Senior | C521: ECM_2 | D521: =+[7]GRC!D19 -> ECM | E521: ECM | F521: SharePoint | G521: AdministratorSharepoint | I521: Senior | J521: 7 - 9 | K521: B3 PL2 (6 to 8 yrs) | L521: B3 PL3 (7 to 10 yrs) | M521: None | N521: Premium | O521: =+K521&" / " &L521 -> B3 PL2 (6 to 8 yrs) / B3 PL3 (7 to 10 yrs) | Q521: =+E521&"/"&F521&"/"&G521&"/"&I521 -> ECM/SharePoint/AdministratorSharepoint/Senior | R521: =+O521 -> B3 PL2 (6 to 8 yrs) / B3 PL3 (7 to 10 yrs) | S521: =+C521 -> ECM_2 | T521: FALSE | U521: =+VLOOKUP($C521,[8]GRC!$B$3:$L$350,9,0) -> B3 PL2 (6 to 8 yrs) | V521: =+VLOOKUP($C521,[8]GRC!$B$3:$L$350,10,0) -> B3 PL3 (7 to 10 yrs) | W521: =+U521=K521 -> TRUE | X521: =+V521=L521 -> TRUE
A522: 18 | B522: ECM_3 - SharePoint/ArchitectSharepoint//Junior | C522: ECM_3 | D522: =+[7]GRC!D20 -> ECM | E522: ECM | F522: SharePoint | G522: ArchitectSharepoint | I522: Junior | J522: 9 - 12 | K522: B4 PM1 (9 to 12 yrs) | L522: None | M522: None | N522: Premium | O522: =+K522&" / " &L522 -> B4 PM1 (9 to 12 yrs) / None | Q522: =+E522&"/"&F522&"/"&G522&"/"&I522 -> ECM/SharePoint/ArchitectSharepoint/Junior | R522: =+O522 -> B4 PM1 (9 to 12 yrs) / None | S522: =+C522 -> ECM_3 | T522: FALSE | U522: =+VLOOKUP($C522,[8]GRC!$B$3:$L$350,9,0) -> B4 PM1 (9 to 12 yrs) | V522: =+VLOOKUP($C522,[8]GRC!$B$3:$L$350,10,0) -> None | W522: =+U522=K522 -> TRUE | X522: =+V522=L522 -> TRUE
A523: 19 | B523: ECM_4 - SharePoint/ArchitectSharepoint//MidLevel | C523: ECM_4 | D523: =+[7]GRC!D21 -> ECM | E523: ECM | F523: SharePoint | G523: ArchitectSharepoint | I523: MidLevel | J523: 12 - 14 | K523: B4 PM2 (10 to 14 yrs) | L523: B4 PM3 (12 to 15 yrs) | M523: None | N523: Premium | O523: =+K523&" / " &L523 -> B4 PM2 (10 to 14 yrs) / B4 PM3 (12 to 15 yrs) | Q523: =+E523&"/"&F523&"/"&G523&"/"&I523 -> ECM/SharePoint/ArchitectSharepoint/MidLevel | R523: =+O523 -> B4 PM2 (10 to 14 yrs) / B4 PM3 (12 to 15 yrs) | S523: =+C523 -> ECM_4 | T523: FALSE | U523: =+VLOOKUP($C523,[8]GRC!$B$3:$L$350,9,0) -> B4 PM2 (10 to 14 yrs) | V523: =+VLOOKUP($C523,[8]GRC!$B$3:$L$350,10,0) -> B4 PM3 (12 to 15 yrs) | W523: =+U523=K523 -> TRUE | X523: =+V523=L523 -> TRUE
A524: 20 | B524: ECM_5 - SharePoint/ArchitectSharepoint//Senior | C524: ECM_5 | D524: =+[7]GRC!D22 -> ECM | E524: ECM | F524: SharePoint | G524: ArchitectSharepoint | I524: Senior | J524: 14+ | K524: B4 PM3 (12 to 15 yrs) | L524: B5 (min 8 yrs) | M524: None | N524: Premium | O524: =+K524&" / " &L524 -> B4 PM3 (12 to 15 yrs) / B5 (min 8 yrs) | Q524: =+E524&"/"&F524&"/"&G524&"/"&I524 -> ECM/SharePoint/ArchitectSharepoint/Senior | R524: =+O524 -> B4 PM3 (12 to 15 yrs) / B5 (min 8 yrs) | S524: =+C524 -> ECM_5 | T524: FALSE | U524: =+VLOOKUP($C524,[8]GRC!$B$3:$L$350,9,0) -> B4 PM3 (12 to 15 yrs) | V524: =+VLOOKUP($C524,[8]GRC!$B$3:$L$350,10,0) -> B5 (min 8 yrs) | W524: =+U524=K524 -> TRUE | X524: =+V524=L524 -> TRUE
A525: 21 | B525: ECM_7 - SharePoint/DeveloperSharepoint//Junior | C525: ECM_7 | D525: =+[7]GRC!D23 -> ECM | E525: ECM | F525: SharePoint | G525: DeveloperSharepoint | I525: Junior | J525: 0 - 3 | K525: B2 AP1 | L525: B2 AP2 (0.6 to 3 yrs) | M525: None | N525: Premium | O525: =+K525&" / " &L525 -> B2 AP1 / B2 AP2 (0.6 to 3 yrs) | Q525: =+E525&"/"&F525&"/"&G525&"/"&I525 -> ECM/SharePoint/DeveloperSharepoint/Junior | R525: =+O525 -> B2 AP1 / B2 AP2 (0.6 to 3 yrs) | S525: =+C525 -> ECM_7 | T525: FALSE | U525: =+VLOOKUP($C525,[8]GRC!$B$3:$L$350,9,0) -> B2 AP1 | V525: =+VLOOKUP($C525,[8]GRC!$B$3:$L$350,10,0) -> B2 AP2 (0.6 to 3 yrs) | W525: =+U525=K525 -> TRUE | X525: =+V525=L525 -> TRUE
A526: 22 | B526: ECM_8 - SharePoint/DeveloperSharepoint//MidLevel | C526: ECM_8 | D526: =+[7]GRC!D24 -> ECM | E526: ECM | F526: SharePoint | G526: DeveloperSharepoint | I526: MidLevel | J526: 3 - 5 | K526: B2 AP2 (0.6 to 3 yrs) | L526: B2 AP3 (3 to 5 yrs) | M526: None | N526: Premium | O526: =+K526&" / " &L526 -> B2 AP2 (0.6 to 3 yrs) / B2 AP3 (3 to 5 yrs) | Q526: =+E526&"/"&F526&"/"&G526&"/"&I526 -> ECM/SharePoint/DeveloperSharepoint/MidLevel | R526: =+O526 -> B2 AP2 (0.6 to 3 yrs) / B2 AP3 (3 to 5 yrs) | S526: =+C526 -> ECM_8 | T526: FALSE | U526: =+VLOOKUP($C526,[8]GRC!$B$3:$L$350,9,0) -> B2 AP2 (0.6 to 3 yrs) | V526: =+VLOOKUP($C526,[8]GRC!$B$3:$L$350,10,0) -> B2 AP3 (3 to 5 yrs) | W526: =+U526=K526 -> TRUE | X526: =+V526=L526 -> TRUE
A527: 23 | B527: ECM_9 - SharePoint/DeveloperSharepoint//Senior | C527: ECM_9 | D527: =+[7]GRC!D25 -> ECM | E527: ECM | F527: SharePoint | G527: DeveloperSharepoint | I527: Senior | J527: 5 - 7 | K527: B2 AP3 (3 to 5 yrs) | L527: B3 PL1 (5 to 7 yrs) | M527: None | N527: Premium | O527: =+K527&" / " &L527 -> B2 AP3 (3 to 5 yrs) / B3 PL1 (5 to 7 yrs) | Q527: =+E527&"/"&F527&"/"&G527&"/"&I527 -> ECM/SharePoint/DeveloperSharepoint/Senior | R527: =+O527 -> B2 AP3 (3 to 5 yrs) / B3 PL1 (5 to 7 yrs) | S527: =+C527 -> ECM_9 | T527: FALSE | U527: =+VLOOKUP($C527,[8]GRC!$B$3:$L$350,9,0) -> B2 AP3 (3 to 5 yrs) | V527: =+VLOOKUP($C527,[8]GRC!$B$3:$L$350,10,0) -> B3 PL1 (5 to 7 yrs) | W527: =+U527=K527 -> TRUE | X527: =+V527=L527 -> TRUE
A528: 24 | B528: ECM_10 - SharePoint/TechnicalLeadSharepoint//Junior | C528: ECM_10 | D528: =+[7]GRC!D26 -> ECM | E528: ECM | F528: SharePoint | G528: TechnicalLeadSharepoint | I528: Junior | J528: 5 - 7 | K528: B3 PL1 (5 to 7 yrs) | L528: B3 PL2 (6 to 8 yrs) | M528: None | N528: Premium | O528: =+K528&" / " &L528 -> B3 PL1 (5 to 7 yrs) / B3 PL2 (6 to 8 yrs) | Q528: =+E528&"/"&F528&"/"&G528&"/"&I528 -> ECM/SharePoint/TechnicalLeadSharepoint/Junior | R528: =+O528 -> B3 PL1 (5 to 7 yrs) / B3 PL2 (6 to 8 yrs) | S528: =+C528 -> ECM_10 | T528: FALSE | U528: =+VLOOKUP($C528,[8]GRC!$B$3:$L$350,9,0) -> B3 PL1 (5 to 7 yrs) | V528: =+VLOOKUP($C528,[8]GRC!$B$3:$L$350,10,0) -> B3 PL2 (6 to 8 yrs) | W528: =+U528=K528 -> TRUE | X528: =+V528=L528 -> TRUE
A529: 25 | B529: ECM_12 - SharePoint/TechnicalLeadSharepoint//Senior | C529: ECM_12 | D529: =+[7]GRC!D27 -> ECM | E529: ECM | F529: SharePoint | G529: TechnicalLeadSharepoint | I529: Senior | J529: 7 - 9 | K529: B3 PL3 (7 to 10 yrs) | L529: None | M529: None | N529: Premium | O529: =+K529&" / " &L529 -> B3 PL3 (7 to 10 yrs) / None | Q529: =+E529&"/"&F529&"/"&G529&"/"&I529 -> ECM/SharePoint/TechnicalLeadSharepoint/Senior | R529: =+O529 -> B3 PL3 (7 to 10 yrs) / None | S529: =+C529 -> ECM_12 | T529: FALSE | U529: =+VLOOKUP($C529,[8]GRC!$B$3:$L$350,9,0) -> B3 PL3 (7 to 10 yrs) | V529: =+VLOOKUP($C529,[8]GRC!$B$3:$L$350,10,0) -> None | W529: =+U529=K529 -> TRUE | X529: =+V529=L529 -> TRUE
A530: 26 | B530: ECM_18 - SharePoint/TestLeadShaerpoint/Functional Testing/Junior | C530: ECM_18 | D530: =+[7]GRC!D28 -> ECM | E530: ECM | F530: SharePoint | G530: TestLeadShaerpoint | H530: Functional Testing | I530: Junior | J530: 5 - 7 | K530: B3 PL1 (5 to 7 yrs) | L530: B3 PL2 (6 to 8 yrs) | M530: None | N530: Premium | O530: =+K530&" / " &L530 -> B3 PL1 (5 to 7 yrs) / B3 PL2 (6 to 8 yrs) | Q530: =+E530&"/"&F530&"/"&G530&"/"&I530 -> ECM/SharePoint/TestLeadShaerpoint/Junior | R530: =+O530 -> B3 PL1 (5 to 7 yrs) / B3 PL2 (6 to 8 yrs) | S530: =+C530 -> ECM_18 | T530: FALSE | U530: =+VLOOKUP($C530,[8]GRC!$B$3:$L$350,9,0) -> B3 PL1 (5 to 7 yrs) | V530: =+VLOOKUP($C530,[8]GRC!$B$3:$L$350,10,0) -> B3 PL2 (6 to 8 yrs) | W530: =+U530=K530 -> TRUE | X530: =+V530=L530 -> TRUE
A531: 27 | B531: ECM_19 - SharePoint/TestLeadShaerpoint/Functional Testing/Senior | C531: ECM_19 | D531: =+[7]GRC!D29 -> ECM | E531: ECM | F531: SharePoint | G531: TestLeadShaerpoint | H531: Functional Testing | I531: Senior | J531: 7 - 9 | K531: B3 PL3 (7 to 10 yrs) | L531: None | M531: None | N531: Premium | O531: =+K531&" / " &L531 -> B3 PL3 (7 to 10 yrs) / None | Q531: =+E531&"/"&F531&"/"&G531&"/"&I531 -> ECM/SharePoint/TestLeadShaerpoint/Senior | R531: =+O531 -> B3 PL3 (7 to 10 yrs) / None | S531: =+C531 -> ECM_19 | T531: FALSE | U531: =+VLOOKUP($C531,[8]GRC!$B$3:$L$350,9,0) -> B3 PL3 (7 to 10 yrs) | V531: =+VLOOKUP($C531,[8]GRC!$B$3:$L$350,10,0) -> None | W531: =+U531=K531 -> TRUE | X531: =+V531=L531 -> TRUE
A532: 28 | B532: ECM_15 - SharePoint/TesterSharepoint/Functional Testing/Junior | C532: ECM_15 | D532: =+[7]GRC!D30 -> ECM | E532: ECM | F532: SharePoint | G532: TesterSharepoint | H532: Functional Testing | I532: Junior | J532: 0 - 3 | K532: B2 AP1 | L532: B2 AP2 (0.6 to 3 yrs) | M532: None | N532: Premium | O532: =+K532&" / " &L532 -> B2 AP1 / B2 AP2 (0.6 to 3 yrs) | Q532: =+E532&"/"&F532&"/"&G532&"/"&I532 -> ECM/SharePoint/TesterSharepoint/Junior | R532: =+O532 -> B2 AP1 / B2 AP2 (0.6 to 3 yrs) | S532: =+C532 -> ECM_15 | T532: FALSE | U532: =+VLOOKUP($C532,[8]GRC!$B$3:$L$350,9,0) -> B2 AP1 | V532: =+VLOOKUP($C532,[8]GRC!$B$3:$L$350,10,0) -> B2 AP2 (0.6 to 3 yrs) | W532: =+U532=K532 -> TRUE | X532: =+V532=L532 -> TRUE
A533: 29 | B533: ECM_17 - SharePoint/TesterSharepoint/Functional Testing/Senior | C533: ECM_17 | D533: =+[7]GRC!D31 -> ECM | E533: ECM | F533: SharePoint | G533: TesterSharepoint | H533: Functional Testing | I533: Senior | J533: 3 - 5 | K533: B2 AP2 (0.6 to 3 yrs) | L533: B2 AP3 (3 to 5 yrs) | M533: None | N533: Premium | O533: =+K533&" / " &L533 -> B2 AP2 (0.6 to 3 yrs) / B2 AP3 (3 to 5 yrs) | Q533: =+E533&"/"&F533&"/"&G533&"/"&I533 -> ECM/SharePoint/TesterSharepoint/Senior | R533: =+O533 -> B2 AP2 (0.6 to 3 yrs) / B2 AP3 (3 to 5 yrs) | S533: =+C533 -> ECM_17 | T533: FALSE | U533: =+VLOOKUP($C533,[8]GRC!$B$3:$L$350,9,0) -> B2 AP2 (0.6 to 3 yrs) | V533: =+VLOOKUP($C533,[8]GRC!$B$3:$L$350,10,0) -> B2 AP3 (3 to 5 yrs) | W533: =+U533=K533 -> TRUE | X533: =+V533=L533 -> TRUE
A534: 30 | B534: IMS_1 - ArchitectIMS/IMSArchitect/Servers/Storage/Ent Tools/Database/Network/Junior | C534: IMS_1 | D534: =+[7]GRC!D32 -> IMS | E534: IMS | F534: ArchitectIMS | G534: IMSArchitect | H534: Servers/Storage/Ent Tools/Database/Network | I534: Junior | J534: 9 - 12 | K534: B4 PM1 (9 to 12 yrs) | L534: None | M534: None | N534: Generic | O534: =+K534&" / " &L534 -> B4 PM1 (9 to 12 yrs) / None | Q534: =+E534&"/"&F534&"/"&G534&"/"&I534 -> IMS/ArchitectIMS/IMSArchitect/Junior | R534: =+O534 -> B4 PM1 (9 to 12 yrs) / None | S534: =+C534 -> IMS_1 | T534: FALSE | U534: =+VLOOKUP($C534,[8]GRC!$B$3:$L$350,9,0) -> B4 PM1 (9 to 12 yrs) | V534: =+VLOOKUP($C534,[8]GRC!$B$3:$L$350,10,0) -> None | W534: =+U534=K534 -> TRUE | X534: =+V534=L534 -> TRUE
A535: 31 | B535: IMS_2 - ArchitectIMS/IMSArchitect/Servers/Storage/Ent Tools/Database/Network/MidLevel | C535: IMS_2 | D535: =+[7]GRC!D33 -> IMS | E535: IMS | F535: ArchitectIMS | G535: IMSArchitect | H535: Servers/Storage/Ent Tools/Database/Network | I535: MidLevel | J535: 12 - 14 | K535: B4 PM2 (10 to 14 yrs) | L535: B4 PM3 (12 to 15 yrs) | M535: None | N535: Generic | O535: =+K535&" / " &L535 -> B4 PM2 (10 to 14 yrs) / B4 PM3 (12 to 15 yrs) | Q535: =+E535&"/"&F535&"/"&G535&"/"&I535 -> IMS/ArchitectIMS/IMSArchitect/MidLevel | R535: =+O535 -> B4 PM2 (10 to 14 yrs) / B4 PM3 (12 to 15 yrs) | S535: =+C535 -> IMS_2 | T535: FALSE | U535: =+VLOOKUP($C535,[8]GRC!$B$3:$L$350,9,0) -> B4 PM2 (10 to 14 yrs) | V535: =+VLOOKUP($C535,[8]GRC!$B$3:$L$350,10,0) -> B4 PM3 (12 to 15 yrs) | W535: =+U535=K535 -> TRUE | X535: =+V535=L535 -> TRUE
A536: 32 | B536: IMS_3 - ArchitectIMS/IMSArchitect/Servers/Storage/Ent Tools/Database/Network/Senior | C536: IMS_3 | D536: =+[7]GRC!D34 -> IMS | E536: IMS | F536: ArchitectIMS | G536: IMSArchitect | H536: Servers/Storage/Ent Tools/Database/Network | I536: Senior | J536: 14+ | K536: B4 PM3 (12 to 15 yrs) | L536: B5 (min 8 yrs) | M536: None | N536: Generic | O536: =+K536&" / " &L536 -> B4 PM3 (12 to 15 yrs) / B5 (min 8 yrs) | Q536: =+E536&"/"&F536&"/"&G536&"/"&I536 -> IMS/ArchitectIMS/IMSArchitect/Senior | R536: =+O536 -> B4 PM3 (12 to 15 yrs) / B5 (min 8 yrs) | S536: =+C536 -> IMS_3 | T536: FALSE | U536: =+VLOOKUP($C536,[8]GRC!$B$3:$L$350,9,0) -> B4 PM3 (12 to 15 yrs) | V536: =+VLOOKUP($C536,[8]GRC!$B$3:$L$350,10,0) -> B5 (min 8 yrs) | W536: =+U536=K536 -> TRUE | X536: =+V536=L536 -> TRUE
A537: 33 | B537: IMS_4 - BuildandReleaseManagement/BuildManager//Junior | C537: IMS_4 | D537: =+[7]GRC!D35 -> IMS | E537: IMS | F537: BuildandReleaseManagement | G537: BuildManager | I537: Junior | J537: 3 - 5 | K537: B2 AP3 (3 to 5 yrs) | L537: None | M537: None | N537: Premium | O537: =+K537&" / " &L537 -> B2 AP3 (3 to 5 yrs) / None | Q537: =+E537&"/"&F537&"/"&G537&"/"&I537 -> IMS/BuildandReleaseManagement/BuildManager/Junior | R537: =+O537 -> B2 AP3 (3 to 5 yrs) / None | S537: =+C537 -> IMS_4 | T537: FALSE | U537: =+VLOOKUP($C537,[8]GRC!$B$3:$L$350,9,0) -> B2 AP3 (3 to 5 yrs) | V537: =+VLOOKUP($C537,[8]GRC!$B$3:$L$350,10,0) -> None | W537: =+U537=K537 -> TRUE | X537: =+V537=L537 -> TRUE
A538: 34 | B538: IMS_5 - BuildandReleaseManagement/BuildManager//MidLevel | C538: IMS_5 | D538: =+[7]GRC!D36 -> IMS | E538: IMS | F538: BuildandReleaseManagement | G538: BuildManager | I538: MidLevel | J538: 5 - 7 | K538: B3 PL1 (5 to 7 yrs) | L538: B3 PL2 (6 to 8 yrs) | M538: None | N538: Premium | O538: =+K538&" / " &L538 -> B3 PL1 (5 to 7 yrs) / B3 PL2 (6 to 8 yrs) | Q538: =+E538&"/"&F538&"/"&G538&"/"&I538 -> IMS/BuildandReleaseManagement/BuildManager/MidLevel | R538: =+O538 -> B3 PL1 (5 to 7 yrs) / B3 PL2 (6 to 8 yrs) | S538: =+C538 -> IMS_5 | T538: FALSE | U538: =+VLOOKUP($C538,[8]GRC!$B$3:$L$350,9,0) -> B3 PL1 (5 to 7 yrs) | V538: =+VLOOKUP($C538,[8]GRC!$B$3:$L$350,10,0) -> B3 PL2 (6 to 8 yrs) | W538: =+U538=K538 -> TRUE | X538: =+V538=L538 -> TRUE
A539: 35 | B539: IMS_6 - BuildandReleaseManagement/BuildManager//Senior | C539: IMS_6 | D539: =+[7]GRC!D37 -> IMS | E539: IMS | F539: BuildandReleaseManagement | G539: BuildManager | I539: Senior | J539: 7 - 9 | K539: B3 PL2 (6 to 8 yrs) | L539: B3 PL3 (7 to 10 yrs) | M539: None | N539: Premium | O539: =+K539&" / " &L539 -> B3 PL2 (6 to 8 yrs) / B3 PL3 (7 to 10 yrs) | Q539: =+E539&"/"&F539&"/"&G539&"/"&I539 -> IMS/BuildandReleaseManagement/BuildManager/Senior | R539: =+O539 -> B3 PL2 (6 to 8 yrs) / B3 PL3 (7 to 10 yrs) | S539: =+C539 -> IMS_6 | T539: FALSE | U539: =+VLOOKUP($C539,[8]GRC!$B$3:$L$350,9,0) -> B3 PL2 (6 to 8 yrs) | V539: =+VLOOKUP($C539,[8]GRC!$B$3:$L$350,10,0) -> B3 PL3 (7 to 10 yrs) | W539: =+U539=K539 -> TRUE | X539: =+V539=L539 -> TRUE
A540: 36 | B540: IMS_7 - DataCentre/DataCenterOperations //Junior | C540: IMS_7 | D540: =+[7]GRC!D38 -> IMS-Basic | E540: IMSBASIC | F540: DataCentre | G540: DataCenterOperations | I540: Junior | J540: 0 - 3 | K540: B2 AP1 | L540: B2 AP2 (0.6 to 3 yrs) | M540: None | N540: Generic | O540: =+K540&" / " &L540 -> B2 AP1 / B2 AP2 (0.6 to 3 yrs) | Q540: =+E540&"/"&F540&"/"&G540&"/"&I540 -> IMSBASIC/DataCentre/DataCenterOperations /Junior | R540: =+O540 -> B2 AP1 / B2 AP2 (0.6 to 3 yrs) | S540: =+C540 -> IMS_7 | T540: FALSE | U540: =+VLOOKUP($C540,[8]GRC!$B$3:$L$350,9,0) -> B2 AP1 | V540: =+VLOOKUP($C540,[8]GRC!$B$3:$L$350,10,0) -> B2 AP2 (0.6 to 3 yrs) | W540: =+U540=K540 -> TRUE | X540: =+V540=L540 -> TRUE
A541: 37 | B541: IMS_8 - DataCentre/DataCenterOperations //MidLevel | C541: IMS_8 | D541: =+[7]GRC!D39 -> IMS-Basic | E541: IMSBASIC | F541: DataCentre | G541: DataCenterOperations | I541: MidLevel | J541: 3 - 5 | K541: B2 AP2 (0.6 to 3 yrs) | L541: B2 AP3 (3 to 5 yrs) | M541: None | N541: Generic | O541: =+K541&" / " &L541 -> B2 AP2 (0.6 to 3 yrs) / B2 AP3 (3 to 5 yrs) | Q541: =+E541&"/"&F541&"/"&G541&"/"&I541 -> IMSBASIC/DataCentre/DataCenterOperations /MidLevel | R541: =+O541 -> B2 AP2 (0.6 to 3 yrs) / B2 AP3 (3 to 5 yrs) | S541: =+C541 -> IMS_8 | T541: FALSE | U541: =+VLOOKUP($C541,[8]GRC!$B$3:$L$350,9,0) -> B2 AP2 (0.6 to 3 yrs) | V541: =+VLOOKUP($C541,[8]GRC!$B$3:$L$350,10,0) -> B2 AP3 (3 to 5 yrs) | W541: =+U541=K541 -> TRUE | X541: =+V541=L541 -> TRUE
A542: 38 | B542: IMS_9 - DataCentre/DataCenterOperations //Senior | C542: IMS_9 | D542: =+[7]GRC!D40 -> IMS-Basic | E542: IMSBASIC | F542: DataCentre | G542: DataCenterOperations | I542: Senior | J542: 5 - 7 | K542: B2 AP3 (3 to 5 yrs) | L542: B3 PL1 (5 to 7 yrs) | M542: None | N542: Generic | O542: =+K542&" / " &L542 -> B2 AP3 (3 to 5 yrs) / B3 PL1 (5 to 7 yrs) | Q542: =+E542&"/"&F542&"/"&G542&"/"&I542 -> IMSBASIC/DataCentre/DataCenterOperations /Senior | R542: =+O542 -> B2 AP3 (3 to 5 yrs) / B3 PL1 (5 to 7 yrs) | S542: =+C542 -> IMS_9 | T542: FALSE | U542: =+VLOOKUP($C542,[8]GRC!$B$3:$L$350,9,0) -> B2 AP3 (3 to 5 yrs) | V542: =+VLOOKUP($C542,[8]GRC!$B$3:$L$350,10,0) -> B3 PL1 (5 to 7 yrs) | W542: =+U542=K542 -> TRUE | X542: =+V542=L542 -> TRUE
A543: 39 | B543: IMS_10 - Desktop/DesktopEngineer/PC Support / Patch / Desk side/Junior | C543: IMS_10 | D543: =+[7]GRC!D41 -> IMS-Basic | E543: IMSBASIC | F543: Desktop | G543: DesktopEngineer | H543: PC Support / Patch / Desk side | I543: Junior | J543: 0 - 3 | K543: B2 AP1 | L543: B2 AP2 (0.6 to 3 yrs) | M543: None | N543: Generic | O543: =+K543&" / " &L543 -> B2 AP1 / B2 AP2 (0.6 to 3 yrs) | Q543: =+E543&"/"&F543&"/"&G543&"/"&I543 -> IMSBASIC/Desktop/DesktopEngineer/Junior | R543: =+O543 -> B2 AP1 / B2 AP2 (0.6 to 3 yrs) | S543: =+C543 -> IMS_10 | T543: FALSE | U543: =+VLOOKUP($C543,[8]GRC!$B$3:$L$350,9,0) -> B2 AP1 | V543: =+VLOOKUP($C543,[8]GRC!$B$3:$L$350,10,0) -> B2 AP2 (0.6 to 3 yrs) | W543: =+U543=K543 -> TRUE | X543: =+V543=L543 -> TRUE
A544: 40 | B544: IMS_11 - Desktop/DesktopEngineer/PC Support / Patch / Desk side/MidLevel | C544: IMS_11 | D544: =+[7]GRC!D42 -> IMS-Basic | E544: IMSBASIC | F544: Desktop | G544: DesktopEngineer | H544: PC Support / Patch / Desk side | I544: MidLevel | J544: 3 - 5 | K544: B2 AP2 (0.6 to 3 yrs) | L544: B2 AP3 (3 to 5 yrs) | M544: None | N544: Generic | O544: =+K544&" / " &L544 -> B2 AP2 (0.6 to 3 yrs) / B2 AP3 (3 to 5 yrs) | Q544: =+E544&"/"&F544&"/"&G544&"/"&I544 -> IMSBASIC/Desktop/DesktopEngineer/MidLevel | R544: =+O544 -> B2 AP2 (0.6 to 3 yrs) / B2 AP3 (3 to 5 yrs) | S544: =+C544 -> IMS_11 | T544: FALSE | U544: =+VLOOKUP($C544,[8]GRC!$B$3:$L$350,9,0) -> B2 AP2 (0.6 to 3 yrs) | V544: =+VLOOKUP($C544,[8]GRC!$B$3:$L$350,10,0) -> B2 AP3 (3 to 5 yrs) | W544: =+U544=K544 -> TRUE | X544: =+V544=L544 -> TRUE
A545: 41 | B545: IMS_12 - Desktop/DesktopEngineer/PC Support / Patch / Desk side/Senior | C545: IMS_12 | D545: =+[7]GRC!D43 -> IMS-Basic | E545: IMSBASIC | F545: Desktop | G545: DesktopEngineer | H545: PC Support / Patch / Desk side | I545: Senior | J545: 5 - 7 | K545: B2 AP3 (3 to 5 yrs) | L545: B3 PL1 (5 to 7 yrs) | M545: None | N545: Generic | O545: =+K545&" / " &L545 -> B2 AP3 (3 to 5 yrs) / B3 PL1 (5 to 7 yrs) | Q545: =+E545&"/"&F545&"/"&G545&"/"&I545 -> IMSBASIC/Desktop/DesktopEngineer/Senior | R545: =+O545 -> B2 AP3 (3 to 5 yrs) / B3 PL1 (5 to 7 yrs) | S545: =+C545 -> IMS_12 | T545: FALSE | U545: =+VLOOKUP($C545,[8]GRC!$B$3:$L$350,9,0) -> B2 AP3 (3 to 5 yrs) | V545: =+VLOOKUP($C545,[8]GRC!$B$3:$L$350,10,0) -> B3 PL1 (5 to 7 yrs) | W545: =+U545=K545 -> TRUE | X545: =+V545=L545 -> TRUE
A546: 42 | B546: IMS_13 - HelpDesk/HelpDeskAnalyst//Junior | C546: IMS_13 | D546: =+[7]GRC!D44 -> IMS-Basic | E546: IMSBASIC | F546: HelpDesk | G546: HelpDeskAnalyst | I546: Junior | J546: 0 - 3 | K546: B2 AP1 | L546: B2 AP2 (0.6 to 3 yrs) | M546: None | N546: Generic | O546: =+K546&" / " &L546 -> B2 AP1 / B2 AP2 (0.6 to 3 yrs) | Q546: =+E546&"/"&F546&"/"&G546&"/"&I546 -> IMSBASIC/HelpDesk/HelpDeskAnalyst/Junior | R546: =+O546 -> B2 AP1 / B2 AP2 (0.6 to 3 yrs) | S546: =+C546 -> IMS_13 | T546: FALSE | U546: =+VLOOKUP($C546,[8]GRC!$B$3:$L$350,9,0) -> B2 AP1 | V546: =+VLOOKUP($C546,[8]GRC!$B$3:$L$350,10,0) -> B2 AP2 (0.6 to 3 yrs) | W546: =+U546=K546 -> TRUE | X546: =+V546=L546 -> TRUE
A547: 43 | B547: IMS_14 - HelpDesk/HelpDeskAnalyst//Senior | C547: IMS_14 | D547: =+[7]GRC!D45 -> IMS-Basic | E547: IMSBASIC | F547: HelpDesk | G547: HelpDeskAnalyst | I547: Senior | J547: 3 - 5 | K547: B2 AP2 (0.6 to 3 yrs) | L547: B2 AP3 (3 to 5 yrs) | M547: None | N547: Generic | O547: =+K547&" / " &L547 -> B2 AP2 (0.6 to 3 yrs) / B2 AP3 (3 to 5 yrs) | Q547: =+E547&"/"&F547&"/"&G547&"/"&I547 -> IMSBASIC/HelpDesk/HelpDeskAnalyst/Senior | R547: =+O547 -> B2 AP2 (0.6 to 3 yrs) / B2 AP3 (3 to 5 yrs) | S547: =+C547 -> IMS_14 | T547: FALSE | U547: =+VLOOKUP($C547,[8]GRC!$B$3:$L$350,9,0) -> B2 AP2 (0.6 to 3 yrs) | V547: =+VLOOKUP($C547,[8]GRC!$B$3:$L$350,10,0) -> B2 AP3 (3 to 5 yrs) | W547: =+U547=K547 -> TRUE | X547: =+V547=L547 -> TRUE
A548: 44 | B548: IMS_15 - ITSM/ConsultantITSM//Junior | C548: IMS_15 | D548: =+[7]GRC!D46 -> IMS | E548: IMS | F548: ITSM | G548: ConsultantITSM | I548: Junior | J548: 9 - 12 | K548: B4 PM1 (9 to 12 yrs) | L548: None | M548: None | N548: Generic | O548: =+K548&" / " &L548 -> B4 PM1 (9 to 12 yrs) / None | Q548: =+E548&"/"&F548&"/"&G548&"/"&I548 -> IMS/ITSM/ConsultantITSM/Junior | R548: =+O548 -> B4 PM1 (9 to 12 yrs) / None | S548: =+C548 -> IMS_15 | T548: FALSE | U548: =+VLOOKUP($C548,[8]GRC!$B$3:$L$350,9,0) -> B4 PM1 (9 to 12 yrs) | V548: =+VLOOKUP($C548,[8]GRC!$B$3:$L$350,10,0) -> None | W548: =+U548=K548 -> TRUE | X548: =+V548=L548 -> TRUE
...

Sheet Staffing-Roles
A1: HeadA | C1: Skillbay/Contract Hires-Onsite
A2: SubHeadA | C2: STAFFING DETAILS
C3: Domestic | E3: =IF(CheckList!P18=46,DS32,"")
C4: Deputed | E4: =IF(CheckList!P18=46,(DS58+DS84+DS110),"") | F4: Jan | G4: Feb | H4: Mar | I4: Apr | J4: May | K4: Jun | L4: Jul | M4: Aug | N4: Sep | O4: Oct | P4: Nov | Q4: Dec | S4: Jan | T4: Feb | U4: Mar | V4: Apr | W4: May | X4: Jun | Y4: Jul | Z4: Aug | AA4: Sep | AB4: Oct | AC4: Nov | AD4: Dec | AF4: Jan | AG4: Feb | AH4: Mar | AI4: Apr | AJ4: May | AK4: Jun | AL4: Jul | AM4: Aug | AN4: Sep | AO4: Oct | AP4: Nov | AQ4: Dec | AS4: Jan | AT4: Feb | AU4: Mar | AV4: Apr | AW4: May | AX4: Jun | AY4: Jul | AZ4: Aug | BA4: Sep | BB4: Oct | BC4: Nov | BD4: Dec | BF4: Jan | BG4: Feb | BH4: Mar | BI4: Apr | BJ4: May | BK4: Jun | BL4: Jul | BM4: Aug | BN4: Sep | BO4: Oct | BP4: Nov | BQ4: Dec | BS4: Jan | BT4: Feb | BU4: Mar | BV4: Apr | BW4: May | BX4: Jun | BY4: Jul | BZ4: Aug | CA4: Sep | CB4: Oct | CC4: Nov | CD4: Dec | CF4: Jan | CG4: Feb | CH4: Mar | CI4: Apr | CJ4: May | CK4: Jun | CL4: Jul | CM4: Aug | CN4: Sep | CO4: Oct | CP4: Nov | CQ4: Dec | CS4: Jan | CT4: Feb | CU4: Mar | CV4: Apr | CW4: May | CX4: Jun | CY4: Jul | CZ4: Aug | DA4: Sep | DB4: Oct | DC4: Nov | DD4: Dec | DF4: Jan | DG4: Feb | DH4: Mar | DI4: Apr | DJ4: May | DK4: Jun | DL4: Jul | DM4: Aug | DN4: Sep | DO4: Oct | DP4: Nov | DQ4: Dec
C5: Offshore | E5: =IF(CheckList!P18=46,DS164,"") | F5: 2019 | G5: =F5 -> 2019 | H5: =G5 -> 2019 | I5: =H5 -> 2019 | J5: =I5 -> 2019 | K5: =J5 -> 2019 | L5: =K5 -> 2019 | M5: =L5 -> 2019 | N5: =M5 -> 2019 | ... R5: =Q5 -> 2019 | S5: =R5+1 -> 2020 | T5: =S5 -> 2020 | U5: =T5 -> 2020 | V5: =U5 -> 2020 | W5: =V5 -> 2020 | X5: =W5 -> 2020 | Y5: =X5 -> 2020 | Z5: =Y5 -> 2020 | AA5: =Z5 -> 2020 | ... AE5: =AD5 -> 2020 | AF5: =AE5+1 -> 2021 | AG5: =AF5 -> 2021 | AH5: =AG5 -> 2021 | AI5: =AH5 -> 2021 | AJ5: =AI5 -> 2021 | AK5: =AJ5 -> 2021 | AL5: =AK5 -> 2021 | AM5: =AL5 -> 2021 | AN5: =AM5 -> 2021 | ... AR5: =AQ5 -> 2021 | AS5: =AR5+1 -> 2022 | AT5: =AS5 -> 2022 | AU5: =AT5 -> 2022 | AV5: =AU5 -> 2022 | AW5: =AV5 -> 2022 | AX5: =AW5 -> 2022 | AY5: =AX5 -> 2022 | AZ5: =AY5 -> 2022 | BA5: =AZ5 -> 2022 | ... BE5: =BD5 -> 2022 | BF5: =BE5+1 -> 2023 | BG5: =BF5 -> 2023 | BH5: =BG5 -> 2023 | BI5: =BH5 -> 2023 | BJ5: =BI5 -> 2023 | BK5: =BJ5 -> 2023 | BL5: =BK5 -> 2023 | BM5: =BL5 -> 2023 | BN5: =BM5 -> 2023 | ... BR5: =BQ5 -> 2023 | BS5: =BR5+1 -> 2024 | BT5: =BS5 -> 2024 | BU5: =BT5 -> 2024 | BV5: =BU5 -> 2024 | BW5: =BV5 -> 2024 | BX5: =BW5 -> 2024 | BY5: =BX5 -> 2024 | BZ5: =BY5 -> 2024 | CA5: =BZ5 -> 2024 | ... CE5: =CD5 -> 2024 | CF5: =CE5+1 -> 2025 | CG5: =CF5 -> 2025 | CH5: =CG5 -> 2025 | CI5: =CH5 -> 2025 | CJ5: =CI5 -> 2025 | CK5: =CJ5 -> 2025 | CL5: =CK5 -> 2025 | CM5: =CL5 -> 2025 | CN5: =CM5 -> 2025 | ... CR5: =CQ5 -> 2025 | CS5: =CR5+1 -> 2026 | CT5: =CS5 -> 2026 | CU5: =CT5 -> 2026 | CV5: =CU5 -> 2026 | CW5: =CV5 -> 2026 | CX5: =CW5 -> 2026 | CY5: =CX5 -> 2026 | CZ5: =CY5 -> 2026 | DA5: =CZ5 -> 2026 | ... DE5: =DD5 -> 2026 | DF5: =DE5+1 -> 2027 | DG5: =DF5 -> 2027 | DH5: =DG5 -> 2027 | DI5: =DH5 -> 2027 | DJ5: =DI5 -> 2027 | DK5: =DJ5 -> 2027 | DL5: =DK5 -> 2027 | DM5: =DL5 -> 2027 | DN5: =DM5 -> 2027 | ... DR5: =DQ5 -> 2027 | DS5: Total | DT5: Total SOG
C6: Onsite - Local (Contractor)
C7: Skillbay/Contract Hires- | G7: =F7 -> 0 | H7: =G7 -> 0 | I7: =H7 -> 0 | J7: =I7 -> 0 | K7: =J7 -> 0 | L7: =K7 -> 0 | M7: =L7 -> 0 | N7: =M7 -> 0 | ... Q7: =P7 -> 0 | S7: =Q7 -> 0 | T7: =S7 -> 0 | U7: =T7 -> 0 | V7: =U7 -> 0 | W7: =V7 -> 0 | X7: =W7 -> 0 | Y7: =X7 -> 0 | Z7: =Y7 -> 0 | AA7: =Z7 -> 0 | ... AD7: =AC7 -> 0 | AF7: =AD7 -> 0 | AG7: =AF7 -> 0 | AH7: =AG7 -> 0 | AI7: =AH7 -> 0 | AJ7: =AI7 -> 0 | AK7: =AJ7 -> 0 | AL7: =AK7 -> 0 | AM7: =AL7 -> 0 | AN7: =AM7 -> 0 | ... AQ7: =AP7 -> 0 | AS7: =AQ7 -> 0 | AT7: =AS7 -> 0 | AU7: =AT7 -> 0 | AV7: =AU7 -> 0 | AW7: =AV7 -> 0 | AX7: =AW7 -> 0 | AY7: =AX7 -> 0 | AZ7: =AY7 -> 0 | BA7: =AZ7 -> 0 | ... BD7: =BC7 -> 0 | BF7: =BD7 -> 0 | BG7: =BF7 -> 0 | BH7: =BG7 -> 0 | BI7: =BH7 -> 0 | BJ7: =BI7 -> 0 | BK7: =BJ7 -> 0 | BL7: =BK7 -> 0 | BM7: =BL7 -> 0 | BN7: =BM7 -> 0 | ... BQ7: =BP7 -> 0 | BS7: =BQ7 -> 0 | BT7: =BS7 -> 0 | BU7: =BT7 -> 0 | BV7: =BU7 -> 0 | BW7: =BV7 -> 0 | BX7: =BW7 -> 0 | BY7: =BX7 -> 0 | BZ7: =BY7 -> 0 | CA7: =BZ7 -> 0 | ... CD7: =CC7 -> 0 | CF7: =CD7 -> 0 | CG7: =CF7 -> 0 | CH7: =CG7 -> 0 | CI7: =CH7 -> 0 | CJ7: =CI7 -> 0 | CK7: =CJ7 -> 0 | CL7: =CK7 -> 0 | CM7: =CL7 -> 0 | CN7: =CM7 -> 0 | ... CQ7: =CP7 -> 0 | CS7: =CQ7 -> 0 | CT7: =CS7 -> 0 | CU7: =CT7 -> 0 | CV7: =CU7 -> 0 | CW7: =CV7 -> 0 | CX7: =CW7 -> 0 | CY7: =CX7 -> 0 | CZ7: =CY7 -> 0 | DA7: =CZ7 -> 0 | ... DD7: =DC7 -> 0 | DF7: =DD7 -> 0 | DG7: =DF7 -> 0 | DH7: =DG7 -> 0 | DI7: =DH7 -> 0 | DJ7: =DI7 -> 0 | DK7: =DJ7 -> 0 | DL7: =DK7 -> 0 | DM7: =DL7 -> 0 | DN7: =DM7 -> 0 | ... DQ7: =DP7 -> 0 | DS7: =SUM(F7:Q7)+SUM(S7:AD7)+SUM(AF7:AQ7)+SUM(AS7:BD7)+SUM(BF7:BQ7)+SUM(BS7:CD7)+SUM(CF7:CQ7)+SUM(CS7:DD7)+SUM(DF7:DQ7) -> 0
C8: Onsite - Local
A9: 1 | B9: 1 | C9: ='Role Selection'!F6 -> IT/JavaNetColdFusionIT/DeveloperJavaNetColdFusion/Junior | D9: ='Role Selection'!HO6 -> 0 | E9: ='Role Selection'!H6 -> B2 AP1 / B2 AP2 (0.6 to 3 yrs) | G9: =F9 -> 0 | H9: =G9 -> 0 | I9: =H9 -> 0 | J9: =I9 -> 0 | K9: =J9 -> 0 | L9: =K9 -> 0 | M9: =L9 -> 0 | N9: =M9 -> 0 | ... Q9: =P9 -> 0 | S9: =+Q9 -> 0 | T9: =S9 -> 0 | U9: =T9 -> 0 | V9: =U9 -> 0 | W9: =V9 -> 0 | X9: =W9 -> 0 | Y9: =X9 -> 0 | Z9: =Y9 -> 0 | AA9: =Z9 -> 0 | ... AD9: =AC9 -> 0 | AF9: =+AD9 -> 0 | AG9: =AF9 -> 0 | AH9: =AG9 -> 0 | AI9: =AH9 -> 0 | AJ9: =AI9 -> 0 | AK9: =AJ9 -> 0 | AL9: =AK9 -> 0 | AM9: =AL9 -> 0 | AN9: =AM9 -> 0 | ... AQ9: =AP9 -> 0 | AS9: =AQ9 -> 0 | AT9: =AS9 -> 0 | AU9: =AT9 -> 0 | AV9: =AU9 -> 0 | AW9: =AV9 -> 0 | AX9: =AW9 -> 0 | AY9: =AX9 -> 0 | AZ9: =AY9 -> 0 | BA9: =AZ9 -> 0 | ... BD9: =BC9 -> 0 | BF9: =BD9 -> 0 | BG9: =BF9 -> 0 | BH9: =BG9 -> 0 | BI9: =BH9 -> 0 | BJ9: =BI9 -> 0 | BK9: =BJ9 -> 0 | BL9: =BK9 -> 0 | BM9: =BL9 -> 0 | BN9: =BM9 -> 0 | ... BQ9: =BP9 -> 0 | BS9: =BQ9 -> 0 | BT9: =BS9 -> 0 | BU9: =BT9 -> 0 | BV9: =BU9 -> 0 | BW9: =BV9 -> 0 | BX9: =BW9 -> 0 | BY9: =BX9 -> 0 | BZ9: =BY9 -> 0 | CA9: =BZ9 -> 0 | ... CD9: =CC9 -> 0 | CF9: =CD9 -> 0 | CG9: =CF9 -> 0 | CH9: =CG9 -> 0 | CI9: =CH9 -> 0 | CJ9: =CI9 -> 0 | CK9: =CJ9 -> 0 | CL9: =CK9 -> 0 | CM9: =CL9 -> 0 | CN9: =CM9 -> 0 | ... CQ9: =CP9 -> 0 | CS9: =CQ9 -> 0 | CT9: =CS9 -> 0 | CU9: =CT9 -> 0 | CV9: =CU9 -> 0 | CW9: =CV9 -> 0 | CX9: =CW9 -> 0 | CY9: =CX9 -> 0 | CZ9: =CY9 -> 0 | DA9: =CZ9 -> 0 | ... DD9: =DC9 -> 0 | DF9: =DD9 -> 0 | DG9: =DF9 -> 0 | DH9: =DG9 -> 0 | DI9: =DH9 -> 0 | DJ9: =DI9 -> 0 | DK9: =DJ9 -> 0 | DL9: =DK9 -> 0 | DM9: =DL9 -> 0 | DN9: =DM9 -> 0 | ... DQ9: =DP9 -> 0 | DS9: =SUM(F9:Q9)+SUM(S9:AD9)+SUM(AF9:AQ9)+SUM(AS9:BD9)+SUM(BF9:BQ9)+SUM(BS9:CD9)+SUM(CF9:CQ9)+SUM(CS9:DD9)+SUM(DF9:DQ9) -> 0
C10: ='Role Selection'!F7 -> /// | D10: ='Role Selection'!HO7 -> 0 | E10: ='Role Selection'!H7 -> 0 | G10: =F10 -> 0 | H10: =G10 -> 0 | I10: =H10 -> 0 | J10: =I10 -> 0 | K10: =J10 -> 0 | L10: =K10 -> 0 | M10: =L10 -> 0 | N10: =M10 -> 0 | ... Q10: =P10 -> 0 | S10: =+Q10 -> 0 | T10: =S10 -> 0 | U10: =T10 -> 0 | V10: =U10 -> 0 | W10: =V10 -> 0 | X10: =W10 -> 0 | Y10: =X10 -> 0 | Z10: =Y10 -> 0 | AA10: =Z10 -> 0 | ... AD10: =AC10 -> 0 | AF10: =AD10 -> 0 | AG10: =AF10 -> 0 | AH10: =AG10 -> 0 | AI10: =AH10 -> 0 | AJ10: =AI10 -> 0 | AK10: =AJ10 -> 0 | AL10: =AK10 -> 0 | AM10: =AL10 -> 0 | AN10: =AM10 -> 0 | ... AQ10: =AP10 -> 0 | AS10: =AQ10 -> 0 | AT10: =AS10 -> 0 | AU10: =AT10 -> 0 | AV10: =AU10 -> 0 | AW10: =AV10 -> 0 | AX10: =AW10 -> 0 | AY10: =AX10 -> 0 | AZ10: =AY10 -> 0 | BA10: =AZ10 -> 0 | ... BD10: =BC10 -> 0 | BF10: =BD10 -> 0 | BG10: =BF10 -> 0 | BH10: =BG10 -> 0 | BI10: =BH10 -> 0 | BJ10: =BI10 -> 0 | BK10: =BJ10 -> 0 | BL10: =BK10 -> 0 | BM10: =BL10 -> 0 | BN10: =BM10 -> 0 | ... BQ10: =BP10 -> 0 | BS10: =BQ10 -> 0 | BT10: =BS10 -> 0 | BU10: =BT10 -> 0 | BV10: =BU10 -> 0 | BW10: =BV10 -> 0 | BX10: =BW10 -> 0 | BY10: =BX10 -> 0 | BZ10: =BY10 -> 0 | CA10: =BZ10 -> 0 | ... CD10: =CC10 -> 0 | CF10: =CD10 -> 0 | CG10: =CF10 -> 0 | CH10: =CG10 -> 0 | CI10: =CH10 -> 0 | CJ10: =CI10 -> 0 | CK10: =CJ10 -> 0 | CL10: =CK10 -> 0 | CM10: =CL10 -> 0 | CN10: =CM10 -> 0 | ... CQ10: =CP10 -> 0 | CS10: =CQ10 -> 0 | CT10: =CS10 -> 0 | CU10: =CT10 -> 0 | CV10: =CU10 -> 0 | CW10: =CV10 -> 0 | CX10: =CW10 -> 0 | CY10: =CX10 -> 0 | CZ10: =CY10 -> 0 | DA10: =CZ10 -> 0 | ... DD10: =DC10 -> 0 | DF10: =DD10 -> 0 | DG10: =DF10 -> 0 | DH10: =DG10 -> 0 | DI10: =DH10 -> 0 | DJ10: =DI10 -> 0 | DK10: =DJ10 -> 0 | DL10: =DK10 -> 0 | DM10: =DL10 -> 0 | DN10: =DM10 -> 0 | ... DQ10: =DP10 -> 0 | DS10: =SUM(F10:Q10)+SUM(S10:AD10)+SUM(AF10:AQ10)+SUM(AS10:BD10)+SUM(BF10:BQ10)+SUM(BS10:CD10)+SUM(CF10:CQ10)+SUM(CS10:DD10)+SUM(DF10:DQ10) -> 0
A11: 1 | B11: 2 | C11: ='Role Selection'!F8 -> /// | D11: ='Role Selection'!HO8 -> 0 | E11: ='Role Selection'!H8 -> 0 | G11: =F11 -> 0 | H11: =G11 -> 0 | I11: =H11 -> 0 | J11: =I11 -> 0 | K11: =J11 -> 0 | L11: =K11 -> 0 | M11: =L11 -> 0 | N11: =M11 -> 0 | ... Q11: =P11 -> 0 | S11: =+Q11 -> 0 | T11: =S11 -> 0 | U11: =T11 -> 0 | V11: =U11 -> 0 | W11: =V11 -> 0 | X11: =W11 -> 0 | Y11: =X11 -> 0 | Z11: =Y11 -> 0 | AA11: =Z11 -> 0 | ... AD11: =AC11 -> 0 | AF11: =AD11 -> 0 | AG11: =AF11 -> 0 | AH11: =AG11 -> 0 | AI11: =AH11 -> 0 | AJ11: =AI11 -> 0 | AK11: =AJ11 -> 0 | AL11: =AK11 -> 0 | AM11: =AL11 -> 0 | AN11: =AM11 -> 0 | ... AQ11: =AP11 -> 0 | AS11: =AQ11 -> 0 | AT11: =AS11 -> 0 | AU11: =AT11 -> 0 | AV11: =AU11 -> 0 | AW11: =AV11 -> 0 | AX11: =AW11 -> 0 | AY11: =AX11 -> 0 | AZ11: =AY11 -> 0 | BA11: =AZ11 -> 0 | ... BD11: =BC11 -> 0 | BF11: =BD11 -> 0 | BG11: =BF11 -> 0 | BH11: =BG11 -> 0 | BI11: =BH11 -> 0 | BJ11: =BI11 -> 0 | BK11: =BJ11 -> 0 | BL11: =BK11 -> 0 | BM11: =BL11 -> 0 | BN11: =BM11 -> 0 | ... BQ11: =BP11 -> 0 | BS11: =BQ11 -> 0 | BT11: =BS11 -> 0 | BU11: =BT11 -> 0 | BV11: =BU11 -> 0 | BW11: =BV11 -> 0 | BX11: =BW11 -> 0 | BY11: =BX11 -> 0 | BZ11: =BY11 -> 0 | CA11: =BZ11 -> 0 | ... CD11: =CC11 -> 0 | CF11: =CD11 -> 0 | CG11: =CF11 -> 0 | CH11: =CG11 -> 0 | CI11: =CH11 -> 0 | CJ11: =CI11 -> 0 | CK11: =CJ11 -> 0 | CL11: =CK11 -> 0 | CM11: =CL11 -> 0 | CN11: =CM11 -> 0 | ... CQ11: =CP11 -> 0 | CS11: =CQ11 -> 0 | CT11: =CS11 -> 0 | CU11: =CT11 -> 0 | CV11: =CU11 -> 0 | CW11: =CV11 -> 0 | CX11: =CW11 -> 0 | CY11: =CX11 -> 0 | CZ11: =CY11 -> 0 | DA11: =CZ11 -> 0 | ... DD11: =DC11 -> 0 | DF11: =DD11 -> 0 | DG11: =DF11 -> 0 | DH11: =DG11 -> 0 | DI11: =DH11 -> 0 | DJ11: =DI11 -> 0 | DK11: =DJ11 -> 0 | DL11: =DK11 -> 0 | DM11: =DL11 -> 0 | DN11: =DM11 -> 0 | ... DQ11: =DP11 -> 0 | DS11: =SUM(F11:Q11)+SUM(S11:AD11)+SUM(AF11:AQ11)+SUM(AS11:BD11)+SUM(BF11:BQ11)+SUM(BS11:CD11)+SUM(CF11:CQ11)+SUM(CS11:DD11)+SUM(DF11:DQ11) -> 0
C12: ='Role Selection'!F9 -> /// | D12: ='Role Selection'!HO9 -> 0 | E12: ='Role Selection'!H9 -> 0 | G12: =F12 -> 0 | H12: =G12 -> 0 | I12: =H12 -> 0 | J12: =I12 -> 0 | K12: =J12 -> 0 | L12: =K12 -> 0 | M12: =L12 -> 0 | N12: =M12 -> 0 | ... Q12: =P12 -> 0 | S12: =+Q12 -> 0 | T12: =S12 -> 0 | U12: =T12 -> 0 | V12: =U12 -> 0 | W12: =V12 -> 0 | X12: =W12 -> 0 | Y12: =X12 -> 0 | Z12: =Y12 -> 0 | AA12: =Z12 -> 0 | ... AD12: =AC12 -> 0 | AF12: =AD12 -> 0 | AG12: =AF12 -> 0 | AH12: =AG12 -> 0 | AI12: =AH12 -> 0 | AJ12: =AI12 -> 0 | AK12: =AJ12 -> 0 | AL12: =AK12 -> 0 | AM12: =AL12 -> 0 | AN12: =AM12 -> 0 | ... AQ12: =AP12 -> 0 | AS12: =AQ12 -> 0 | AT12: =AS12 -> 0 | AU12: =AT12 -> 0 | AV12: =AU12 -> 0 | AW12: =AV12 -> 0 | AX12: =AW12 -> 0 | AY12: =AX12 -> 0 | AZ12: =AY12 -> 0 | BA12: =AZ12 -> 0 | ... BD12: =BC12 -> 0 | BF12: =BD12 -> 0 | BG12: =BF12 -> 0 | BH12: =BG12 -> 0 | BI12: =BH12 -> 0 | BJ12: =BI12 -> 0 | BK12: =BJ12 -> 0 | BL12: =BK12 -> 0 | BM12: =BL12 -> 0 | BN12: =BM12 -> 0 | ... BQ12: =BP12 -> 0 | BS12: =BQ12 -> 0 | BT12: =BS12 -> 0 | BU12: =BT12 -> 0 | BV12: =BU12 -> 0 | BW12: =BV12 -> 0 | BX12: =BW12 -> 0 | BY12: =BX12 -> 0 | BZ12: =BY12 -> 0 | CA12: =BZ12 -> 0 | ... CD12: =CC12 -> 0 | CF12: =CD12 -> 0 | CG12: =CF12 -> 0 | CH12: =CG12 -> 0 | CI12: =CH12 -> 0 | CJ12: =CI12 -> 0 | CK12: =CJ12 -> 0 | CL12: =CK12 -> 0 | CM12: =CL12 -> 0 | CN12: =CM12 -> 0 | ... CQ12: =CP12 -> 0 | CS12: =CQ12 -> 0 | CT12: =CS12 -> 0 | CU12: =CT12 -> 0 | CV12: =CU12 -> 0 | CW12: =CV12 -> 0 | CX12: =CW12 -> 0 | CY12: =CX12 -> 0 | CZ12: =CY12 -> 0 | DA12: =CZ12 -> 0 | ... DD12: =DC12 -> 0 | DF12: =DD12 -> 0 | DG12: =DF12 -> 0 | DH12: =DG12 -> 0 | DI12: =DH12 -> 0 | DJ12: =DI12 -> 0 | DK12: =DJ12 -> 0 | DL12: =DK12 -> 0 | DM12: =DL12 -> 0 | DN12: =DM12 -> 0 | ... DQ12: =DP12 -> 0 | DS12: =SUM(F12:Q12)+SUM(S12:AD12)+SUM(AF12:AQ12)+SUM(AS12:BD12)+SUM(BF12:BQ12)+SUM(BS12:CD12)+SUM(CF12:CQ12)+SUM(CS12:DD12)+SUM(DF12:DQ12) -> 0
A13: 1 | B13: 3 | C13: ='Role Selection'!F10 -> /// | D13: ='Role Selection'!HO10 -> 0 | E13: ='Role Selection'!H10 -> 0 | G13: =F13 -> 0 | H13: =G13 -> 0 | I13: =H13 -> 0 | J13: =I13 -> 0 | K13: =J13 -> 0 | L13: =K13 -> 0 | M13: =L13 -> 0 | N13: =M13 -> 0 | ... Q13: =P13 -> 0 | S13: =+Q13 -> 0 | T13: =S13 -> 0 | U13: =T13 -> 0 | V13: =U13 -> 0 | W13: =V13 -> 0 | X13: =W13 -> 0 | Y13: =X13 -> 0 | Z13: =Y13 -> 0 | AA13: =Z13 -> 0 | ... AD13: =AC13 -> 0 | AF13: =AD13 -> 0 | AG13: =AF13 -> 0 | AH13: =AG13 -> 0 | AI13: =AH13 -> 0 | AJ13: =AI13 -> 0 | AK13: =AJ13 -> 0 | AL13: =AK13 -> 0 | AM13: =AL13 -> 0 | AN13: =AM13 -> 0 | ... AQ13: =AP13 -> 0 | AS13: =AQ13 -> 0 | AT13: =AS13 -> 0 | AU13: =AT13 -> 0 | AV13: =AU13 -> 0 | AW13: =AV13 -> 0 | AX13: =AW13 -> 0 | AY13: =AX13 -> 0 | AZ13: =AY13 -> 0 | BA13: =AZ13 -> 0 | ... BD13: =BC13 -> 0 | BF13: =BD13 -> 0 | BG13: =BF13 -> 0 | BH13: =BG13 -> 0 | BI13: =BH13 -> 0 | BJ13: =BI13 -> 0 | BK13: =BJ13 -> 0 | BL13: =BK13 -> 0 | BM13: =BL13 -> 0 | BN13: =BM13 -> 0 | ... BQ13: =BP13 -> 0 | BS13: =BQ13 -> 0 | BT13: =BS13 -> 0 | BU13: =BT13 -> 0 | BV13: =BU13 -> 0 | BW13: =BV13 -> 0 | BX13: =BW13 -> 0 | BY13: =BX13 -> 0 | BZ13: =BY13 -> 0 | CA13: =BZ13 -> 0 | ... CD13: =CC13 -> 0 | CF13: =CD13 -> 0 | CG13: =CF13 -> 0 | CH13: =CG13 -> 0 | CI13: =CH13 -> 0 | CJ13: =CI13 -> 0 | CK13: =CJ13 -> 0 | CL13: =CK13 -> 0 | CM13: =CL13 -> 0 | CN13: =CM13 -> 0 | ... CQ13: =CP13 -> 0 | CS13: =CQ13 -> 0 | CT13: =CS13 -> 0 | CU13: =CT13 -> 0 | CV13: =CU13 -> 0 | CW13: =CV13 -> 0 | CX13: =CW13 -> 0 | CY13: =CX13 -> 0 | CZ13: =CY13 -> 0 | DA13: =CZ13 -> 0 | ... DD13: =DC13 -> 0 | DF13: =DD13 -> 0 | DG13: =DF13 -> 0 | DH13: =DG13 -> 0 | DI13: =DH13 -> 0 | DJ13: =DI13 -> 0 | DK13: =DJ13 -> 0 | DL13: =DK13 -> 0 | DM13: =DL13 -> 0 | DN13: =DM13 -> 0 | ... DQ13: =DP13 -> 0 | DS13: =SUM(F13:Q13)+SUM(S13:AD13)+SUM(AF13:AQ13)+SUM(AS13:BD13)+SUM(BF13:BQ13)+SUM(BS13:CD13)+SUM(CF13:CQ13)+SUM(CS13:DD13)+SUM(DF13:DQ13) -> 0
C14: ='Role Selection'!F11 -> /// | D14: ='Role Selection'!HO11 -> 0 | E14: ='Role Selection'!H11 -> 0 | G14: =F14 -> 0 | H14: =G14 -> 0 | I14: =H14 -> 0 | J14: =I14 -> 0 | K14: =J14 -> 0 | L14: =K14 -> 0 | M14: =L14 -> 0 | N14: =M14 -> 0 | ... Q14: =P14 -> 0 | S14: =+Q14 -> 0 | T14: =S14 -> 0 | U14: =T14 -> 0 | V14: =U14 -> 0 | W14: =V14 -> 0 | X14: =W14 -> 0 | Y14: =X14 -> 0 | Z14: =Y14 -> 0 | AA14: =Z14 -> 0 | ... AD14: =AC14 -> 0 | AF14: =AD14 -> 0 | AG14: =AF14 -> 0 | AH14: =AG14 -> 0 | AI14: =AH14 -> 0 | AJ14: =AI14 -> 0 | AK14: =AJ14 -> 0 | AL14: =AK14 -> 0 | AM14: =AL14 -> 0 | AN14: =AM14 -> 0 | ... AQ14: =AP14 -> 0 | AS14: =AQ14 -> 0 | AT14: =AS14 -> 0 | AU14: =AT14 -> 0 | AV14: =AU14 -> 0 | AW14: =AV14 -> 0 | AX14: =AW14 -> 0 | AY14: =AX14 -> 0 | AZ14: =AY14 -> 0 | BA14: =AZ14 -> 0 | ... BD14: =BC14 -> 0 | BF14: =BD14 -> 0 | BG14: =BF14 -> 0 | BH14: =BG14 -> 0 | BI14: =BH14 -> 0 | BJ14: =BI14 -> 0 | BK14: =BJ14 -> 0 | BL14: =BK14 -> 0 | BM14: =BL14 -> 0 | BN14: =BM14 -> 0 | ... BQ14: =BP14 -> 0 | BS14: =BQ14 -> 0 | BT14: =BS14 -> 0 | BU14: =BT14 -> 0 | BV14: =BU14 -> 0 | BW14: =BV14 -> 0 | BX14: =BW14 -> 0 | BY14: =BX14 -> 0 | BZ14: =BY14 -> 0 | CA14: =BZ14 -> 0 | ... CD14: =CC14 -> 0 | CF14: =CD14 -> 0 | CG14: =CF14 -> 0 | CH14: =CG14 -> 0 | CI14: =CH14 -> 0 | CJ14: =CI14 -> 0 | CK14: =CJ14 -> 0 | CL14: =CK14 -> 0 | CM14: =CL14 -> 0 | CN14: =CM14 -> 0 | ... CQ14: =CP14 -> 0 | CS14: =CQ14 -> 0 | CT14: =CS14 -> 0 | CU14: =CT14 -> 0 | CV14: =CU14 -> 0 | CW14: =CV14 -> 0 | CX14: =CW14 -> 0 | CY14: =CX14 -> 0 | CZ14: =CY14 -> 0 | DA14: =CZ14 -> 0 | ... DD14: =DC14 -> 0 | DF14: =DD14 -> 0 | DG14: =DF14 -> 0 | DH14: =DG14 -> 0 | DI14: =DH14 -> 0 | DJ14: =DI14 -> 0 | DK14: =DJ14 -> 0 | DL14: =DK14 -> 0 | DM14: =DL14 -> 0 | DN14: =DM14 -> 0 | ... DQ14: =DP14 -> 0 | DS14: =SUM(F14:Q14)+SUM(S14:AD14)+SUM(AF14:AQ14)+SUM(AS14:BD14)+SUM(BF14:BQ14)+SUM(BS14:CD14)+SUM(CF14:CQ14)+SUM(CS14:DD14)+SUM(DF14:DQ14) -> 0
A15: 1 | B15: 4 | C15: ='Role Selection'!F12 -> /// | D15: ='Role Selection'!HO12 -> 0 | E15: ='Role Selection'!H12 -> 0 | G15: =F15 -> 0 | H15: =G15 -> 0 | I15: =H15 -> 0 | J15: =I15 -> 0 | K15: =J15 -> 0 | L15: =K15 -> 0 | M15: =L15 -> 0 | N15: =M15 -> 0 | ... Q15: =P15 -> 0 | S15: =+Q15 -> 0 | T15: =S15 -> 0 | U15: =T15 -> 0 | V15: =U15 -> 0 | W15: =V15 -> 0 | X15: =W15 -> 0 | Y15: =X15 -> 0 | Z15: =Y15 -> 0 | AA15: =Z15 -> 0 | ... AD15: =AC15 -> 0 | AF15: =AD15 -> 0 | AG15: =AF15 -> 0 | AH15: =AG15 -> 0 | AI15: =AH15 -> 0 | AJ15: =AI15 -> 0 | AK15: =AJ15 -> 0 | AL15: =AK15 -> 0 | AM15: =AL15 -> 0 | AN15: =AM15 -> 0 | ... AQ15: =AP15 -> 0 | AS15: =AQ15 -> 0 | AT15: =AS15 -> 0 | AU15: =AT15 -> 0 | AV15: =AU15 -> 0 | AW15: =AV15 -> 0 | AX15: =AW15 -> 0 | AY15: =AX15 -> 0 | AZ15: =AY15 -> 0 | BA15: =AZ15 -> 0 | ... BD15: =BC15 -> 0 | BF15: =BD15 -> 0 | BG15: =BF15 -> 0 | BH15: =BG15 -> 0 | BI15: =BH15 -> 0 | BJ15: =BI15 -> 0 | BK15: =BJ15 -> 0 | BL15: =BK15 -> 0 | BM15: =BL15 -> 0 | BN15: =BM15 -> 0 | ... BQ15: =BP15 -> 0 | BS15: =BQ15 -> 0 | BT15: =BS15 -> 0 | BU15: =BT15 -> 0 | BV15: =BU15 -> 0 | BW15: =BV15 -> 0 | BX15: =BW15 -> 0 | BY15: =BX15 -> 0 | BZ15: =BY15 -> 0 | CA15: =BZ15 -> 0 | ... CD15: =CC15 -> 0 | CF15: =CD15 -> 0 | CG15: =CF15 -> 0 | CH15: =CG15 -> 0 | CI15: =CH15 -> 0 | CJ15: =CI15 -> 0 | CK15: =CJ15 -> 0 | CL15: =CK15 -> 0 | CM15: =CL15 -> 0 | CN15: =CM15 -> 0 | ... CQ15: =CP15 -> 0 | CS15: =CQ15 -> 0 | CT15: =CS15 -> 0 | CU15: =CT15 -> 0 | CV15: =CU15 -> 0 | CW15: =CV15 -> 0 | CX15: =CW15 -> 0 | CY15: =CX15 -> 0 | CZ15: =CY15 -> 0 | DA15: =CZ15 -> 0 | ... DD15: =DC15 -> 0 | DF15: =DD15 -> 0 | DG15: =DF15 -> 0 | DH15: =DG15 -> 0 | DI15: =DH15 -> 0 | DJ15: =DI15 -> 0 | DK15: =DJ15 -> 0 | DL15: =DK15 -> 0 | DM15: =DL15 -> 0 | DN15: =DM15 -> 0 | ... DQ15: =DP15 -> 0 | DS15: =SUM(F15:Q15)+SUM(S15:AD15)+SUM(AF15:AQ15)+SUM(AS15:BD15)+SUM(BF15:BQ15)+SUM(BS15:CD15)+SUM(CF15:CQ15)+SUM(CS15:DD15)+SUM(DF15:DQ15) -> 0
C16: ='Role Selection'!F13 -> /// | D16: ='Role Selection'!HO13 -> 0 | E16: ='Role Selection'!H13 -> 0 | G16: =F16 -> 0 | H16: =G16 -> 0 | I16: =H16 -> 0 | J16: =I16 -> 0 | K16: =J16 -> 0 | L16: =K16 -> 0 | M16: =L16 -> 0 | N16: =M16 -> 0 | ... Q16: =P16 -> 0 | S16: =+Q16 -> 0 | T16: =S16 -> 0 | U16: =T16 -> 0 | V16: =U16 -> 0 | W16: =V16 -> 0 | X16: =W16 -> 0 | Y16: =X16 -> 0 | Z16: =Y16 -> 0 | AA16: =Z16 -> 0 | ... AD16: =AC16 -> 0 | AF16: =AD16 -> 0 | AG16: =AF16 -> 0 | AH16: =AG16 -> 0 | AI16: =AH16 -> 0 | AJ16: =AI16 -> 0 | AK16: =AJ16 -> 0 | AL16: =AK16 -> 0 | AM16: =AL16 -> 0 | AN16: =AM16 -> 0 | ... AQ16: =AP16 -> 0 | AS16: =AQ16 -> 0 | AT16: =AS16 -> 0 | AU16: =AT16 -> 0 | AV16: =AU16 -> 0 | AW16: =AV16 -> 0 | AX16: =AW16 -> 0 | AY16: =AX16 -> 0 | AZ16: =AY16 -> 0 | BA16: =AZ16 -> 0 | ... BD16: =BC16 -> 0 | BF16: =BD16 -> 0 | BG16: =BF16 -> 0 | BH16: =BG16 -> 0 | BI16: =BH16 -> 0 | BJ16: =BI16 -> 0 | BK16: =BJ16 -> 0 | BL16: =BK16 -> 0 | BM16: =BL16 -> 0 | BN16: =BM16 -> 0 | ... BQ16: =BP16 -> 0 | BS16: =BQ16 -> 0 | BT16: =BS16 -> 0 | BU16: =BT16 -> 0 | BV16: =BU16 -> 0 | BW16: =BV16 -> 0 | BX16: =BW16 -> 0 | BY16: =BX16 -> 0 | BZ16: =BY16 -> 0 | CA16: =BZ16 -> 0 | ... CD16: =CC16 -> 0 | CF16: =CD16 -> 0 | CG16: =CF16 -> 0 | CH16: =CG16 -> 0 | CI16: =CH16 -> 0 | CJ16: =CI16 -> 0 | CK16: =CJ16 -> 0 | CL16: =CK16 -> 0 | CM16: =CL16 -> 0 | CN16: =CM16 -> 0 | ... CQ16: =CP16 -> 0 | CS16: =CQ16 -> 0 | CT16: =CS16 -> 0 | CU16: =CT16 -> 0 | CV16: =CU16 -> 0 | CW16: =CV16 -> 0 | CX16: =CW16 -> 0 | CY16: =CX16 -> 0 | CZ16: =CY16 -> 0 | DA16: =CZ16 -> 0 | ... DD16: =DC16 -> 0 | DF16: =DD16 -> 0 | DG16: =DF16 -> 0 | DH16: =DG16 -> 0 | DI16: =DH16 -> 0 | DJ16: =DI16 -> 0 | DK16: =DJ16 -> 0 | DL16: =DK16 -> 0 | DM16: =DL16 -> 0 | DN16: =DM16 -> 0 | ... DQ16: =DP16 -> 0 | DS16: =SUM(F16:Q16)+SUM(S16:AD16)+SUM(AF16:AQ16)+SUM(AS16:BD16)+SUM(BF16:BQ16)+SUM(BS16:CD16)+SUM(CF16:CQ16)+SUM(CS16:DD16)+SUM(DF16:DQ16) -> 0
C17: ='Role Selection'!F14 -> /// | D17: ='Role Selection'!HO14 -> 0 | E17: ='Role Selection'!H14 -> 0 | G17: =F17 -> 0 | H17: =G17 -> 0 | I17: =H17 -> 0 | J17: =I17 -> 0 | K17: =J17 -> 0 | L17: =K17 -> 0 | M17: =L17 -> 0 | N17: =M17 -> 0 | ... Q17: =P17 -> 0 | S17: =+Q17 -> 0 | T17: =S17 -> 0 | U17: =T17 -> 0 | V17: =U17 -> 0 | W17: =V17 -> 0 | X17: =W17 -> 0 | Y17: =X17 -> 0 | Z17: =Y17 -> 0 | AA17: =Z17 -> 0 | ... AD17: =AC17 -> 0 | AF17: =AD17 -> 0 | AG17: =AF17 -> 0 | AH17: =AG17 -> 0 | AI17: =AH17 -> 0 | AJ17: =AI17 -> 0 | AK17: =AJ17 -> 0 | AL17: =AK17 -> 0 | AM17: =AL17 -> 0 | AN17: =AM17 -> 0 | ... AQ17: =AP17 -> 0 | AS17: =AQ17 -> 0 | AT17: =AS17 -> 0 | AU17: =AT17 -> 0 | AV17: =AU17 -> 0 | AW17: =AV17 -> 0 | AX17: =AW17 -> 0 | AY17: =AX17 -> 0 | AZ17: =AY17 -> 0 | BA17: =AZ17 -> 0 | ... BD17: =BC17 -> 0 | BF17: =BD17 -> 0 | BG17: =BF17 -> 0 | BH17: =BG17 -> 0 | BI17: =BH17 -> 0 | BJ17: =BI17 -> 0 | BK17: =BJ17 -> 0 | BL17: =BK17 -> 0 | BM17: =BL17 -> 0 | BN17: =BM17 -> 0 | ... BQ17: =BP17 -> 0 | BS17: =BQ17 -> 0 | BT17: =BS17 -> 0 | BU17: =BT17 -> 0 | BV17: =BU17 -> 0 | BW17: =BV17 -> 0 | BX17: =BW17 -> 0 | BY17: =BX17 -> 0 | BZ17: =BY17 -> 0 | CA17: =BZ17 -> 0 | ... CD17: =CC17 -> 0 | CF17: =CD17 -> 0 | CG17: =CF17 -> 0 | CH17: =CG17 -> 0 | CI17: =CH17 -> 0 | CJ17: =CI17 -> 0 | CK17: =CJ17 -> 0 | CL17: =CK17 -> 0 | CM17: =CL17 -> 0 | CN17: =CM17 -> 0 | ... CQ17: =CP17 -> 0 | CS17: =CQ17 -> 0 | CT17: =CS17 -> 0 | CU17: =CT17 -> 0 | CV17: =CU17 -> 0 | CW17: =CV17 -> 0 | CX17: =CW17 -> 0 | CY17: =CX17 -> 0 | CZ17: =CY17 -> 0 | DA17: =CZ17 -> 0 | ... DD17: =DC17 -> 0 | DF17: =DD17 -> 0 | DG17: =DF17 -> 0 | DH17: =DG17 -> 0 | DI17: =DH17 -> 0 | DJ17: =DI17 -> 0 | DK17: =DJ17 -> 0 | DL17: =DK17 -> 0 | DM17: =DL17 -> 0 | DN17: =DM17 -> 0 | ... DQ17: =DP17 -> 0 | DS17: =SUM(F17:Q17)+SUM(S17:AD17)+SUM(AF17:AQ17)+SUM(AS17:BD17)+SUM(BF17:BQ17)+SUM(BS17:CD17)+SUM(CF17:CQ17)+SUM(CS17:DD17)+SUM(DF17:DQ17) -> 0
A18: 1 | B18: 5 | C18: ='Role Selection'!F15 -> /// | D18: ='Role Selection'!HO15 -> 0 | E18: ='Role Selection'!H15 -> 0 | G18: =F18 -> 0 | H18: =G18 -> 0 | I18: =H18 -> 0 | J18: =I18 -> 0 | K18: =J18 -> 0 | L18: =K18 -> 0 | M18: =L18 -> 0 | N18: =M18 -> 0 | ... Q18: =P18 -> 0 | S18: =+Q18 -> 0 | T18: =S18 -> 0 | U18: =T18 -> 0 | V18: =U18 -> 0 | W18: =V18 -> 0 | X18: =W18 -> 0 | Y18: =X18 -> 0 | Z18: =Y18 -> 0 | AA18: =Z18 -> 0 | ... AD18: =AC18 -> 0 | AF18: =AD18 -> 0 | AG18: =AF18 -> 0 | AH18: =AG18 -> 0 | AI18: =AH18 -> 0 | AJ18: =AI18 -> 0 | AK18: =AJ18 -> 0 | AL18: =AK18 -> 0 | AM18: =AL18 -> 0 | AN18: =AM18 -> 0 | ... AQ18: =AP18 -> 0 | AS18: =AQ18 -> 0 | AT18: =AS18 -> 0 | AU18: =AT18 -> 0 | AV18: =AU18 -> 0 | AW18: =AV18 -> 0 | AX18: =AW18 -> 0 | AY18: =AX18 -> 0 | AZ18: =AY18 -> 0 | BA18: =AZ18 -> 0 | ... BD18: =BC18 -> 0 | BF18: =BD18 -> 0 | BG18: =BF18 -> 0 | BH18: =BG18 -> 0 | BI18: =BH18 -> 0 | BJ18: =BI18 -> 0 | BK18: =BJ18 -> 0 | BL18: =BK18 -> 0 | BM18: =BL18 -> 0 | BN18: =BM18 -> 0 | ... BQ18: =BP18 -> 0 | BS18: =BQ18 -> 0 | BT18: =BS18 -> 0 | BU18: =BT18 -> 0 | BV18: =BU18 -> 0 | BW18: =BV18 -> 0 | BX18: =BW18 -> 0 | BY18: =BX18 -> 0 | BZ18: =BY18 -> 0 | CA18: =BZ18 -> 0 | ... CD18: =CC18 -> 0 | CF18: =CD18 -> 0 | CG18: =CF18 -> 0 | CH18: =CG18 -> 0 | CI18: =CH18 -> 0 | CJ18: =CI18 -> 0 | CK18: =CJ18 -> 0 | CL18: =CK18 -> 0 | CM18: =CL18 -> 0 | CN18: =CM18 -> 0 | ... CQ18: =CP18 -> 0 | CS18: =CQ18 -> 0 | CT18: =CS18 -> 0 | CU18: =CT18 -> 0 | CV18: =CU18 -> 0 | CW18: =CV18 -> 0 | CX18: =CW18 -> 0 | CY18: =CX18 -> 0 | CZ18: =CY18 -> 0 | DA18: =CZ18 -> 0 | ... DD18: =DC18 -> 0 | DF18: =DD18 -> 0 | DG18: =DF18 -> 0 | DH18: =DG18 -> 0 | DI18: =DH18 -> 0 | DJ18: =DI18 -> 0 | DK18: =DJ18 -> 0 | DL18: =DK18 -> 0 | DM18: =DL18 -> 0 | DN18: =DM18 -> 0 | ... DQ18: =DP18 -> 0 | DS18: =SUM(F18:Q18)+SUM(S18:AD18)+SUM(AF18:AQ18)+SUM(AS18:BD18)+SUM(BF18:BQ18)+SUM(BS18:CD18)+SUM(CF18:CQ18)+SUM(CS18:DD18)+SUM(DF18:DQ18) -> 0
C19: ='Role Selection'!F16 -> /// | D19: ='Role Selection'!HO16 -> 0 | E19: ='Role Selection'!H16 -> 0 | G19: =F19 -> 0 | H19: =G19 -> 0 | I19: =H19 -> 0 | J19: =I19 -> 0 | K19: =J19 -> 0 | L19: =K19 -> 0 | M19: =L19 -> 0 | N19: =M19 -> 0 | ... Q19: =P19 -> 0 | S19: =+Q19 -> 0 | T19: =S19 -> 0 | U19: =T19 -> 0 | V19: =U19 -> 0 | W19: =V19 -> 0 | X19: =W19 -> 0 | Y19: =X19 -> 0 | Z19: =Y19 -> 0 | AA19: =Z19 -> 0 | ... AD19: =AC19 -> 0 | AF19: =AD19 -> 0 | AG19: =AF19 -> 0 | AH19: =AG19 -> 0 | AI19: =AH19 -> 0 | AJ19: =AI19 -> 0 | AK19: =AJ19 -> 0 | AL19: =AK19 -> 0 | AM19: =AL19 -> 0 | AN19: =AM19 -> 0 | ... AQ19: =AP19 -> 0 | AS19: =AQ19 -> 0 | AT19: =AS19 -> 0 | AU19: =AT19 -> 0 | AV19: =AU19 -> 0 | AW19: =AV19 -> 0 | AX19: =AW19 -> 0 | AY19: =AX19 -> 0 | AZ19: =AY19 -> 0 | BA19: =AZ19 -> 0 | ... BD19: =BC19 -> 0 | BF19: =BD19 -> 0 | BG19: =BF19 -> 0 | BH19: =BG19 -> 0 | BI19: =BH19 -> 0 | BJ19: =BI19 -> 0 | BK19: =BJ19 -> 0 | BL19: =BK19 -> 0 | BM19: =BL19 -> 0 | BN19: =BM19 -> 0 | ... BQ19: =BP19 -> 0 | BS19: =BQ19 -> 0 | BT19: =BS19 -> 0 | BU19: =BT19 -> 0 | BV19: =BU19 -> 0 | BW19: =BV19 -> 0 | BX19: =BW19 -> 0 | BY19: =BX19 -> 0 | BZ19: =BY19 -> 0 | CA19: =BZ19 -> 0 | ... CD19: =CC19 -> 0 | CF19: =CD19 -> 0 | CG19: =CF19 -> 0 | CH19: =CG19 -> 0 | CI19: =CH19 -> 0 | CJ19: =CI19 -> 0 | CK19: =CJ19 -> 0 | CL19: =CK19 -> 0 | CM19: =CL19 -> 0 | CN19: =CM19 -> 0 | ... CQ19: =CP19 -> 0 | CS19: =CQ19 -> 0 | CT19: =CS19 -> 0 | CU19: =CT19 -> 0 | CV19: =CU19 -> 0 | CW19: =CV19 -> 0 | CX19: =CW19 -> 0 | CY19: =CX19 -> 0 | CZ19: =CY19 -> 0 | DA19: =CZ19 -> 0 | ... DD19: =DC19 -> 0 | DF19: =DD19 -> 0 | DG19: =DF19 -> 0 | DH19: =DG19 -> 0 | DI19: =DH19 -> 0 | DJ19: =DI19 -> 0 | DK19: =DJ19 -> 0 | DL19: =DK19 -> 0 | DM19: =DL19 -> 0 | DN19: =DM19 -> 0 | ... DQ19: =DP19 -> 0 | DS19: =SUM(F19:Q19)+SUM(S19:AD19)+SUM(AF19:AQ19)+SUM(AS19:BD19)+SUM(BF19:BQ19)+SUM(BS19:CD19)+SUM(CF19:CQ19)+SUM(CS19:DD19)+SUM(DF19:DQ19) -> 0
A20: 1 | B20: 6 | C20: ='Role Selection'!F17 -> /// | D20: ='Role Selection'!HO17 -> 0 | E20: ='Role Selection'!H17 -> 0 | G20: =F20 -> 0 | H20: =G20 -> 0 | I20: =H20 -> 0 | J20: =I20 -> 0 | K20: =J20 -> 0 | L20: =K20 -> 0 | M20: =L20 -> 0 | N20: =M20 -> 0 | ... Q20: =P20 -> 0 | S20: =+Q20 -> 0 | T20: =S20 -> 0 | U20: =T20 -> 0 | V20: =U20 -> 0 | W20: =V20 -> 0 | X20: =W20 -> 0 | Y20: =X20 -> 0 | Z20: =Y20 -> 0 | AA20: =Z20 -> 0 | ... AD20: =AC20 -> 0 | AF20: =AD20 -> 0 | AG20: =AF20 -> 0 | AH20: =AG20 -> 0 | AI20: =AH20 -> 0 | AJ20: =AI20 -> 0 | AK20: =AJ20 -> 0 | AL20: =AK20 -> 0 | AM20: =AL20 -> 0 | AN20: =AM20 -> 0 | ... AQ20: =AP20 -> 0 | AS20: =AQ20 -> 0 | AT20: =AS20 -> 0 | AU20: =AT20 -> 0 | AV20: =AU20 -> 0 | AW20: =AV20 -> 0 | AX20: =AW20 -> 0 | AY20: =AX20 -> 0 | AZ20: =AY20 -> 0 | BA20: =AZ20 -> 0 | ... BD20: =BC20 -> 0 | BF20: =BD20 -> 0 | BG20: =BF20 -> 0 | BH20: =BG20 -> 0 | BI20: =BH20 -> 0 | BJ20: =BI20 -> 0 | BK20: =BJ20 -> 0 | BL20: =BK20 -> 0 | BM20: =BL20 -> 0 | BN20: =BM20 -> 0 | ... BQ20: =BP20 -> 0 | BS20: =BQ20 -> 0 | BT20: =BS20 -> 0 | BU20: =BT20 -> 0 | BV20: =BU20 -> 0 | BW20: =BV20 -> 0 | BX20: =BW20 -> 0 | BY20: =BX20 -> 0 | BZ20: =BY20 -> 0 | CA20: =BZ20 -> 0 | ... CD20: =CC20 -> 0 | CF20: =CD20 -> 0 | CG20: =CF20 -> 0 | CH20: =CG20 -> 0 | CI20: =CH20 -> 0 | CJ20: =CI20 -> 0 | CK20: =CJ20 -> 0 | CL20: =CK20 -> 0 | CM20: =CL20 -> 0 | CN20: =CM20 -> 0 | ... CQ20: =CP20 -> 0 | CS20: =CQ20 -> 0 | CT20: =CS20 -> 0 | CU20: =CT20 -> 0 | CV20: =CU20 -> 0 | CW20: =CV20 -> 0 | CX20: =CW20 -> 0 | CY20: =CX20 -> 0 | CZ20: =CY20 -> 0 | DA20: =CZ20 -> 0 | ... DD20: =DC20 -> 0 | DF20: =DD20 -> 0 | DG20: =DF20 -> 0 | DH20: =DG20 -> 0 | DI20: =DH20 -> 0 | DJ20: =DI20 -> 0 | DK20: =DJ20 -> 0 | DL20: =DK20 -> 0 | DM20: =DL20 -> 0 | DN20: =DM20 -> 0 | ... DQ20: =DP20 -> 0 | DS20: =SUM(F20:Q20)+SUM(S20:AD20)+SUM(AF20:AQ20)+SUM(AS20:BD20)+SUM(BF20:BQ20)+SUM(BS20:CD20)+SUM(CF20:CQ20)+SUM(CS20:DD20)+SUM(DF20:DQ20) -> 0
C21: ='Role Selection'!F18 -> /// | D21: ='Role Selection'!HO18 -> 0 | E21: ='Role Selection'!H18 -> 0 | G21: =F21 -> 0 | H21: =G21 -> 0 | I21: =H21 -> 0 | J21: =I21 -> 0 | K21: =J21 -> 0 | L21: =K21 -> 0 | M21: =L21 -> 0 | N21: =M21 -> 0 | ... Q21: =P21 -> 0 | S21: =+Q21 -> 0 | T21: =S21 -> 0 | U21: =T21 -> 0 | V21: =U21 -> 0 | W21: =V21 -> 0 | X21: =W21 -> 0 | Y21: =X21 -> 0 | Z21: =Y21 -> 0 | AA21: =Z21 -> 0 | ... AD21: =AC21 -> 0 | AF21: =AD21 -> 0 | AG21: =AF21 -> 0 | AH21: =AG21 -> 0 | AI21: =AH21 -> 0 | AJ21: =AI21 -> 0 | AK21: =AJ21 -> 0 | AL21: =AK21 -> 0 | AM21: =AL21 -> 0 | AN21: =AM21 -> 0 | ... AQ21: =AP21 -> 0 | AS21: =AQ21 -> 0 | AT21: =AS21 -> 0 | AU21: =AT21 -> 0 | AV21: =AU21 -> 0 | AW21: =AV21 -> 0 | AX21: =AW21 -> 0 | AY21: =AX21 -> 0 | AZ21: =AY21 -> 0 | BA21: =AZ21 -> 0 | ... BD21: =BC21 -> 0 | BF21: =BD21 -> 0 | BG21: =BF21 -> 0 | BH21: =BG21 -> 0 | BI21: =BH21 -> 0 | BJ21: =BI21 -> 0 | BK21: =BJ21 -> 0 | BL21: =BK21 -> 0 | BM21: =BL21 -> 0 | BN21: =BM21 -> 0 | ... BQ21: =BP21 -> 0 | BS21: =BQ21 -> 0 | BT21: =BS21 -> 0 | BU21: =BT21 -> 0 | BV21: =BU21 -> 0 | BW21: =BV21 -> 0 | BX21: =BW21 -> 0 | BY21: =BX21 -> 0 | BZ21: =BY21 -> 0 | CA21: =BZ21 -> 0 | ... CD21: =CC21 -> 0 | CF21: =CD21 -> 0 | CG21: =CF21 -> 0 | CH21: =CG21 -> 0 | CI21: =CH21 -> 0 | CJ21: =CI21 -> 0 | CK21: =CJ21 -> 0 | CL21: =CK21 -> 0 | CM21: =CL21 -> 0 | CN21: =CM21 -> 0 | ... CQ21: =CP21 -> 0 | CS21: =CQ21 -> 0 | CT21: =CS21 -> 0 | CU21: =CT21 -> 0 | CV21: =CU21 -> 0 | CW21: =CV21 -> 0 | CX21: =CW21 -> 0 | CY21: =CX21 -> 0 | CZ21: =CY21 -> 0 | DA21: =CZ21 -> 0 | ... DD21: =DC21 -> 0 | DF21: =DD21 -> 0 | DG21: =DF21 -> 0 | DH21: =DG21 -> 0 | DI21: =DH21 -> 0 | DJ21: =DI21 -> 0 | DK21: =DJ21 -> 0 | DL21: =DK21 -> 0 | DM21: =DL21 -> 0 | DN21: =DM21 -> 0 | ... DQ21: =DP21 -> 0 | DS21: =SUM(F21:Q21)+SUM(S21:AD21)+SUM(AF21:AQ21)+SUM(AS21:BD21)+SUM(BF21:BQ21)+SUM(BS21:CD21)+SUM(CF21:CQ21)+SUM(CS21:DD21)+SUM(DF21:DQ21) -> 0
A22: 1 | B22: 7 | C22: ='Role Selection'!F19 -> /// | D22: ='Role Selection'!HO19 -> 0 | E22: ='Role Selection'!H19 -> 0 | G22: =F22 -> 0 | H22: =G22 -> 0 | I22: =H22 -> 0 | J22: =I22 -> 0 | K22: =J22 -> 0 | L22: =K22 -> 0 | M22: =L22 -> 0 | N22: =M22 -> 0 | ... Q22: =P22 -> 0 | S22: =+Q22 -> 0 | T22: =S22 -> 0 | U22: =T22 -> 0 | V22: =U22 -> 0 | W22: =V22 -> 0 | X22: =W22 -> 0 | Y22: =X22 -> 0 | Z22: =Y22 -> 0 | AA22: =Z22 -> 0 | ... AD22: =AC22 -> 0 | AF22: =AD22 -> 0 | AG22: =AF22 -> 0 | AH22: =AG22 -> 0 | AI22: =AH22 -> 0 | AJ22: =AI22 -> 0 | AK22: =AJ22 -> 0 | AL22: =AK22 -> 0 | AM22: =AL22 -> 0 | AN22: =AM22 -> 0 | ... AQ22: =AP22 -> 0 | AS22: =AQ22 -> 0 | AT22: =AS22 -> 0 | AU22: =AT22 -> 0 | AV22: =AU22 -> 0 | AW22: =AV22 -> 0 | AX22: =AW22 -> 0 | AY22: =AX22 -> 0 | AZ22: =AY22 -> 0 | BA22: =AZ22 -> 0 | ... BD22: =BC22 -> 0 | BF22: =BD22 -> 0 | BG22: =BF22 -> 0 | BH22: =BG22 -> 0 | BI22: =BH22 -> 0 | BJ22: =BI22 -> 0 | BK22: =BJ22 -> 0 | BL22: =BK22 -> 0 | BM22: =BL22 -> 0 | BN22: =BM22 -> 0 | ... BQ22: =BP22 -> 0 | BS22: =BQ22 -> 0 | BT22: =BS22 -> 0 | BU22: =BT22 -> 0 | BV22: =BU22 -> 0 | BW22: =BV22 -> 0 | BX22: =BW22 -> 0 | BY22: =BX22 -> 0 | BZ22: =BY22 -> 0 | CA22: =BZ22 -> 0 | ... CD22: =CC22 -> 0 | CF22: =CD22 -> 0 | CG22: =CF22 -> 0 | CH22: =CG22 -> 0 | CI22: =CH22 -> 0 | CJ22: =CI22 -> 0 | CK22: =CJ22 -> 0 | CL22: =CK22 -> 0 | CM22: =CL22 -> 0 | CN22: =CM22 -> 0 | ... CQ22: =CP22 -> 0 | CS22: =CQ22 -> 0 | CT22: =CS22 -> 0 | CU22: =CT22 -> 0 | CV22: =CU22 -> 0 | CW22: =CV22 -> 0 | CX22: =CW22 -> 0 | CY22: =CX22 -> 0 | CZ22: =CY22 -> 0 | DA22: =CZ22 -> 0 | ... DD22: =DC22 -> 0 | DF22: =DD22 -> 0 | DG22: =DF22 -> 0 | DH22: =DG22 -> 0 | DI22: =DH22 -> 0 | DJ22: =DI22 -> 0 | DK22: =DJ22 -> 0 | DL22: =DK22 -> 0 | DM22: =DL22 -> 0 | DN22: =DM22 -> 0 | ... DQ22: =DP22 -> 0 | DS22: =SUM(F22:Q22)+SUM(S22:AD22)+SUM(AF22:AQ22)+SUM(AS22:BD22)+SUM(BF22:BQ22)+SUM(BS22:CD22)+SUM(CF22:CQ22)+SUM(CS22:DD22)+SUM(DF22:DQ22) -> 0
C23: ='Role Selection'!F20 -> /// | D23: ='Role Selection'!HO20 -> 0 | E23: ='Role Selection'!H20 -> 0 | G23: =F23 -> 0 | H23: =G23 -> 0 | I23: =H23 -> 0 | J23: =I23 -> 0 | K23: =J23 -> 0 | L23: =K23 -> 0 | M23: =L23 -> 0 | N23: =M23 -> 0 | ... Q23: =P23 -> 0 | S23: =+Q23 -> 0 | T23: =S23 -> 0 | U23: =T23 -> 0 | V23: =U23 -> 0 | W23: =V23 -> 0 | X23: =W23 -> 0 | Y23: =X23 -> 0 | Z23: =Y23 -> 0 | AA23: =Z23 -> 0 | ... AD23: =AC23 -> 0 | AF23: =AD23 -> 0 | AG23: =AF23 -> 0 | AH23: =AG23 -> 0 | AI23: =AH23 -> 0 | AJ23: =AI23 -> 0 | AK23: =AJ23 -> 0 | AL23: =AK23 -> 0 | AM23: =AL23 -> 0 | AN23: =AM23 -> 0 | ... AQ23: =AP23 -> 0 | AS23: =AQ23 -> 0 | AT23: =AS23 -> 0 | AU23: =AT23 -> 0 | AV23: =AU23 -> 0 | AW23: =AV23 -> 0 | AX23: =AW23 -> 0 | AY23: =AX23 -> 0 | AZ23: =AY23 -> 0 | BA23: =AZ23 -> 0 | ... BD23: =BC23 -> 0 | BF23: =BD23 -> 0 | BG23: =BF23 -> 0 | BH23: =BG23 -> 0 | BI23: =BH23 -> 0 | BJ23: =BI23 -> 0 | BK23: =BJ23 -> 0 | BL23: =BK23 -> 0 | BM23: =BL23 -> 0 | BN23: =BM23 -> 0 | ... BQ23: =BP23 -> 0 | BS23: =BQ23 -> 0 | BT23: =BS23 -> 0 | BU23: =BT23 -> 0 | BV23: =BU23 -> 0 | BW23: =BV23 -> 0 | BX23: =BW23 -> 0 | BY23: =BX23 -> 0 | BZ23: =BY23 -> 0 | CA23: =BZ23 -> 0 | ... CD23: =CC23 -> 0 | CF23: =CD23 -> 0 | CG23: =CF23 -> 0 | CH23: =CG23 -> 0 | CI23: =CH23 -> 0 | CJ23: =CI23 -> 0 | CK23: =CJ23 -> 0 | CL23: =CK23 -> 0 | CM23: =CL23 -> 0 | CN23: =CM23 -> 0 | ... CQ23: =CP23 -> 0 | CS23: =CQ23 -> 0 | CT23: =CS23 -> 0 | CU23: =CT23 -> 0 | CV23: =CU23 -> 0 | CW23: =CV23 -> 0 | CX23: =CW23 -> 0 | CY23: =CX23 -> 0 | CZ23: =CY23 -> 0 | DA23: =CZ23 -> 0 | ... DD23: =DC23 -> 0 | DF23: =DD23 -> 0 | DG23: =DF23 -> 0 | DH23: =DG23 -> 0 | DI23: =DH23 -> 0 | DJ23: =DI23 -> 0 | DK23: =DJ23 -> 0 | DL23: =DK23 -> 0 | DM23: =DL23 -> 0 | DN23: =DM23 -> 0 | ... DQ23: =DP23 -> 0 | DS23: =SUM(F23:Q23)+SUM(S23:AD23)+SUM(AF23:AQ23)+SUM(AS23:BD23)+SUM(BF23:BQ23)+SUM(BS23:CD23)+SUM(CF23:CQ23)+SUM(CS23:DD23)+SUM(DF23:DQ23) -> 0
C24: ='Role Selection'!F21 -> /// | D24: ='Role Selection'!HO21 -> 0 | E24: ='Role Selection'!H21 -> 0 | G24: =F24 -> 0 | H24: =G24 -> 0 | I24: =H24 -> 0 | J24: =I24 -> 0 | K24: =J24 -> 0 | L24: =K24 -> 0 | M24: =L24 -> 0 | N24: =M24 -> 0 | ... Q24: =P24 -> 0 | S24: =+Q24 -> 0 | T24: =S24 -> 0 | U24: =T24 -> 0 | V24: =U24 -> 0 | W24: =V24 -> 0 | X24: =W24 -> 0 | Y24: =X24 -> 0 | Z24: =Y24 -> 0 | AA24: =Z24 -> 0 | ... AD24: =AC24 -> 0 | AF24: =AD24 -> 0 | AG24: =AF24 -> 0 | AH24: =AG24 -> 0 | AI24: =AH24 -> 0 | AJ24: =AI24 -> 0 | AK24: =AJ24 -> 0 | AL24: =AK24 -> 0 | AM24: =AL24 -> 0 | AN24: =AM24 -> 0 | ... AQ24: =AP24 -> 0 | AS24: =AQ24 -> 0 | AT24: =AS24 -> 0 | AU24: =AT24 -> 0 | AV24: =AU24 -> 0 | AW24: =AV24 -> 0 | AX24: =AW24 -> 0 | AY24: =AX24 -> 0 | AZ24: =AY24 -> 0 | BA24: =AZ24 -> 0 | ... BD24: =BC24 -> 0 | BF24: =BD24 -> 0 | BG24: =BF24 -> 0 | BH24: =BG24 -> 0 | BI24: =BH24 -> 0 | BJ24: =BI24 -> 0 | BK24: =BJ24 -> 0 | BL24: =BK24 -> 0 | BM24: =BL24 -> 0 | BN24: =BM24 -> 0 | ... BQ24: =BP24 -> 0 | BS24: =BQ24 -> 0 | BT24: =BS24 -> 0 | BU24: =BT24 -> 0 | BV24: =BU24 -> 0 | BW24: =BV24 -> 0 | BX24: =BW24 -> 0 | BY24: =BX24 -> 0 | BZ24: =BY24 -> 0 | CA24: =BZ24 -> 0 | ... CD24: =CC24 -> 0 | CF24: =CD24 -> 0 | CG24: =CF24 -> 0 | CH24: =CG24 -> 0 | CI24: =CH24 -> 0 | CJ24: =CI24 -> 0 | CK24: =CJ24 -> 0 | CL24: =CK24 -> 0 | CM24: =CL24 -> 0 | CN24: =CM24 -> 0 | ... CQ24: =CP24 -> 0 | CS24: =CQ24 -> 0 | CT24: =CS24 -> 0 | CU24: =CT24 -> 0 | CV24: =CU24 -> 0 | CW24: =CV24 -> 0 | CX24: =CW24 -> 0 | CY24: =CX24 -> 0 | CZ24: =CY24 -> 0 | DA24: =CZ24 -> 0 | ... DD24: =DC24 -> 0 | DF24: =DD24 -> 0 | DG24: =DF24 -> 0 | DH24: =DG24 -> 0 | DI24: =DH24 -> 0 | DJ24: =DI24 -> 0 | DK24: =DJ24 -> 0 | DL24: =DK24 -> 0 | DM24: =DL24 -> 0 | DN24: =DM24 -> 0 | ... DQ24: =DP24 -> 0 | DS24: =SUM(F24:Q24)+SUM(S24:AD24)+SUM(AF24:AQ24)+SUM(AS24:BD24)+SUM(BF24:BQ24)+SUM(BS24:CD24)+SUM(CF24:CQ24)+SUM(CS24:DD24)+SUM(DF24:DQ24) -> 0
A25: 1 | B25: 8 | C25: ='Role Selection'!F22 -> /// | D25: ='Role Selection'!HO22 -> 0 | E25: ='Role Selection'!H22 -> 0 | G25: =F25 -> 0 | H25: =G25 -> 0 | I25: =H25 -> 0 | J25: =I25 -> 0 | K25: =J25 -> 0 | L25: =K25 -> 0 | M25: =L25 -> 0 | N25: =M25 -> 0 | ... Q25: =P25 -> 0 | S25: =+Q25 -> 0 | T25: =S25 -> 0 | U25: =T25 -> 0 | V25: =U25 -> 0 | W25: =V25 -> 0 | X25: =W25 -> 0 | Y25: =X25 -> 0 | Z25: =Y25 -> 0 | AA25: =Z25 -> 0 | ... AD25: =AC25 -> 0 | AF25: =AD25 -> 0 | AG25: =AF25 -> 0 | AH25: =AG25 -> 0 | AI25: =AH25 -> 0 | AJ25: =AI25 -> 0 | AK25: =AJ25 -> 0 | AL25: =AK25 -> 0 | AM25: =AL25 -> 0 | AN25: =AM25 -> 0 | ... AQ25: =AP25 -> 0 | AS25: =AQ25 -> 0 | AT25: =AS25 -> 0 | AU25: =AT25 -> 0 | AV25: =AU25 -> 0 | AW25: =AV25 -> 0 | AX25: =AW25 -> 0 | AY25: =AX25 -> 0 | AZ25: =AY25 -> 0 | BA25: =AZ25 -> 0 | ... BD25: =BC25 -> 0 | BF25: =BD25 -> 0 | BG25: =BF25 -> 0 | BH25: =BG25 -> 0 | BI25: =BH25 -> 0 | BJ25: =BI25 -> 0 | BK25: =BJ25 -> 0 | BL25: =BK25 -> 0 | BM25: =BL25 -> 0 | BN25: =BM25 -> 0 | ... BQ25: =BP25 -> 0 | BS25: =BQ25 -> 0 | BT25: =BS25 -> 0 | BU25: =BT25 -> 0 | BV25: =BU25 -> 0 | BW25: =BV25 -> 0 | BX25: =BW25 -> 0 | BY25: =BX25 -> 0 | BZ25: =BY25 -> 0 | CA25: =BZ25 -> 0 | ... CD25: =CC25 -> 0 | CF25: =CD25 -> 0 | CG25: =CF25 -> 0 | CH25: =CG25 -> 0 | CI25: =CH25 -> 0 | CJ25: =CI25 -> 0 | CK25: =CJ25 -> 0 | CL25: =CK25 -> 0 | CM25: =CL25 -> 0 | CN25: =CM25 -> 0 | ... CQ25: =CP25 -> 0 | CS25: =CQ25 -> 0 | CT25: =CS25 -> 0 | CU25: =CT25 -> 0 | CV25: =CU25 -> 0 | CW25: =CV25 -> 0 | CX25: =CW25 -> 0 | CY25: =CX25 -> 0 | CZ25: =CY25 -> 0 | DA25: =CZ25 -> 0 | ... DD25: =DC25 -> 0 | DF25: =DD25 -> 0 | DG25: =DF25 -> 0 | DH25: =DG25 -> 0 | DI25: =DH25 -> 0 | DJ25: =DI25 -> 0 | DK25: =DJ25 -> 0 | DL25: =DK25 -> 0 | DM25: =DL25 -> 0 | DN25: =DM25 -> 0 | ... DQ25: =DP25 -> 0 | DS25: =SUM(F25:Q25)+SUM(S25:AD25)+SUM(AF25:AQ25)+SUM(AS25:BD25)+SUM(BF25:BQ25)+SUM(BS25:CD25)+SUM(CF25:CQ25)+SUM(CS25:DD25)+SUM(DF25:DQ25) -> 0
C26: ='Role Selection'!F23 -> /// | D26: ='Role Selection'!HO23 -> 0 | E26: ='Role Selection'!H23 -> 0 | G26: =F26 -> 0 | H26: =G26 -> 0 | I26: =H26 -> 0 | J26: =I26 -> 0 | K26: =J26 -> 0 | L26: =K26 -> 0 | M26: =L26 -> 0 | N26: =M26 -> 0 | ... Q26: =P26 -> 0 | S26: =+Q26 -> 0 | T26: =S26 -> 0 | U26: =T26 -> 0 | V26: =U26 -> 0 | W26: =V26 -> 0 | X26: =W26 -> 0 | Y26: =X26 -> 0 | Z26: =Y26 -> 0 | AA26: =Z26 -> 0 | ... AD26: =AC26 -> 0 | AF26: =AD26 -> 0 | AG26: =AF26 -> 0 | AH26: =AG26 -> 0 | AI26: =AH26 -> 0 | AJ26: =AI26 -> 0 | AK26: =AJ26 -> 0 | AL26: =AK26 -> 0 | AM26: =AL26 -> 0 | AN26: =AM26 -> 0 | ... AQ26: =AP26 -> 0 | AS26: =AQ26 -> 0 | AT26: =AS26 -> 0 | AU26: =AT26 -> 0 | AV26: =AU26 -> 0 | AW26: =AV26 -> 0 | AX26: =AW26 -> 0 | AY26: =AX26 -> 0 | AZ26: =AY26 -> 0 | BA26: =AZ26 -> 0 | ... BD26: =BC26 -> 0 | BF26: =BD26 -> 0 | BG26: =BF26 -> 0 | BH26: =BG26 -> 0 | BI26: =BH26 -> 0 | BJ26: =BI26 -> 0 | BK26: =BJ26 -> 0 | BL26: =BK26 -> 0 | BM26: =BL26 -> 0 | BN26: =BM26 -> 0 | ... BQ26: =BP26 -> 0 | BS26: =BQ26 -> 0 | BT26: =BS26 -> 0 | BU26: =BT26 -> 0 | BV26: =BU26 -> 0 | BW26: =BV26 -> 0 | BX26: =BW26 -> 0 | BY26: =BX26 -> 0 | BZ26: =BY26 -> 0 | CA26: =BZ26 -> 0 | ... CD26: =CC26 -> 0 | CF26: =CD26 -> 0 | CG26: =CF26 -> 0 | CH26: =CG26 -> 0 | CI26: =CH26 -> 0 | CJ26: =CI26 -> 0 | CK26: =CJ26 -> 0 | CL26: =CK26 -> 0 | CM26: =CL26 -> 0 | CN26: =CM26 -> 0 | ... CQ26: =CP26 -> 0 | CS26: =CQ26 -> 0 | CT26: =CS26 -> 0 | CU26: =CT26 -> 0 | CV26: =CU26 -> 0 | CW26: =CV26 -> 0 | CX26: =CW26 -> 0 | CY26: =CX26 -> 0 | CZ26: =CY26 -> 0 | DA26: =CZ26 -> 0 | ... DD26: =DC26 -> 0 | DF26: =DD26 -> 0 | DG26: =DF26 -> 0 | DH26: =DG26 -> 0 | DI26: =DH26 -> 0 | DJ26: =DI26 -> 0 | DK26: =DJ26 -> 0 | DL26: =DK26 -> 0 | DM26: =DL26 -> 0 | DN26: =DM26 -> 0 | ... DQ26: =DP26 -> 0 | DS26: =SUM(F26:Q26)+SUM(S26:AD26)+SUM(AF26:AQ26)+SUM(AS26:BD26)+SUM(BF26:BQ26)+SUM(BS26:CD26)+SUM(CF26:CQ26)+SUM(CS26:DD26)+SUM(DF26:DQ26) -> 0
A27: 1 | B27: 9 | C27: ='Role Selection'!F24 -> /// | D27: ='Role Selection'!HO24 -> 0 | E27: ='Role Selection'!H24 -> 0 | G27: =F27 -> 0 | H27: =G27 -> 0 | I27: =H27 -> 0 | J27: =I27 -> 0 | K27: =J27 -> 0 | L27: =K27 -> 0 | M27: =L27 -> 0 | N27: =M27 -> 0 | ... Q27: =P27 -> 0 | S27: =+Q27 -> 0 | T27: =S27 -> 0 | U27: =T27 -> 0 | V27: =U27 -> 0 | W27: =V27 -> 0 | X27: =W27 -> 0 | Y27: =X27 -> 0 | Z27: =Y27 -> 0 | AA27: =Z27 -> 0 | ... AD27: =AC27 -> 0 | AF27: =AD27 -> 0 | AG27: =AF27 -> 0 | AH27: =AG27 -> 0 | AI27: =AH27 -> 0 | AJ27: =AI27 -> 0 | AK27: =AJ27 -> 0 | AL27: =AK27 -> 0 | AM27: =AL27 -> 0 | AN27: =AM27 -> 0 | ... AQ27: =AP27 -> 0 | AS27: =AQ27 -> 0 | AT27: =AS27 -> 0 | AU27: =AT27 -> 0 | AV27: =AU27 -> 0 | AW27: =AV27 -> 0 | AX27: =AW27 -> 0 | AY27: =AX27 -> 0 | AZ27: =AY27 -> 0 | BA27: =AZ27 -> 0 | ... BD27: =BC27 -> 0 | BF27: =BD27 -> 0 | BG27: =BF27 -> 0 | BH27: =BG27 -> 0 | BI27: =BH27 -> 0 | BJ27: =BI27 -> 0 | BK27: =BJ27 -> 0 | BL27: =BK27 -> 0 | BM27: =BL27 -> 0 | BN27: =BM27 -> 0 | ... BQ27: =BP27 -> 0 | BS27: =BQ27 -> 0 | BT27: =BS27 -> 0 | BU27: =BT27 -> 0 | BV27: =BU27 -> 0 | BW27: =BV27 -> 0 | BX27: =BW27 -> 0 | BY27: =BX27 -> 0 | BZ27: =BY27 -> 0 | CA27: =BZ27 -> 0 | ... CD27: =CC27 -> 0 | CF27: =CD27 -> 0 | CG27: =CF27 -> 0 | CH27: =CG27 -> 0 | CI27: =CH27 -> 0 | CJ27: =CI27 -> 0 | CK27: =CJ27 -> 0 | CL27: =CK27 -> 0 | CM27: =CL27 -> 0 | CN27: =CM27 -> 0 | ... CQ27: =CP27 -> 0 | CS27: =CQ27 -> 0 | CT27: =CS27 -> 0 | CU27: =CT27 -> 0 | CV27: =CU27 -> 0 | CW27: =CV27 -> 0 | CX27: =CW27 -> 0 | CY27: =CX27 -> 0 | CZ27: =CY27 -> 0 | DA27: =CZ27 -> 0 | ... DD27: =DC27 -> 0 | DF27: =DD27 -> 0 | DG27: =DF27 -> 0 | DH27: =DG27 -> 0 | DI27: =DH27 -> 0 | DJ27: =DI27 -> 0 | DK27: =DJ27 -> 0 | DL27: =DK27 -> 0 | DM27: =DL27 -> 0 | DN27: =DM27 -> 0 | ... DQ27: =DP27 -> 0 | DS27: =SUM(F27:Q27)+SUM(S27:AD27)+SUM(AF27:AQ27)+SUM(AS27:BD27)+SUM(BF27:BQ27)+SUM(BS27:CD27)+SUM(CF27:CQ27)+SUM(CS27:DD27)+SUM(DF27:DQ27) -> 0
C28: ='Role Selection'!F25 -> /// | D28: ='Role Selection'!HO25 -> 0 | E28: ='Role Selection'!H25 -> 0 | G28: =F28 -> 0 | H28: =G28 -> 0 | I28: =H28 -> 0 | J28: =I28 -> 0 | K28: =J28 -> 0 | L28: =K28 -> 0 | M28: =L28 -> 0 | N28: =M28 -> 0 | ... Q28: =P28 -> 0 | S28: =+Q28 -> 0 | T28: =S28 -> 0 | U28: =T28 -> 0 | V28: =U28 -> 0 | W28: =V28 -> 0 | X28: =W28 -> 0 | Y28: =X28 -> 0 | Z28: =Y28 -> 0 | AA28: =Z28 -> 0 | ... AD28: =AC28 -> 0 | AF28: =AD28 -> 0 | AG28: =AF28 -> 0 | AH28: =AG28 -> 0 | AI28: =AH28 -> 0 | AJ28: =AI28 -> 0 | AK28: =AJ28 -> 0 | AL28: =AK28 -> 0 | AM28: =AL28 -> 0 | AN28: =AM28 -> 0 | ... AQ28: =AP28 -> 0 | AS28: =AQ28 -> 0 | AT28: =AS28 -> 0 | AU28: =AT28 -> 0 | AV28: =AU28 -> 0 | AW28: =AV28 -> 0 | AX28: =AW28 -> 0 | AY28: =AX28 -> 0 | AZ28: =AY28 -> 0 | BA28: =AZ28 -> 0 | ... BD28: =BC28 -> 0 | BF28: =BD28 -> 0 | BG28: =BF28 -> 0 | BH28: =BG28 -> 0 | BI28: =BH28 -> 0 | BJ28: =BI28 -> 0 | BK28: =BJ28 -> 0 | BL28: =BK28 -> 0 | BM28: =BL28 -> 0 | BN28: =BM28 -> 0 | ... BQ28: =BP28 -> 0 | BS28: =BQ28 -> 0 | BT28: =BS28 -> 0 | BU28: =BT28 -> 0 | BV28: =BU28 -> 0 | BW28: =BV28 -> 0 | BX28: =BW28 -> 0 | BY28: =BX28 -> 0 | BZ28: =BY28 -> 0 | CA28: =BZ28 -> 0 | ... CD28: =CC28 -> 0 | CF28: =CD28 -> 0 | CG28: =CF28 -> 0 | CH28: =CG28 -> 0 | CI28: =CH28 -> 0 | CJ28: =CI28 -> 0 | CK28: =CJ28 -> 0 | CL28: =CK28 -> 0 | CM28: =CL28 -> 0 | CN28: =CM28 -> 0 | ... CQ28: =CP28 -> 0 | CS28: =CQ28 -> 0 | CT28: =CS28 -> 0 | CU28: =CT28 -> 0 | CV28: =CU28 -> 0 | CW28: =CV28 -> 0 | CX28: =CW28 -> 0 | CY28: =CX28 -> 0 | CZ28: =CY28 -> 0 | DA28: =CZ28 -> 0 | ... DD28: =DC28 -> 0 | DF28: =DD28 -> 0 | DG28: =DF28 -> 0 | DH28: =DG28 -> 0 | DI28: =DH28 -> 0 | DJ28: =DI28 -> 0 | DK28: =DJ28 -> 0 | DL28: =DK28 -> 0 | DM28: =DL28 -> 0 | DN28: =DM28 -> 0 | ... DQ28: =DP28 -> 0 | DS28: =SUM(F28:Q28)+SUM(S28:AD28)+SUM(AF28:AQ28)+SUM(AS28:BD28)+SUM(BF28:BQ28)+SUM(BS28:CD28)+SUM(CF28:CQ28)+SUM(CS28:DD28)+SUM(DF28:DQ28) -> 0
C29: ='Role Selection'!F26 -> /// | D29: ='Role Selection'!HO26 -> 0 | E29: ='Role Selection'!H26 -> 0 | G29: =F29 -> 0 | H29: =G29 -> 0 | I29: =H29 -> 0 | J29: =I29 -> 0 | K29: =J29 -> 0 | L29: =K29 -> 0 | M29: =L29 -> 0 | N29: =M29 -> 0 | ... Q29: =P29 -> 0 | S29: =+Q29 -> 0 | T29: =S29 -> 0 | U29: =T29 -> 0 | V29: =U29 -> 0 | W29: =V29 -> 0 | X29: =W29 -> 0 | Y29: =X29 -> 0 | Z29: =Y29 -> 0 | AA29: =Z29 -> 0 | ... AD29: =AC29 -> 0 | AF29: =AD29 -> 0 | AG29: =AF29 -> 0 | AH29: =AG29 -> 0 | AI29: =AH29 -> 0 | AJ29: =AI29 -> 0 | AK29: =AJ29 -> 0 | AL29: =AK29 -> 0 | AM29: =AL29 -> 0 | AN29: =AM29 -> 0 | ... AQ29: =AP29 -> 0 | AS29: =AQ29 -> 0 | AT29: =AS29 -> 0 | AU29: =AT29 -> 0 | AV29: =AU29 -> 0 | AW29: =AV29 -> 0 | AX29: =AW29 -> 0 | AY29: =AX29 -> 0 | AZ29: =AY29 -> 0 | BA29: =AZ29 -> 0 | ... BD29: =BC29 -> 0 | BF29: =BD29 -> 0 | BG29: =BF29 -> 0 | BH29: =BG29 -> 0 | BI29: =BH29 -> 0 | BJ29: =BI29 -> 0 | BK29: =BJ29 -> 0 | BL29: =BK29 -> 0 | BM29: =BL29 -> 0 | BN29: =BM29 -> 0 | ... BQ29: =BP29 -> 0 | BS29: =BQ29 -> 0 | BT29: =BS29 -> 0 | BU29: =BT29 -> 0 | BV29: =BU29 -> 0 | BW29: =BV29 -> 0 | BX29: =BW29 -> 0 | BY29: =BX29 -> 0 | BZ29: =BY29 -> 0 | CA29: =BZ29 -> 0 | ... CD29: =CC29 -> 0 | CF29: =CD29 -> 0 | CG29: =CF29 -> 0 | CH29: =CG29 -> 0 | CI29: =CH29 -> 0 | CJ29: =CI29 -> 0 | CK29: =CJ29 -> 0 | CL29: =CK29 -> 0 | CM29: =CL29 -> 0 | CN29: =CM29 -> 0 | ... CQ29: =CP29 -> 0 | CS29: =CQ29 -> 0 | CT29: =CS29 -> 0 | CU29: =CT29 -> 0 | CV29: =CU29 -> 0 | CW29: =CV29 -> 0 | CX29: =CW29 -> 0 | CY29: =CX29 -> 0 | CZ29: =CY29 -> 0 | DA29: =CZ29 -> 0 | ... DD29: =DC29 -> 0 | DF29: =DD29 -> 0 | DG29: =DF29 -> 0 | DH29: =DG29 -> 0 | DI29: =DH29 -> 0 | DJ29: =DI29 -> 0 | DK29: =DJ29 -> 0 | DL29: =DK29 -> 0 | DM29: =DL29 -> 0 | DN29: =DM29 -> 0 | ... DQ29: =DP29 -> 0 | DS29: =SUM(F29:Q29)+SUM(S29:AD29)+SUM(AF29:AQ29)+SUM(AS29:BD29)+SUM(BF29:BQ29)+SUM(BS29:CD29)+SUM(CF29:CQ29)+SUM(CS29:DD29)+SUM(DF29:DQ29) -> 0
C30: Open | F30: 0 | G30: =F30 -> 0 | H30: =G30 -> 0 | I30: =H30 -> 0 | J30: =I30 -> 0 | K30: =J30 -> 0 | L30: =K30 -> 0 | M30: =L30 -> 0 | N30: =M30 -> 0 | ... Q30: =P30 -> 0 | S30: =Q30 -> 0 | T30: =S30 -> 0 | U30: =T30 -> 0 | V30: =U30 -> 0 | W30: =V30 -> 0 | X30: =W30 -> 0 | Y30: =X30 -> 0 | Z30: =Y30 -> 0 | AA30: =Z30 -> 0 | ... AD30: =AC30 -> 0 | AR30: =AD30*AR$4/12 -> 0 | BE30: =AR30*BE$4/12 -> 0 | BR30: =BE30*BR$4/12 -> 0 | CE30: =BR30*CE$4/12 -> 0 | CR30: =CE30*CR$4/12 -> 0 | DE30: =CR30*DE$4/12 -> 0 | DR30: =DE30*DR$4/12 -> 0
C31: Open | F31: 0 | G31: =F31 -> 0 | H31: =G31 -> 0 | I31: =H31 -> 0 | J31: =I31 -> 0 | K31: =J31 -> 0 | L31: =K31 -> 0 | M31: =L31 -> 0 | N31: =M31 -> 0 | ... Q31: =P31 -> 0 | S31: =Q31 -> 0 | T31: =S31 -> 0 | U31: =T31 -> 0 | V31: =U31 -> 0 | W31: =V31 -> 0 | X31: =W31 -> 0 | Y31: =X31 -> 0 | Z31: =Y31 -> 0 | AA31: =Z31 -> 0 | ... AD31: =AC31 -> 0 | AR31: =AD31*AR$4/12 -> 0 | BE31: =AR31*BE$4/12 -> 0 | BR31: =BE31*BR$4/12 -> 0 | CE31: =BR31*CE$4/12 -> 0 | CR31: =CE31*CR$4/12 -> 0 | DE31: =CR31*DE$4/12 -> 0 | DR31: =DE31*DR$4/12 -> 0
C32: Subtotal | F32: =SUM(F7:F31) -> 0 | G32: =SUM(G7:G31) -> 0 | H32: =SUM(H7:H31) -> 0 | I32: =SUM(I7:I31) -> 0 | J32: =SUM(J7:J31) -> 0 | K32: =SUM(K7:K31) -> 0 | L32: =SUM(L7:L31) -> 0 | M32: =SUM(M7:M31) -> 0 | ... DT32: =SUM(DT7:DT31) -> 0
C34: Onsite Deputed Short term (<= 3 months)
C35: =C9 -> IT/JavaNetColdFusionIT/DeveloperJavaNetColdFusion/Junior | D35: =+D9 -> 0 | E35: =E9 -> B2 AP1 / B2 AP2 (0.6 to 3 yrs) | G35: =F35 -> 0 | H35: =G35 -> 0 | I35: =H35 -> 0 | J35: =I35 -> 0 | K35: =J35 -> 0 | L35: =K35 -> 0 | M35: =L35 -> 0 | N35: =M35 -> 0 | ... Q35: =P35 -> 0 | S35: =+Q35 -> 0 | T35: =S35 -> 0 | U35: =T35 -> 0 | V35: =U35 -> 0 | W35: =V35 -> 0 | X35: =W35 -> 0 | Y35: =X35 -> 0 | Z35: =Y35 -> 0 | AA35: =Z35 -> 0 | ... AD35: =AC35 -> 0 | AF35: =AD35 -> 0 | AG35: =AF35 -> 0 | AH35: =AG35 -> 0 | AI35: =AH35 -> 0 | AJ35: =AI35 -> 0 | AK35: =AJ35 -> 0 | AL35: =AK35 -> 0 | AM35: =AL35 -> 0 | AN35: =AM35 -> 0 | ... AQ35: =AP35 -> 0 | AS35: =AQ35 -> 0 | AT35: =AS35 -> 0 | AU35: =AT35 -> 0 | AV35: =AU35 -> 0 | AW35: =AV35 -> 0 | AX35: =AW35 -> 0 | AY35: =AX35 -> 0 | AZ35: =AY35 -> 0 | BA35: =AZ35 -> 0 | ... BD35: =BC35 -> 0 | BF35: =BD35 -> 0 | BG35: =BF35 -> 0 | BH35: =BG35 -> 0 | BI35: =BH35 -> 0 | BJ35: =BI35 -> 0 | BK35: =BJ35 -> 0 | BL35: =BK35 -> 0 | BM35: =BL35 -> 0 | BN35: =BM35 -> 0 | ... BQ35: =BP35 -> 0 | BS35: =BQ35 -> 0 | BT35: =BS35 -> 0 | BU35: =BT35 -> 0 | BV35: =BU35 -> 0 | BW35: =BV35 -> 0 | BX35: =BW35 -> 0 | BY35: =BX35 -> 0 | BZ35: =BY35 -> 0 | CA35: =BZ35 -> 0 | ... CD35: =CC35 -> 0 | CF35: =CD35 -> 0 | CG35: =CF35 -> 0 | CH35: =CG35 -> 0 | CI35: =CH35 -> 0 | CJ35: =CI35 -> 0 | CK35: =CJ35 -> 0 | CL35: =CK35 -> 0 | CM35: =CL35 -> 0 | CN35: =CM35 -> 0 | ... CQ35: =CP35 -> 0 | CS35: =CQ35 -> 0 | CT35: =CS35 -> 0 | CU35: =CT35 -> 0 | CV35: =CU35 -> 0 | CW35: =CV35 -> 0 | CX35: =CW35 -> 0 | CY35: =CX35 -> 0 | CZ35: =CY35 -> 0 | DA35: =CZ35 -> 0 | ... DD35: =DC35 -> 0 | DF35: =DD35 -> 0 | DG35: =DF35 -> 0 | DH35: =DG35 -> 0 | DI35: =DH35 -> 0 | DJ35: =DI35 -> 0 | DK35: =DJ35 -> 0 | DL35: =DK35 -> 0 | DM35: =DL35 -> 0 | DN35: =DM35 -> 0 | ... DQ35: =DP35 -> 0 | DS35: =SUM(F35:Q35)+SUM(S35:AD35)+SUM(AF35:AQ35)+SUM(AS35:BD35)+SUM(BF35:BQ35)+SUM(BS35:CD35)+SUM(CF35:CQ35)+SUM(CS35:DD35)+SUM(DF35:DQ35) -> 0
C36: =C10 -> /// | D36: =+D10 -> 0 | E36: =E10 -> 0 | G36: =F36 -> 0 | H36: =G36 -> 0 | I36: =H36 -> 0 | J36: =I36 -> 0 | K36: =J36 -> 0 | L36: =K36 -> 0 | M36: =L36 -> 0 | N36: =M36 -> 0 | ... Q36: =P36 -> 0 | T36: =S36 -> 0 | U36: =T36 -> 0 | V36: =U36 -> 0 | W36: =V36 -> 0 | X36: =W36 -> 0 | Y36: =X36 -> 0 | Z36: =Y36 -> 0 | AA36: =Z36 -> 0 | ... AD36: =AC36 -> 0 | AF36: =AD36 -> 0 | AG36: =AF36 -> 0 | AH36: =AG36 -> 0 | AI36: =AH36 -> 0 | AJ36: =AI36 -> 0 | AK36: =AJ36 -> 0 | AL36: =AK36 -> 0 | AM36: =AL36 -> 0 | AN36: =AM36 -> 0 | ... AQ36: =AP36 -> 0 | AS36: =AQ36 -> 0 | AT36: =AS36 -> 0 | AU36: =AT36 -> 0 | AV36: =AU36 -> 0 | AW36: =AV36 -> 0 | AX36: =AW36 -> 0 | AY36: =AX36 -> 0 | AZ36: =AY36 -> 0 | BA36: =AZ36 -> 0 | ... BD36: =BC36 -> 0 | BF36: =BD36 -> 0 | BG36: =BF36 -> 0 | BH36: =BG36 -> 0 | BI36: =BH36 -> 0 | BJ36: =BI36 -> 0 | BK36: =BJ36 -> 0 | BL36: =BK36 -> 0 | BM36: =BL36 -> 0 | BN36: =BM36 -> 0 | ... BQ36: =BP36 -> 0 | BS36: =BQ36 -> 0 | BT36: =BS36 -> 0 | BU36: =BT36 -> 0 | BV36: =BU36 -> 0 | BW36: =BV36 -> 0 | BX36: =BW36 -> 0 | BY36: =BX36 -> 0 | BZ36: =BY36 -> 0 | CA36: =BZ36 -> 0 | ... CD36: =CC36 -> 0 | CF36: =CD36 -> 0 | CG36: =CF36 -> 0 | CH36: =CG36 -> 0 | CI36: =CH36 -> 0 | CJ36: =CI36 -> 0 | CK36: =CJ36 -> 0 | CL36: =CK36 -> 0 | CM36: =CL36 -> 0 | CN36: =CM36 -> 0 | ... CQ36: =CP36 -> 0 | CS36: =CQ36 -> 0 | CT36: =CS36 -> 0 | CU36: =CT36 -> 0 | CV36: =CU36 -> 0 | CW36: =CV36 -> 0 | CX36: =CW36 -> 0 | CY36: =CX36 -> 0 | CZ36: =CY36 -> 0 | DA36: =CZ36 -> 0 | ... DD36: =DC36 -> 0 | DF36: =DD36 -> 0 | DG36: =DF36 -> 0 | DH36: =DG36 -> 0 | DI36: =DH36 -> 0 | DJ36: =DI36 -> 0 | DK36: =DJ36 -> 0 | DL36: =DK36 -> 0 | DM36: =DL36 -> 0 | DN36: =DM36 -> 0 | ... DQ36: =DP36 -> 0 | DS36: =SUM(F36:Q36)+SUM(S36:AD36)+SUM(AF36:AQ36)+SUM(AS36:BD36)+SUM(BF36:BQ36)+SUM(BS36:CD36)+SUM(CF36:CQ36)+SUM(CS36:DD36)+SUM(DF36:DQ36) -> 0
C37: =C11 -> /// | D37: =+D11 -> 0 | E37: =E11 -> 0 | G37: =F37 -> 0 | H37: =G37 -> 0 | I37: =H37 -> 0 | J37: =I37 -> 0 | K37: =J37 -> 0 | L37: =K37 -> 0 | M37: =L37 -> 0 | N37: =M37 -> 0 | ... Q37: =P37 -> 0 | T37: =S37 -> 0 | U37: =T37 -> 0 | V37: =U37 -> 0 | W37: =V37 -> 0 | X37: =W37 -> 0 | Y37: =X37 -> 0 | Z37: =Y37 -> 0 | AA37: =Z37 -> 0 | ... AD37: =AC37 -> 0 | AF37: =AD37 -> 0 | AG37: =AF37 -> 0 | AH37: =AG37 -> 0 | AI37: =AH37 -> 0 | AJ37: =AI37 -> 0 | AK37: =AJ37 -> 0 | AL37: =AK37 -> 0 | AM37: =AL37 -> 0 | AN37: =AM37 -> 0 | ... AQ37: =AP37 -> 0 | AS37: =AQ37 -> 0 | AT37: =AS37 -> 0 | AU37: =AT37 -> 0 | AV37: =AU37 -> 0 | AW37: =AV37 -> 0 | AX37: =AW37 -> 0 | AY37: =AX37 -> 0 | AZ37: =AY37 -> 0 | BA37: =AZ37 -> 0 | ... BD37: =BC37 -> 0 | BF37: =BD37 -> 0 | BG37: =BF37 -> 0 | BH37: =BG37 -> 0 | BI37: =BH37 -> 0 | BJ37: =BI37 -> 0 | BK37: =BJ37 -> 0 | BL37: =BK37 -> 0 | BM37: =BL37 -> 0 | BN37: =BM37 -> 0 | ... BQ37: =BP37 -> 0 | BS37: =BQ37 -> 0 | BT37: =BS37 -> 0 | BU37: =BT37 -> 0 | BV37: =BU37 -> 0 | BW37: =BV37 -> 0 | BX37: =BW37 -> 0 | BY37: =BX37 -> 0 | BZ37: =BY37 -> 0 | CA37: =BZ37 -> 0 | ... CD37: =CC37 -> 0 | CF37: =CD37 -> 0 | CG37: =CF37 -> 0 | CH37: =CG37 -> 0 | CI37: =CH37 -> 0 | CJ37: =CI37 -> 0 | CK37: =CJ37 -> 0 | CL37: =CK37 -> 0 | CM37: =CL37 -> 0 | CN37: =CM37 -> 0 | ... CQ37: =CP37 -> 0 | CS37: =CQ37 -> 0 | CT37: =CS37 -> 0 | CU37: =CT37 -> 0 | CV37: =CU37 -> 0 | CW37: =CV37 -> 0 | CX37: =CW37 -> 0 | CY37: =CX37 -> 0 | CZ37: =CY37 -> 0 | DA37: =CZ37 -> 0 | ... DD37: =DC37 -> 0 | DF37: =DD37 -> 0 | DG37: =DF37 -> 0 | DH37: =DG37 -> 0 | DI37: =DH37 -> 0 | DJ37: =DI37 -> 0 | DK37: =DJ37 -> 0 | DL37: =DK37 -> 0 | DM37: =DL37 -> 0 | DN37: =DM37 -> 0 | ... DQ37: =DP37 -> 0 | DS37: =SUM(F37:Q37)+SUM(S37:AD37)+SUM(AF37:AQ37)+SUM(AS37:BD37)+SUM(BF37:BQ37)+SUM(BS37:CD37)+SUM(CF37:CQ37)+SUM(CS37:DD37)+SUM(DF37:DQ37) -> 0
C38: =C12 -> /// | D38: =+D12 -> 0 | E38: =E12 -> 0 | G38: =F38 -> 0 | H38: =G38 -> 0 | I38: =H38 -> 0 | J38: =I38 -> 0 | K38: =J38 -> 0 | L38: =K38 -> 0 | M38: =L38 -> 0 | N38: =M38 -> 0 | ... Q38: =P38 -> 0 | T38: =S38 -> 0 | U38: =T38 -> 0 | V38: =U38 -> 0 | W38: =V38 -> 0 | X38: =W38 -> 0 | Y38: =X38 -> 0 | Z38: =Y38 -> 0 | AA38: =Z38 -> 0 | ... AD38: =AC38 -> 0 | AF38: =AD38 -> 0 | AG38: =AF38 -> 0 | AH38: =AG38 -> 0 | AI38: =AH38 -> 0 | AJ38: =AI38 -> 0 | AK38: =AJ38 -> 0 | AL38: =AK38 -> 0 | AM38: =AL38 -> 0 | AN38: =AM38 -> 0 | ... AQ38: =AP38 -> 0 | AS38: =AQ38 -> 0 | AT38: =AS38 -> 0 | AU38: =AT38 -> 0 | AV38: =AU38 -> 0 | AW38: =AV38 -> 0 | AX38: =AW38 -> 0 | AY38: =AX38 -> 0 | AZ38: =AY38 -> 0 | BA38: =AZ38 -> 0 | ... BD38: =BC38 -> 0 | BF38: =BD38 -> 0 | BG38: =BF38 -> 0 | BH38: =BG38 -> 0 | BI38: =BH38 -> 0 | BJ38: =BI38 -> 0 | BK38: =BJ38 -> 0 | BL38: =BK38 -> 0 | BM38: =BL38 -> 0 | BN38: =BM38 -> 0 | ... BQ38: =BP38 -> 0 | BS38: =BQ38 -> 0 | BT38: =BS38 -> 0 | BU38: =BT38 -> 0 | BV38: =BU38 -> 0 | BW38: =BV38 -> 0 | BX38: =BW38 -> 0 | BY38: =BX38 -> 0 | BZ38: =BY38 -> 0 | CA38: =BZ38 -> 0 | ... CD38: =CC38 -> 0 | CF38: =CD38 -> 0 | CG38: =CF38 -> 0 | CH38: =CG38 -> 0 | CI38: =CH38 -> 0 | CJ38: =CI38 -> 0 | CK38: =CJ38 -> 0 | CL38: =CK38 -> 0 | CM38: =CL38 -> 0 | CN38: =CM38 -> 0 | ... CQ38: =CP38 -> 0 | CS38: =CQ38 -> 0 | CT38: =CS38 -> 0 | CU38: =CT38 -> 0 | CV38: =CU38 -> 0 | CW38: =CV38 -> 0 | CX38: =CW38 -> 0 | CY38: =CX38 -> 0 | CZ38: =CY38 -> 0 | DA38: =CZ38 -> 0 | ... DD38: =DC38 -> 0 | DF38: =DD38 -> 0 | DG38: =DF38 -> 0 | DH38: =DG38 -> 0 | DI38: =DH38 -> 0 | DJ38: =DI38 -> 0 | DK38: =DJ38 -> 0 | DL38: =DK38 -> 0 | DM38: =DL38 -> 0 | DN38: =DM38 -> 0 | ... DQ38: =DP38 -> 0 | DS38: =SUM(F38:Q38)+SUM(S38:AD38)+SUM(AF38:AQ38)+SUM(AS38:BD38)+SUM(BF38:BQ38)+SUM(BS38:CD38)+SUM(CF38:CQ38)+SUM(CS38:DD38)+SUM(DF38:DQ38) -> 0
A39: 2 | B39: 1 | C39: =C13 -> /// | D39: =+D13 -> 0 | E39: =E13 -> 0 | G39: =F39 -> 0 | H39: =G39 -> 0 | I39: =H39 -> 0 | J39: =I39 -> 0 | K39: =J39 -> 0 | L39: =K39 -> 0 | M39: =L39 -> 0 | N39: =M39 -> 0 | ... Q39: =P39 -> 0 | T39: =S39 -> 0 | U39: =T39 -> 0 | V39: =U39 -> 0 | W39: =V39 -> 0 | X39: =W39 -> 0 | Y39: =X39 -> 0 | Z39: =Y39 -> 0 | AA39: =Z39 -> 0 | ... AD39: =AC39 -> 0 | AF39: =AD39 -> 0 | AG39: =AF39 -> 0 | AH39: =AG39 -> 0 | AI39: =AH39 -> 0 | AJ39: =AI39 -> 0 | AK39: =AJ39 -> 0 | AL39: =AK39 -> 0 | AM39: =AL39 -> 0 | AN39: =AM39 -> 0 | ... AQ39: =AP39 -> 0 | AS39: =AQ39 -> 0 | AT39: =AS39 -> 0 | AU39: =AT39 -> 0 | AV39: =AU39 -> 0 | AW39: =AV39 -> 0 | AX39: =AW39 -> 0 | AY39: =AX39 -> 0 | AZ39: =AY39 -> 0 | BA39: =AZ39 -> 0 | ... BD39: =BC39 -> 0 | BF39: =BD39 -> 0 | BG39: =BF39 -> 0 | BH39: =BG39 -> 0 | BI39: =BH39 -> 0 | BJ39: =BI39 -> 0 | BK39: =BJ39 -> 0 | BL39: =BK39 -> 0 | BM39: =BL39 -> 0 | BN39: =BM39 -> 0 | ... BQ39: =BP39 -> 0 | BS39: =BQ39 -> 0 | BT39: =BS39 -> 0 | BU39: =BT39 -> 0 | BV39: =BU39 -> 0 | BW39: =BV39 -> 0 | BX39: =BW39 -> 0 | BY39: =BX39 -> 0 | BZ39: =BY39 -> 0 | CA39: =BZ39 -> 0 | ... CD39: =CC39 -> 0 | CF39: =CD39 -> 0 | CG39: =CF39 -> 0 | CH39: =CG39 -> 0 | CI39: =CH39 -> 0 | CJ39: =CI39 -> 0 | CK39: =CJ39 -> 0 | CL39: =CK39 -> 0 | CM39: =CL39 -> 0 | CN39: =CM39 -> 0 | ... CQ39: =CP39 -> 0 | CS39: =CQ39 -> 0 | CT39: =CS39 -> 0 | CU39: =CT39 -> 0 | CV39: =CU39 -> 0 | CW39: =CV39 -> 0 | CX39: =CW39 -> 0 | CY39: =CX39 -> 0 | CZ39: =CY39 -> 0 | DA39: =CZ39 -> 0 | ... DD39: =DC39 -> 0 | DF39: =DD39 -> 0 | DG39: =DF39 -> 0 | DH39: =DG39 -> 0 | DI39: =DH39 -> 0 | DJ39: =DI39 -> 0 | DK39: =DJ39 -> 0 | DL39: =DK39 -> 0 | DM39: =DL39 -> 0 | DN39: =DM39 -> 0 | ... DQ39: =DP39 -> 0 | DS39: =SUM(F39:Q39)+SUM(S39:AD39)+SUM(AF39:AQ39)+SUM(AS39:BD39)+SUM(BF39:BQ39)+SUM(BS39:CD39)+SUM(CF39:CQ39)+SUM(CS39:DD39)+SUM(DF39:DQ39) -> 0
C40: =C14 -> /// | D40: =+D14 -> 0 | E40: =E14 -> 0 | G40: =F40 -> 0 | H40: =G40 -> 0 | I40: =H40 -> 0 | J40: =I40 -> 0 | K40: =J40 -> 0 | L40: =K40 -> 0 | M40: =L40 -> 0 | N40: =M40 -> 0 | ... Q40: =P40 -> 0 | S40: =Q40 -> 0 | T40: =S40 -> 0 | U40: =T40 -> 0 | V40: =U40 -> 0 | W40: =V40 -> 0 | X40: =W40 -> 0 | Y40: =X40 -> 0 | Z40: =Y40 -> 0 | AA40: =Z40 -> 0 | ... AD40: =AC40 -> 0 | AF40: =AD40 -> 0 | AG40: =AF40 -> 0 | AH40: =AG40 -> 0 | AI40: =AH40 -> 0 | AJ40: =AI40 -> 0 | AK40: =AJ40 -> 0 | AL40: =AK40 -> 0 | AM40: =AL40 -> 0 | AN40: =AM40 -> 0 | ... AQ40: =AP40 -> 0 | AS40: =AQ40 -> 0 | AT40: =AS40 -> 0 | AU40: =AT40 -> 0 | AV40: =AU40 -> 0 | AW40: =AV40 -> 0 | AX40: =AW40 -> 0 | AY40: =AX40 -> 0 | AZ40: =AY40 -> 0 | BA40: =AZ40 -> 0 | ... BD40: =BC40 -> 0 | BF40: =BD40 -> 0 | BG40: =BF40 -> 0 | BH40: =BG40 -> 0 | BI40: =BH40 -> 0 | BJ40: =BI40 -> 0 | BK40: =BJ40 -> 0 | BL40: =BK40 -> 0 | BM40: =BL40 -> 0 | BN40: =BM40 -> 0 | ... BQ40: =BP40 -> 0 | BS40: =BQ40 -> 0 | BT40: =BS40 -> 0 | BU40: =BT40 -> 0 | BV40: =BU40 -> 0 | BW40: =BV40 -> 0 | BX40: =BW40 -> 0 | BY40: =BX40 -> 0 | BZ40: =BY40 -> 0 | CA40: =BZ40 -> 0 | ... CD40: =CC40 -> 0 | CF40: =CD40 -> 0 | CG40: =CF40 -> 0 | CH40: =CG40 -> 0 | CI40: =CH40 -> 0 | CJ40: =CI40 -> 0 | CK40: =CJ40 -> 0 | CL40: =CK40 -> 0 | CM40: =CL40 -> 0 | CN40: =CM40 -> 0 | ... CQ40: =CP40 -> 0 | CS40: =CQ40 -> 0 | CT40: =CS40 -> 0 | CU40: =CT40 -> 0 | CV40: =CU40 -> 0 | CW40: =CV40 -> 0 | CX40: =CW40 -> 0 | CY40: =CX40 -> 0 | CZ40: =CY40 -> 0 | DA40: =CZ40 -> 0 | ... DD40: =DC40 -> 0 | DF40: =DD40 -> 0 | DG40: =DF40 -> 0 | DH40: =DG40 -> 0 | DI40: =DH40 -> 0 | DJ40: =DI40 -> 0 | DK40: =DJ40 -> 0 | DL40: =DK40 -> 0 | DM40: =DL40 -> 0 | DN40: =DM40 -> 0 | ... DQ40: =DP40 -> 0 | DS40: =SUM(F40:Q40)+SUM(S40:AD40)+SUM(AF40:AQ40)+SUM(AS40:BD40)+SUM(BF40:BQ40)+SUM(BS40:CD40)+SUM(CF40:CQ40)+SUM(CS40:DD40)+SUM(DF40:DQ40) -> 0
A41: 2 | B41: 2 | C41: =C15 -> /// | D41: =+D15 -> 0 | E41: =E15 -> 0 | G41: =F41 -> 0 | H41: =G41 -> 0 | I41: =H41 -> 0 | J41: =I41 -> 0 | K41: =J41 -> 0 | L41: =K41 -> 0 | M41: =L41 -> 0 | N41: =M41 -> 0 | ... Q41: =P41 -> 0 | S41: =Q41 -> 0 | T41: =S41 -> 0 | U41: =T41 -> 0 | V41: =U41 -> 0 | W41: =V41 -> 0 | X41: =W41 -> 0 | Y41: =X41 -> 0 | Z41: =Y41 -> 0 | AA41: =Z41 -> 0 | ... AD41: =AC41 -> 0 | AF41: =AD41 -> 0 | AG41: =AF41 -> 0 | AH41: =AG41 -> 0 | AI41: =AH41 -> 0 | AJ41: =AI41 -> 0 | AK41: =AJ41 -> 0 | AL41: =AK41 -> 0 | AM41: =AL41 -> 0 | AN41: =AM41 -> 0 | ... AQ41: =AP41 -> 0 | AS41: =AQ41 -> 0 | AT41: =AS41 -> 0 | AU41: =AT41 -> 0 | AV41: =AU41 -> 0 | AW41: =AV41 -> 0 | AX41: =AW41 -> 0 | AY41: =AX41 -> 0 | AZ41: =AY41 -> 0 | BA41: =AZ41 -> 0 | ... BD41: =BC41 -> 0 | BF41: =BD41 -> 0 | BG41: =BF41 -> 0 | BH41: =BG41 -> 0 | BI41: =BH41 -> 0 | BJ41: =BI41 -> 0 | BK41: =BJ41 -> 0 | BL41: =BK41 -> 0 | BM41: =BL41 -> 0 | BN41: =BM41 -> 0 | ... BQ41: =BP41 -> 0 | BS41: =BQ41 -> 0 | BT41: =BS41 -> 0 | BU41: =BT41 -> 0 | BV41: =BU41 -> 0 | BW41: =BV41 -> 0 | BX41: =BW41 -> 0 | BY41: =BX41 -> 0 | BZ41: =BY41 -> 0 | CA41: =BZ41 -> 0 | ... CD41: =CC41 -> 0 | CF41: =CD41 -> 0 | CG41: =CF41 -> 0 | CH41: =CG41 -> 0 | CI41: =CH41 -> 0 | CJ41: =CI41 -> 0 | CK41: =CJ41 -> 0 | CL41: =CK41 -> 0 | CM41: =CL41 -> 0 | CN41: =CM41 -> 0 | ... CQ41: =CP41 -> 0 | CS41: =CQ41 -> 0 | CT41: =CS41 -> 0 | CU41: =CT41 -> 0 | CV41: =CU41 -> 0 | CW41: =CV41 -> 0 | CX41: =CW41 -> 0 | CY41: =CX41 -> 0 | CZ41: =CY41 -> 0 | DA41: =CZ41 -> 0 | ... DD41: =DC41 -> 0 | DF41: =DD41 -> 0 | DG41: =DF41 -> 0 | DH41: =DG41 -> 0 | DI41: =DH41 -> 0 | DJ41: =DI41 -> 0 | DK41: =DJ41 -> 0 | DL41: =DK41 -> 0 | DM41: =DL41 -> 0 | DN41: =DM41 -> 0 | ... DQ41: =DP41 -> 0 | DS41: =SUM(F41:Q41)+SUM(S41:AD41)+SUM(AF41:AQ41)+SUM(AS41:BD41)+SUM(BF41:BQ41)+SUM(BS41:CD41)+SUM(CF41:CQ41)+SUM(CS41:DD41)+SUM(DF41:DQ41) -> 0
C42: =C16 -> /// | D42: =+D16 -> 0 | E42: =E16 -> 0 | G42: =F42 -> 0 | H42: =G42 -> 0 | I42: =H42 -> 0 | J42: =I42 -> 0 | K42: =J42 -> 0 | L42: =K42 -> 0 | M42: =L42 -> 0 | N42: =M42 -> 0 | ... Q42: =P42 -> 0 | S42: =Q42 -> 0 | T42: =S42 -> 0 | U42: =T42 -> 0 | V42: =U42 -> 0 | W42: =V42 -> 0 | X42: =W42 -> 0 | Y42: =X42 -> 0 | Z42: =Y42 -> 0 | AA42: =Z42 -> 0 | ... AD42: =AC42 -> 0 | AF42: =AD42 -> 0 | AG42: =AF42 -> 0 | AH42: =AG42 -> 0 | AI42: =AH42 -> 0 | AJ42: =AI42 -> 0 | AK42: =AJ42 -> 0 | AL42: =AK42 -> 0 | AM42: =AL42 -> 0 | AN42: =AM42 -> 0 | ... AQ42: =AP42 -> 0 | AS42: =AQ42 -> 0 | AT42: =AS42 -> 0 | AU42: =AT42 -> 0 | AV42: =AU42 -> 0 | AW42: =AV42 -> 0 | AX42: =AW42 -> 0 | AY42: =AX42 -> 0 | AZ42: =AY42 -> 0 | BA42: =AZ42 -> 0 | ... BD42: =BC42 -> 0 | BF42: =BD42 -> 0 | BG42: =BF42 -> 0 | BH42: =BG42 -> 0 | BI42: =BH42 -> 0 | BJ42: =BI42 -> 0 | BK42: =BJ42 -> 0 | BL42: =BK42 -> 0 | BM42: =BL42 -> 0 | BN42: =BM42 -> 0 | ... BQ42: =BP42 -> 0 | BS42: =BQ42 -> 0 | BT42: =BS42 -> 0 | BU42: =BT42 -> 0 | BV42: =BU42 -> 0 | BW42: =BV42 -> 0 | BX42: =BW42 -> 0 | BY42: =BX42 -> 0 | BZ42: =BY42 -> 0 | CA42: =BZ42 -> 0 | ... CD42: =CC42 -> 0 | CF42: =CD42 -> 0 | CG42: =CF42 -> 0 | CH42: =CG42 -> 0 | CI42: =CH42 -> 0 | CJ42: =CI42 -> 0 | CK42: =CJ42 -> 0 | CL42: =CK42 -> 0 | CM42: =CL42 -> 0 | CN42: =CM42 -> 0 | ... CQ42: =CP42 -> 0 | CS42: =CQ42 -> 0 | CT42: =CS42 -> 0 | CU42: =CT42 -> 0 | CV42: =CU42 -> 0 | CW42: =CV42 -> 0 | CX42: =CW42 -> 0 | CY42: =CX42 -> 0 | CZ42: =CY42 -> 0 | DA42: =CZ42 -> 0 | ... DD42: =DC42 -> 0 | DF42: =DD42 -> 0 | DG42: =DF42 -> 0 | DH42: =DG42 -> 0 | DI42: =DH42 -> 0 | DJ42: =DI42 -> 0 | DK42: =DJ42 -> 0 | DL42: =DK42 -> 0 | DM42: =DL42 -> 0 | DN42: =DM42 -> 0 | ... DQ42: =DP42 -> 0 | DS42: =SUM(F42:Q42)+SUM(S42:AD42)+SUM(AF42:AQ42)+SUM(AS42:BD42)+SUM(BF42:BQ42)+SUM(BS42:CD42)+SUM(CF42:CQ42)+SUM(CS42:DD42)+SUM(DF42:DQ42) -> 0
C43: =C17 -> /// | D43: =+D17 -> 0 | E43: =E17 -> 0 | G43: =F43 -> 0 | H43: =G43 -> 0 | I43: =H43 -> 0 | J43: =I43 -> 0 | K43: =J43 -> 0 | L43: =K43 -> 0 | M43: =L43 -> 0 | N43: =M43 -> 0 | ... Q43: =P43 -> 0 | S43: =Q43 -> 0 | T43: =S43 -> 0 | U43: =T43 -> 0 | V43: =U43 -> 0 | W43: =V43 -> 0 | X43: =W43 -> 0 | Y43: =X43 -> 0 | Z43: =Y43 -> 0 | AA43: =Z43 -> 0 | ... AD43: =AC43 -> 0 | AF43: =AD43 -> 0 | AG43: =AF43 -> 0 | AH43: =AG43 -> 0 | AI43: =AH43 -> 0 | AJ43: =AI43 -> 0 | AK43: =AJ43 -> 0 | AL43: =AK43 -> 0 | AM43: =AL43 -> 0 | AN43: =AM43 -> 0 | ... AQ43: =AP43 -> 0 | AS43: =AQ43 -> 0 | AT43: =AS43 -> 0 | AU43: =AT43 -> 0 | AV43: =AU43 -> 0 | AW43: =AV43 -> 0 | AX43: =AW43 -> 0 | AY43: =AX43 -> 0 | AZ43: =AY43 -> 0 | BA43: =AZ43 -> 0 | ... BD43: =BC43 -> 0 | BF43: =BD43 -> 0 | BG43: =BF43 -> 0 | BH43: =BG43 -> 0 | BI43: =BH43 -> 0 | BJ43: =BI43 -> 0 | BK43: =BJ43 -> 0 | BL43: =BK43 -> 0 | BM43: =BL43 -> 0 | BN43: =BM43 -> 0 | ... BQ43: =BP43 -> 0 | BS43: =BQ43 -> 0 | BT43: =BS43 -> 0 | BU43: =BT43 -> 0 | BV43: =BU43 -> 0 | BW43: =BV43 -> 0 | BX43: =BW43 -> 0 | BY43: =BX43 -> 0 | BZ43: =BY43 -> 0 | CA43: =BZ43 -> 0 | ... CD43: =CC43 -> 0 | CF43: =CD43 -> 0 | CG43: =CF43 -> 0 | CH43: =CG43 -> 0 | CI43: =CH43 -> 0 | CJ43: =CI43 -> 0 | CK43: =CJ43 -> 0 | CL43: =CK43 -> 0 | CM43: =CL43 -> 0 | CN43: =CM43 -> 0 | ... CQ43: =CP43 -> 0 | CS43: =CQ43 -> 0 | CT43: =CS43 -> 0 | CU43: =CT43 -> 0 | CV43: =CU43 -> 0 | CW43: =CV43 -> 0 | CX43: =CW43 -> 0 | CY43: =CX43 -> 0 | CZ43: =CY43 -> 0 | DA43: =CZ43 -> 0 | ... DD43: =DC43 -> 0 | DF43: =DD43 -> 0 | DG43: =DF43 -> 0 | DH43: =DG43 -> 0 | DI43: =DH43 -> 0 | DJ43: =DI43 -> 0 | DK43: =DJ43 -> 0 | DL43: =DK43 -> 0 | DM43: =DL43 -> 0 | DN43: =DM43 -> 0 | ... DQ43: =DP43 -> 0 | DS43: =SUM(F43:Q43)+SUM(S43:AD43)+SUM(AF43:AQ43)+SUM(AS43:BD43)+SUM(BF43:BQ43)+SUM(BS43:CD43)+SUM(CF43:CQ43)+SUM(CS43:DD43)+SUM(DF43:DQ43) -> 0
A44: 2 | B44: 3 | C44: =C18 -> /// | D44: =+D18 -> 0 | E44: =E18 -> 0 | G44: =F44 -> 0 | H44: =G44 -> 0 | I44: =H44 -> 0 | J44: =I44 -> 0 | K44: =J44 -> 0 | L44: =K44 -> 0 | M44: =L44 -> 0 | N44: =M44 -> 0 | ... Q44: =P44 -> 0 | S44: =Q44 -> 0 | T44: =S44 -> 0 | U44: =T44 -> 0 | V44: =U44 -> 0 | W44: =V44 -> 0 | X44: =W44 -> 0 | Y44: =X44 -> 0 | Z44: =Y44 -> 0 | AA44: =Z44 -> 0 | ... AD44: =AC44 -> 0 | AF44: =AD44 -> 0 | AG44: =AF44 -> 0 | AH44: =AG44 -> 0 | AI44: =AH44 -> 0 | AJ44: =AI44 -> 0 | AK44: =AJ44 -> 0 | AL44: =AK44 -> 0 | AM44: =AL44 -> 0 | AN44: =AM44 -> 0 | ... AQ44: =AP44 -> 0 | AS44: =AQ44 -> 0 | AT44: =AS44 -> 0 | AU44: =AT44 -> 0 | AV44: =AU44 -> 0 | AW44: =AV44 -> 0 | AX44: =AW44 -> 0 | AY44: =AX44 -> 0 | AZ44: =AY44 -> 0 | BA44: =AZ44 -> 0 | ... BD44: =BC44 -> 0 | BF44: =BD44 -> 0 | BG44: =BF44 -> 0 | BH44: =BG44 -> 0 | BI44: =BH44 -> 0 | BJ44: =BI44 -> 0 | BK44: =BJ44 -> 0 | BL44: =BK44 -> 0 | BM44: =BL44 -> 0 | BN44: =BM44 -> 0 | ... BQ44: =BP44 -> 0 | BS44: =BQ44 -> 0 | BT44: =BS44 -> 0 | BU44: =BT44 -> 0 | BV44: =BU44 -> 0 | BW44: =BV44 -> 0 | BX44: =BW44 -> 0 | BY44: =BX44 -> 0 | BZ44: =BY44 -> 0 | CA44: =BZ44 -> 0 | ... CD44: =CC44 -> 0 | CF44: =CD44 -> 0 | CG44: =CF44 -> 0 | CH44: =CG44 -> 0 | CI44: =CH44 -> 0 | CJ44: =CI44 -> 0 | CK44: =CJ44 -> 0 | CL44: =CK44 -> 0 | CM44: =CL44 -> 0 | CN44: =CM44 -> 0 | ... CQ44: =CP44 -> 0 | CS44: =CQ44 -> 0 | CT44: =CS44 -> 0 | CU44: =CT44 -> 0 | CV44: =CU44 -> 0 | CW44: =CV44 -> 0 | CX44: =CW44 -> 0 | CY44: =CX44 -> 0 | CZ44: =CY44 -> 0 | DA44: =CZ44 -> 0 | ... DD44: =DC44 -> 0 | DF44: =DD44 -> 0 | DG44: =DF44 -> 0 | DH44: =DG44 -> 0 | DI44: =DH44 -> 0 | DJ44: =DI44 -> 0 | DK44: =DJ44 -> 0 | DL44: =DK44 -> 0 | DM44: =DL44 -> 0 | DN44: =DM44 -> 0 | ... DQ44: =DP44 -> 0 | DS44: =SUM(F44:Q44)+SUM(S44:AD44)+SUM(AF44:AQ44)+SUM(AS44:BD44)+SUM(BF44:BQ44)+SUM(BS44:CD44)+SUM(CF44:CQ44)+SUM(CS44:DD44)+SUM(DF44:DQ44) -> 0
C45: =C19 -> /// | D45: =+D19 -> 0 | E45: =E19 -> 0 | G45: =F45 -> 0 | H45: =G45 -> 0 | I45: =H45 -> 0 | J45: =I45 -> 0 | K45: =J45 -> 0 | L45: =K45 -> 0 | M45: =L45 -> 0 | N45: =M45 -> 0 | ... Q45: =P45 -> 0 | S45: =Q45 -> 0 | T45: =S45 -> 0 | U45: =T45 -> 0 | V45: =U45 -> 0 | W45: =V45 -> 0 | X45: =W45 -> 0 | Y45: =X45 -> 0 | Z45: =Y45 -> 0 | AA45: =Z45 -> 0 | ... AD45: =AC45 -> 0 | AF45: =AD45 -> 0 | AG45: =AF45 -> 0 | AH45: =AG45 -> 0 | AI45: =AH45 -> 0 | AJ45: =AI45 -> 0 | AK45: =AJ45 -> 0 | AL45: =AK45 -> 0 | AM45: =AL45 -> 0 | AN45: =AM45 -> 0 | ... AQ45: =AP45 -> 0 | AS45: =AQ45 -> 0 | AT45: =AS45 -> 0 | AU45: =AT45 -> 0 | AV45: =AU45 -> 0 | AW45: =AV45 -> 0 | AX45: =AW45 -> 0 | AY45: =AX45 -> 0 | AZ45: =AY45 -> 0 | BA45: =AZ45 -> 0 | ... BD45: =BC45 -> 0 | BF45: =BD45 -> 0 | BG45: =BF45 -> 0 | BH45: =BG45 -> 0 | BI45: =BH45 -> 0 | BJ45: =BI45 -> 0 | BK45: =BJ45 -> 0 | BL45: =BK45 -> 0 | BM45: =BL45 -> 0 | BN45: =BM45 -> 0 | ... BQ45: =BP45 -> 0 | BS45: =BQ45 -> 0 | BT45: =BS45 -> 0 | BU45: =BT45 -> 0 | BV45: =BU45 -> 0 | BW45: =BV45 -> 0 | BX45: =BW45 -> 0 | BY45: =BX45 -> 0 | BZ45: =BY45 -> 0 | CA45: =BZ45 -> 0 | ... CD45: =CC45 -> 0 | CF45: =CD45 -> 0 | CG45: =CF45 -> 0 | CH45: =CG45 -> 0 | CI45: =CH45 -> 0 | CJ45: =CI45 -> 0 | CK45: =CJ45 -> 0 | CL45: =CK45 -> 0 | CM45: =CL45 -> 0 | CN45: =CM45 -> 0 | ... CQ45: =CP45 -> 0 | CS45: =CQ45 -> 0 | CT45: =CS45 -> 0 | CU45: =CT45 -> 0 | CV45: =CU45 -> 0 | CW45: =CV45 -> 0 | CX45: =CW45 -> 0 | CY45: =CX45 -> 0 | CZ45: =CY45 -> 0 | DA45: =CZ45 -> 0 | ... DD45: =DC45 -> 0 | DF45: =DD45 -> 0 | DG45: =DF45 -> 0 | DH45: =DG45 -> 0 | DI45: =DH45 -> 0 | DJ45: =DI45 -> 0 | DK45: =DJ45 -> 0 | DL45: =DK45 -> 0 | DM45: =DL45 -> 0 | DN45: =DM45 -> 0 | ... DQ45: =DP45 -> 0 | DS45: =SUM(F45:Q45)+SUM(S45:AD45)+SUM(AF45:AQ45)+SUM(AS45:BD45)+SUM(BF45:BQ45)+SUM(BS45:CD45)+SUM(CF45:CQ45)+SUM(CS45:DD45)+SUM(DF45:DQ45) -> 0
A46: 2 | B46: 4 | C46: =C20 -> /// | D46: =+D20 -> 0 | E46: =E20 -> 0 | G46: =F46 -> 0 | H46: =G46 -> 0 | I46: =H46 -> 0 | J46: =I46 -> 0 | K46: =J46 -> 0 | L46: =K46 -> 0 | M46: =L46 -> 0 | N46: =M46 -> 0 | ... Q46: =P46 -> 0 | S46: =Q46 -> 0 | T46: =S46 -> 0 | U46: =T46 -> 0 | V46: =U46 -> 0 | W46: =V46 -> 0 | X46: =W46 -> 0 | Y46: =X46 -> 0 | Z46: =Y46 -> 0 | AA46: =Z46 -> 0 | ... AD46: =AC46 -> 0 | AF46: =AD46 -> 0 | AG46: =AF46 -> 0 | AH46: =AG46 -> 0 | AI46: =AH46 -> 0 | AJ46: =AI46 -> 0 | AK46: =AJ46 -> 0 | AL46: =AK46 -> 0 | AM46: =AL46 -> 0 | AN46: =AM46 -> 0 | ... AQ46: =AP46 -> 0 | AS46: =AQ46 -> 0 | AT46: =AS46 -> 0 | AU46: =AT46 -> 0 | AV46: =AU46 -> 0 | AW46: =AV46 -> 0 | AX46: =AW46 -> 0 | AY46: =AX46 -> 0 | AZ46: =AY46 -> 0 | BA46: =AZ46 -> 0 | ... BD46: =BC46 -> 0 | BF46: =BD46 -> 0 | BG46: =BF46 -> 0 | BH46: =BG46 -> 0 | BI46: =BH46 -> 0 | BJ46: =BI46 -> 0 | BK46: =BJ46 -> 0 | BL46: =BK46 -> 0 | BM46: =BL46 -> 0 | BN46: =BM46 -> 0 | ... BQ46: =BP46 -> 0 | BS46: =BQ46 -> 0 | BT46: =BS46 -> 0 | BU46: =BT46 -> 0 | BV46: =BU46 -> 0 | BW46: =BV46 -> 0 | BX46: =BW46 -> 0 | BY46: =BX46 -> 0 | BZ46: =BY46 -> 0 | CA46: =BZ46 -> 0 | ... CD46: =CC46 -> 0 | CF46: =CD46 -> 0 | CG46: =CF46 -> 0 | CH46: =CG46 -> 0 | CI46: =CH46 -> 0 | CJ46: =CI46 -> 0 | CK46: =CJ46 -> 0 | CL46: =CK46 -> 0 | CM46: =CL46 -> 0 | CN46: =CM46 -> 0 | ... CQ46: =CP46 -> 0 | CS46: =CQ46 -> 0 | CT46: =CS46 -> 0 | CU46: =CT46 -> 0 | CV46: =CU46 -> 0 | CW46: =CV46 -> 0 | CX46: =CW46 -> 0 | CY46: =CX46 -> 0 | CZ46: =CY46 -> 0 | DA46: =CZ46 -> 0 | ... DD46: =DC46 -> 0 | DF46: =DD46 -> 0 | DG46: =DF46 -> 0 | DH46: =DG46 -> 0 | DI46: =DH46 -> 0 | DJ46: =DI46 -> 0 | DK46: =DJ46 -> 0 | DL46: =DK46 -> 0 | DM46: =DL46 -> 0 | DN46: =DM46 -> 0 | ... DQ46: =DP46 -> 0 | DS46: =SUM(F46:Q46)+SUM(S46:AD46)+SUM(AF46:AQ46)+SUM(AS46:BD46)+SUM(BF46:BQ46)+SUM(BS46:CD46)+SUM(CF46:CQ46)+SUM(CS46:DD46)+SUM(DF46:DQ46) -> 0
C47: =C21 -> /// | D47: =+D21 -> 0 | E47: =E21 -> 0 | G47: =F47 -> 0 | H47: =G47 -> 0 | I47: =H47 -> 0 | J47: =I47 -> 0 | K47: =J47 -> 0 | L47: =K47 -> 0 | M47: =L47 -> 0 | N47: =M47 -> 0 | ... Q47: =P47 -> 0 | S47: =Q47 -> 0 | T47: =S47 -> 0 | U47: =T47 -> 0 | V47: =U47 -> 0 | W47: =V47 -> 0 | X47: =W47 -> 0 | Y47: =X47 -> 0 | Z47: =Y47 -> 0 | AA47: =Z47 -> 0 | ... AD47: =AC47 -> 0 | AF47: =AD47 -> 0 | AG47: =AF47 -> 0 | AH47: =AG47 -> 0 | AI47: =AH47 -> 0 | AJ47: =AI47 -> 0 | AK47: =AJ47 -> 0 | AL47: =AK47 -> 0 | AM47: =AL47 -> 0 | AN47: =AM47 -> 0 | ... AQ47: =AP47 -> 0 | AS47: =AQ47 -> 0 | AT47: =AS47 -> 0 | AU47: =AT47 -> 0 | AV47: =AU47 -> 0 | AW47: =AV47 -> 0 | AX47: =AW47 -> 0 | AY47: =AX47 -> 0 | AZ47: =AY47 -> 0 | BA47: =AZ47 -> 0 | ... BD47: =BC47 -> 0 | BF47: =BD47 -> 0 | BG47: =BF47 -> 0 | BH47: =BG47 -> 0 | BI47: =BH47 -> 0 | BJ47: =BI47 -> 0 | BK47: =BJ47 -> 0 | BL47: =BK47 -> 0 | BM47: =BL47 -> 0 | BN47: =BM47 -> 0 | ... BQ47: =BP47 -> 0 | BS47: =BQ47 -> 0 | BT47: =BS47 -> 0 | BU47: =BT47 -> 0 | BV47: =BU47 -> 0 | BW47: =BV47 -> 0 | BX47: =BW47 -> 0 | BY47: =BX47 -> 0 | BZ47: =BY47 -> 0 | CA47: =BZ47 -> 0 | ... CD47: =CC47 -> 0 | CF47: =CD47 -> 0 | CG47: =CF47 -> 0 | CH47: =CG47 -> 0 | CI47: =CH47 -> 0 | CJ47: =CI47 -> 0 | CK47: =CJ47 -> 0 | CL47: =CK47 -> 0 | CM47: =CL47 -> 0 | CN47: =CM47 -> 0 | ... CQ47: =CP47 -> 0 | CS47: =CQ47 -> 0 | CT47: =CS47 -> 0 | CU47: =CT47 -> 0 | CV47: =CU47 -> 0 | CW47: =CV47 -> 0 | CX47: =CW47 -> 0 | CY47: =CX47 -> 0 | CZ47: =CY47 -> 0 | DA47: =CZ47 -> 0 | ... DD47: =DC47 -> 0 | DF47: =DD47 -> 0 | DG47: =DF47 -> 0 | DH47: =DG47 -> 0 | DI47: =DH47 -> 0 | DJ47: =DI47 -> 0 | DK47: =DJ47 -> 0 | DL47: =DK47 -> 0 | DM47: =DL47 -> 0 | DN47: =DM47 -> 0 | ... DQ47: =DP47 -> 0 | DS47: =SUM(F47:Q47)+SUM(S47:AD47)+SUM(AF47:AQ47)+SUM(AS47:BD47)+SUM(BF47:BQ47)+SUM(BS47:CD47)+SUM(CF47:CQ47)+SUM(CS47:DD47)+SUM(DF47:DQ47) -> 0
A48: 2 | B48: 5 | C48: =C22 -> /// | D48: =+D22 -> 0 | E48: =E22 -> 0 | G48: =F48 -> 0 | H48: =G48 -> 0 | I48: =H48 -> 0 | J48: =I48 -> 0 | K48: =J48 -> 0 | L48: =K48 -> 0 | M48: =L48 -> 0 | N48: =M48 -> 0 | ... Q48: =P48 -> 0 | S48: =Q48 -> 0 | T48: =S48 -> 0 | U48: =T48 -> 0 | V48: =U48 -> 0 | W48: =V48 -> 0 | X48: =W48 -> 0 | Y48: =X48 -> 0 | Z48: =Y48 -> 0 | AA48: =Z48 -> 0 | ... AD48: =AC48 -> 0 | AF48: =AD48 -> 0 | AG48: =AF48 -> 0 | AH48: =AG48 -> 0 | AI48: =AH48 -> 0 | AJ48: =AI48 -> 0 | AK48: =AJ48 -> 0 | AL48: =AK48 -> 0 | AM48: =AL48 -> 0 | AN48: =AM48 -> 0 | ... AQ48: =AP48 -> 0 | AS48: =AQ48 -> 0 | AT48: =AS48 -> 0 | AU48: =AT48 -> 0 | AV48: =AU48 -> 0 | AW48: =AV48 -> 0 | AX48: =AW48 -> 0 | AY48: =AX48 -> 0 | AZ48: =AY48 -> 0 | BA48: =AZ48 -> 0 | ... BD48: =BC48 -> 0 | BF48: =BD48 -> 0 | BG48: =BF48 -> 0 | BH48: =BG48 -> 0 | BI48: =BH48 -> 0 | BJ48: =BI48 -> 0 | BK48: =BJ48 -> 0 | BL48: =BK48 -> 0 | BM48: =BL48 -> 0 | BN48: =BM48 -> 0 | ... BQ48: =BP48 -> 0 | BS48: =BQ48 -> 0 | BT48: =BS48 -> 0 | BU48: =BT48 -> 0 | BV48: =BU48 -> 0 | BW48: =BV48 -> 0 | BX48: =BW48 -> 0 | BY48: =BX48 -> 0 | BZ48: =BY48 -> 0 | CA48: =BZ48 -> 0 | ... CD48: =CC48 -> 0 | CF48: =CD48 -> 0 | CG48: =CF48 -> 0 | CH48: =CG48 -> 0 | CI48: =CH48 -> 0 | CJ48: =CI48 -> 0 | CK48: =CJ48 -> 0 | CL48: =CK48 -> 0 | CM48: =CL48 -> 0 | CN48: =CM48 -> 0 | ... CQ48: =CP48 -> 0 | CS48: =CQ48 -> 0 | CT48: =CS48 -> 0 | CU48: =CT48 -> 0 | CV48: =CU48 -> 0 | CW48: =CV48 -> 0 | CX48: =CW48 -> 0 | CY48: =CX48 -> 0 | CZ48: =CY48 -> 0 | DA48: =CZ48 -> 0 | ... DD48: =DC48 -> 0 | DF48: =DD48 -> 0 | DG48: =DF48 -> 0 | DH48: =DG48 -> 0 | DI48: =DH48 -> 0 | DJ48: =DI48 -> 0 | DK48: =DJ48 -> 0 | DL48: =DK48 -> 0 | DM48: =DL48 -> 0 | DN48: =DM48 -> 0 | ... DQ48: =DP48 -> 0 | DS48: =SUM(F48:Q48)+SUM(S48:AD48)+SUM(AF48:AQ48)+SUM(AS48:BD48)+SUM(BF48:BQ48)+SUM(BS48:CD48)+SUM(CF48:CQ48)+SUM(CS48:DD48)+SUM(DF48:DQ48) -> 0
C49: =C23 -> /// | D49: =+D23 -> 0 | E49: =E23 -> 0 | G49: =F49 -> 0 | H49: =G49 -> 0 | I49: =H49 -> 0 | J49: =I49 -> 0 | K49: =J49 -> 0 | L49: =K49 -> 0 | M49: =L49 -> 0 | N49: =M49 -> 0 | ... Q49: =P49 -> 0 | S49: =Q49 -> 0 | T49: =S49 -> 0 | U49: =T49 -> 0 | V49: =U49 -> 0 | W49: =V49 -> 0 | X49: =W49 -> 0 | Y49: =X49 -> 0 | Z49: =Y49 -> 0 | AA49: =Z49 -> 0 | ... AD49: =AC49 -> 0 | AF49: =AD49 -> 0 | AG49: =AF49 -> 0 | AH49: =AG49 -> 0 | AI49: =AH49 -> 0 | AJ49: =AI49 -> 0 | AK49: =AJ49 -> 0 | AL49: =AK49 -> 0 | AM49: =AL49 -> 0 | AN49: =AM49 -> 0 | ... AQ49: =AP49 -> 0 | AS49: =AQ49 -> 0 | AT49: =AS49 -> 0 | AU49: =AT49 -> 0 | AV49: =AU49 -> 0 | AW49: =AV49 -> 0 | AX49: =AW49 -> 0 | AY49: =AX49 -> 0 | AZ49: =AY49 -> 0 | BA49: =AZ49 -> 0 | ... BD49: =BC49 -> 0 | BF49: =BD49 -> 0 | BG49: =BF49 -> 0 | BH49: =BG49 -> 0 | BI49: =BH49 -> 0 | BJ49: =BI49 -> 0 | BK49: =BJ49 -> 0 | BL49: =BK49 -> 0 | BM49: =BL49 -> 0 | BN49: =BM49 -> 0 | ... BQ49: =BP49 -> 0 | BS49: =BQ49 -> 0 | BT49: =BS49 -> 0 | BU49: =BT49 -> 0 | BV49: =BU49 -> 0 | BW49: =BV49 -> 0 | BX49: =BW49 -> 0 | BY49: =BX49 -> 0 | BZ49: =BY49 -> 0 | CA49: =BZ49 -> 0 | ... CD49: =CC49 -> 0 | CF49: =CD49 -> 0 | CG49: =CF49 -> 0 | CH49: =CG49 -> 0 | CI49: =CH49 -> 0 | CJ49: =CI49 -> 0 | CK49: =CJ49 -> 0 | CL49: =CK49 -> 0 | CM49: =CL49 -> 0 | CN49: =CM49 -> 0 | ... CQ49: =CP49 -> 0 | CS49: =CQ49 -> 0 | CT49: =CS49 -> 0 | CU49: =CT49 -> 0 | CV49: =CU49 -> 0 | CW49: =CV49 -> 0 | CX49: =CW49 -> 0 | CY49: =CX49 -> 0 | CZ49: =CY49 -> 0 | DA49: =CZ49 -> 0 | ... DD49: =DC49 -> 0 | DF49: =DD49 -> 0 | DG49: =DF49 -> 0 | DH49: =DG49 -> 0 | DI49: =DH49 -> 0 | DJ49: =DI49 -> 0 | DK49: =DJ49 -> 0 | DL49: =DK49 -> 0 | DM49: =DL49 -> 0 | DN49: =DM49 -> 0 | ... DQ49: =DP49 -> 0 | DS49: =SUM(F49:Q49)+SUM(S49:AD49)+SUM(AF49:AQ49)+SUM(AS49:BD49)+SUM(BF49:BQ49)+SUM(BS49:CD49)+SUM(CF49:CQ49)+SUM(CS49:DD49)+SUM(DF49:DQ49) -> 0
C50: =C24 -> /// | D50: =+D24 -> 0 | E50: =E24 -> 0 | G50: =F50 -> 0 | H50: =G50 -> 0 | I50: =H50 -> 0 | J50: =I50 -> 0 | K50: =J50 -> 0 | L50: =K50 -> 0 | M50: =L50 -> 0 | N50: =M50 -> 0 | ... Q50: =P50 -> 0 | S50: =Q50 -> 0 | T50: =S50 -> 0 | U50: =T50 -> 0 | V50: =U50 -> 0 | W50: =V50 -> 0 | X50: =W50 -> 0 | Y50: =X50 -> 0 | Z50: =Y50 -> 0 | AA50: =Z50 -> 0 | ... AD50: =AC50 -> 0 | AF50: =AD50 -> 0 | AG50: =AF50 -> 0 | AH50: =AG50 -> 0 | AI50: =AH50 -> 0 | AJ50: =AI50 -> 0 | AK50: =AJ50 -> 0 | AL50: =AK50 -> 0 | AM50: =AL50 -> 0 | AN50: =AM50 -> 0 | ... AQ50: =AP50 -> 0 | AS50: =AQ50 -> 0 | AT50: =AS50 -> 0 | AU50: =AT50 -> 0 | AV50: =AU50 -> 0 | AW50: =AV50 -> 0 | AX50: =AW50 -> 0 | AY50: =AX50 -> 0 | AZ50: =AY50 -> 0 | BA50: =AZ50 -> 0 | ... BD50: =BC50 -> 0 | BF50: =BD50 -> 0 | BG50: =BF50 -> 0 | BH50: =BG50 -> 0 | BI50: =BH50 -> 0 | BJ50: =BI50 -> 0 | BK50: =BJ50 -> 0 | BL50: =BK50 -> 0 | BM50: =BL50 -> 0 | BN50: =BM50 -> 0 | ... BQ50: =BP50 -> 0 | BS50: =BQ50 -> 0 | BT50: =BS50 -> 0 | BU50: =BT50 -> 0 | BV50: =BU50 -> 0 | BW50: =BV50 -> 0 | BX50: =BW50 -> 0 | BY50: =BX50 -> 0 | BZ50: =BY50 -> 0 | CA50: =BZ50 -> 0 | ... CD50: =CC50 -> 0 | CF50: =CD50 -> 0 | CG50: =CF50 -> 0 | CH50: =CG50 -> 0 | CI50: =CH50 -> 0 | CJ50: =CI50 -> 0 | CK50: =CJ50 -> 0 | CL50: =CK50 -> 0 | CM50: =CL50 -> 0 | CN50: =CM50 -> 0 | ... CQ50: =CP50 -> 0 | CS50: =CQ50 -> 0 | CT50: =CS50 -> 0 | CU50: =CT50 -> 0 | CV50: =CU50 -> 0 | CW50: =CV50 -> 0 | CX50: =CW50 -> 0 | CY50: =CX50 -> 0 | CZ50: =CY50 -> 0 | DA50: =CZ50 -> 0 | ... DD50: =DC50 -> 0 | DF50: =DD50 -> 0 | DG50: =DF50 -> 0 | DH50: =DG50 -> 0 | DI50: =DH50 -> 0 | DJ50: =DI50 -> 0 | DK50: =DJ50 -> 0 | DL50: =DK50 -> 0 | DM50: =DL50 -> 0 | DN50: =DM50 -> 0 | ... DQ50: =DP50 -> 0 | DS50: =SUM(F50:Q50)+SUM(S50:AD50)+SUM(AF50:AQ50)+SUM(AS50:BD50)+SUM(BF50:BQ50)+SUM(BS50:CD50)+SUM(CF50:CQ50)+SUM(CS50:DD50)+SUM(DF50:DQ50) -> 0
A51: 2 | B51: 6 | C51: =C25 -> /// | D51: =+D25 -> 0 | E51: =E25 -> 0 | G51: =F51 -> 0 | H51: =G51 -> 0 | I51: =H51 -> 0 | J51: =I51 -> 0 | K51: =J51 -> 0 | L51: =K51 -> 0 | M51: =L51 -> 0 | N51: =M51 -> 0 | ... Q51: =P51 -> 0 | S51: =Q51 -> 0 | T51: =S51 -> 0 | U51: =T51 -> 0 | V51: =U51 -> 0 | W51: =V51 -> 0 | X51: =W51 -> 0 | Y51: =X51 -> 0 | Z51: =Y51 -> 0 | AA51: =Z51 -> 0 | ... AD51: =AC51 -> 0 | AF51: =AD51 -> 0 | AG51: =AF51 -> 0 | AH51: =AG51 -> 0 | AI51: =AH51 -> 0 | AJ51: =AI51 -> 0 | AK51: =AJ51 -> 0 | AL51: =AK51 -> 0 | AM51: =AL51 -> 0 | AN51: =AM51 -> 0 | ... AQ51: =AP51 -> 0 | AS51: =AQ51 -> 0 | AT51: =AS51 -> 0 | AU51: =AT51 -> 0 | AV51: =AU51 -> 0 | AW51: =AV51 -> 0 | AX51: =AW51 -> 0 | AY51: =AX51 -> 0 | AZ51: =AY51 -> 0 | BA51: =AZ51 -> 0 | ... BD51: =BC51 -> 0 | BF51: =BD51 -> 0 | BG51: =BF51 -> 0 | BH51: =BG51 -> 0 | BI51: =BH51 -> 0 | BJ51: =BI51 -> 0 | BK51: =BJ51 -> 0 | BL51: =BK51 -> 0 | BM51: =BL51 -> 0 | BN51: =BM51 -> 0 | ... BQ51: =BP51 -> 0 | BS51: =BQ51 -> 0 | BT51: =BS51 -> 0 | BU51: =BT51 -> 0 | BV51: =BU51 -> 0 | BW51: =BV51 -> 0 | BX51: =BW51 -> 0 | BY51: =BX51 -> 0 | BZ51: =BY51 -> 0 | CA51: =BZ51 -> 0 | ... CD51: =CC51 -> 0 | CF51: =CD51 -> 0 | CG51: =CF51 -> 0 | CH51: =CG51 -> 0 | CI51: =CH51 -> 0 | CJ51: =CI51 -> 0 | CK51: =CJ51 -> 0 | CL51: =CK51 -> 0 | CM51: =CL51 -> 0 | CN51: =CM51 -> 0 | ... CQ51: =CP51 -> 0 | CS51: =CQ51 -> 0 | CT51: =CS51 -> 0 | CU51: =CT51 -> 0 | CV51: =CU51 -> 0 | CW51: =CV51 -> 0 | CX51: =CW51 -> 0 | CY51: =CX51 -> 0 | CZ51: =CY51 -> 0 | DA51: =CZ51 -> 0 | ... DD51: =DC51 -> 0 | DF51: =DD51 -> 0 | DG51: =DF51 -> 0 | DH51: =DG51 -> 0 | DI51: =DH51 -> 0 | DJ51: =DI51 -> 0 | DK51: =DJ51 -> 0 | DL51: =DK51 -> 0 | DM51: =DL51 -> 0 | DN51: =DM51 -> 0 | ... DQ51: =DP51 -> 0 | DS51: =SUM(F51:Q51)+SUM(S51:AD51)+SUM(AF51:AQ51)+SUM(AS51:BD51)+SUM(BF51:BQ51)+SUM(BS51:CD51)+SUM(CF51:CQ51)+SUM(CS51:DD51)+SUM(DF51:DQ51) -> 0
C52: =C26 -> /// | D52: =+D26 -> 0 | E52: =E26 -> 0 | G52: =F52 -> 0 | H52: =G52 -> 0 | I52: =H52 -> 0 | J52: =I52 -> 0 | K52: =J52 -> 0 | L52: =K52 -> 0 | M52: =L52 -> 0 | N52: =M52 -> 0 | ... Q52: =P52 -> 0 | S52: =Q52 -> 0 | T52: =S52 -> 0 | U52: =T52 -> 0 | V52: =U52 -> 0 | W52: =V52 -> 0 | X52: =W52 -> 0 | Y52: =X52 -> 0 | Z52: =Y52 -> 0 | AA52: =Z52 -> 0 | ... AD52: =AC52 -> 0 | AF52: =AD52 -> 0 | AG52: =AF52 -> 0 | AH52: =AG52 -> 0 | AI52: =AH52 -> 0 | AJ52: =AI52 -> 0 | AK52: =AJ52 -> 0 | AL52: =AK52 -> 0 | AM52: =AL52 -> 0 | AN52: =AM52 -> 0 | ... AQ52: =AP52 -> 0 | AS52: =AQ52 -> 0 | AT52: =AS52 -> 0 | AU52: =AT52 -> 0 | AV52: =AU52 -> 0 | AW52: =AV52 -> 0 | AX52: =AW52 -> 0 | AY52: =AX52 -> 0 | AZ52: =AY52 -> 0 | BA52: =AZ52 -> 0 | ... BD52: =BC52 -> 0 | BF52: =BD52 -> 0 | BG52: =BF52 -> 0 | BH52: =BG52 -> 0 | BI52: =BH52 -> 0 | BJ52: =BI52 -> 0 | BK52: =BJ52 -> 0 | BL52: =BK52 -> 0 | BM52: =BL52 -> 0 | BN52: =BM52 -> 0 | ... BQ52: =BP52 -> 0 | BS52: =BQ52 -> 0 | BT52: =BS52 -> 0 | BU52: =BT52 -> 0 | BV52: =BU52 -> 0 | BW52: =BV52 -> 0 | BX52: =BW52 -> 0 | BY52: =BX52 -> 0 | BZ52: =BY52 -> 0 | CA52: =BZ52 -> 0 | ... CD52: =CC52 -> 0 | CF52: =CD52 -> 0 | CG52: =CF52 -> 0 | CH52: =CG52 -> 0 | CI52: =CH52 -> 0 | CJ52: =CI52 -> 0 | CK52: =CJ52 -> 0 | CL52: =CK52 -> 0 | CM52: =CL52 -> 0 | CN52: =CM52 -> 0 | ... CQ52: =CP52 -> 0 | CS52: =CQ52 -> 0 | CT52: =CS52 -> 0 | CU52: =CT52 -> 0 | CV52: =CU52 -> 0 | CW52: =CV52 -> 0 | CX52: =CW52 -> 0 | CY52: =CX52 -> 0 | CZ52: =CY52 -> 0 | DA52: =CZ52 -> 0 | ... DD52: =DC52 -> 0 | DF52: =DD52 -> 0 | DG52: =DF52 -> 0 | DH52: =DG52 -> 0 | DI52: =DH52 -> 0 | DJ52: =DI52 -> 0 | DK52: =DJ52 -> 0 | DL52: =DK52 -> 0 | DM52: =DL52 -> 0 | DN52: =DM52 -> 0 | ... DQ52: =DP52 -> 0 | DS52: =SUM(F52:Q52)+SUM(S52:AD52)+SUM(AF52:AQ52)+SUM(AS52:BD52)+SUM(BF52:BQ52)+SUM(BS52:CD52)+SUM(CF52:CQ52)+SUM(CS52:DD52)+SUM(DF52:DQ52) -> 0
A53: 2 | B53: 7 | C53: =C27 -> /// | D53: =+D27 -> 0 | E53: =E27 -> 0 | G53: =F53 -> 0 | H53: =G53 -> 0 | I53: =H53 -> 0 | J53: =I53 -> 0 | K53: =J53 -> 0 | L53: =K53 -> 0 | M53: =L53 -> 0 | N53: =M53 -> 0 | ... Q53: =P53 -> 0 | S53: =Q53 -> 0 | T53: =S53 -> 0 | U53: =T53 -> 0 | V53: =U53 -> 0 | W53: =V53 -> 0 | X53: =W53 -> 0 | Y53: =X53 -> 0 | Z53: =Y53 -> 0 | AA53: =Z53 -> 0 | ... AD53: =AC53 -> 0 | AF53: =AD53 -> 0 | AG53: =AF53 -> 0 | AH53: =AG53 -> 0 | AI53: =AH53 -> 0 | AJ53: =AI53 -> 0 | AK53: =AJ53 -> 0 | AL53: =AK53 -> 0 | AM53: =AL53 -> 0 | AN53: =AM53 -> 0 | ... AQ53: =AP53 -> 0 | AS53: =AQ53 -> 0 | AT53: =AS53 -> 0 | AU53: =AT53 -> 0 | AV53: =AU53 -> 0 | AW53: =AV53 -> 0 | AX53: =AW53 -> 0 | AY53: =AX53 -> 0 | AZ53: =AY53 -> 0 | BA53: =AZ53 -> 0 | ... BD53: =BC53 -> 0 | BF53: =BD53 -> 0 | BG53: =BF53 -> 0 | BH53: =BG53 -> 0 | BI53: =BH53 -> 0 | BJ53: =BI53 -> 0 | BK53: =BJ53 -> 0 | BL53: =BK53 -> 0 | BM53: =BL53 -> 0 | BN53: =BM53 -> 0 | ... BQ53: =BP53 -> 0 | BS53: =BQ53 -> 0 | BT53: =BS53 -> 0 | BU53: =BT53 -> 0 | BV53: =BU53 -> 0 | BW53: =BV53 -> 0 | BX53: =BW53 -> 0 | BY53: =BX53 -> 0 | BZ53: =BY53 -> 0 | CA53: =BZ53 -> 0 | ... CD53: =CC53 -> 0 | CF53: =CD53 -> 0 | CG53: =CF53 -> 0 | CH53: =CG53 -> 0 | CI53: =CH53 -> 0 | CJ53: =CI53 -> 0 | CK53: =CJ53 -> 0 | CL53: =CK53 -> 0 | CM53: =CL53 -> 0 | CN53: =CM53 -> 0 | ... CQ53: =CP53 -> 0 | CS53: =CQ53 -> 0 | CT53: =CS53 -> 0 | CU53: =CT53 -> 0 | CV53: =CU53 -> 0 | CW53: =CV53 -> 0 | CX53: =CW53 -> 0 | CY53: =CX53 -> 0 | CZ53: =CY53 -> 0 | DA53: =CZ53 -> 0 | ... DD53: =DC53 -> 0 | DF53: =DD53 -> 0 | DG53: =DF53 -> 0 | DH53: =DG53 -> 0 | DI53: =DH53 -> 0 | DJ53: =DI53 -> 0 | DK53: =DJ53 -> 0 | DL53: =DK53 -> 0 | DM53: =DL53 -> 0 | DN53: =DM53 -> 0 | ... DQ53: =DP53 -> 0 | DS53: =SUM(F53:Q53)+SUM(S53:AD53)+SUM(AF53:AQ53)+SUM(AS53:BD53)+SUM(BF53:BQ53)+SUM(BS53:CD53)+SUM(CF53:CQ53)+SUM(CS53:DD53)+SUM(DF53:DQ53) -> 0
C54: =C28 -> /// | D54: =+D28 -> 0 | E54: =E28 -> 0 | G54: =F54 -> 0 | H54: =G54 -> 0 | I54: =H54 -> 0 | J54: =I54 -> 0 | K54: =J54 -> 0 | L54: =K54 -> 0 | M54: =L54 -> 0 | N54: =M54 -> 0 | ... Q54: =P54 -> 0 | S54: =Q54 -> 0 | T54: =S54 -> 0 | U54: =T54 -> 0 | V54: =U54 -> 0 | W54: =V54 -> 0 | X54: =W54 -> 0 | Y54: =X54 -> 0 | Z54: =Y54 -> 0 | AA54: =Z54 -> 0 | ... AD54: =AC54 -> 0 | AF54: =AD54 -> 0 | AG54: =AF54 -> 0 | AH54: =AG54 -> 0 | AI54: =AH54 -> 0 | AJ54: =AI54 -> 0 | AK54: =AJ54 -> 0 | AL54: =AK54 -> 0 | AM54: =AL54 -> 0 | AN54: =AM54 -> 0 | ... AQ54: =AP54 -> 0 | AS54: =AQ54 -> 0 | AT54: =AS54 -> 0 | AU54: =AT54 -> 0 | AV54: =AU54 -> 0 | AW54: =AV54 -> 0 | AX54: =AW54 -> 0 | AY54: =AX54 -> 0 | AZ54: =AY54 -> 0 | BA54: =AZ54 -> 0 | ... BD54: =BC54 -> 0 | BF54: =BD54 -> 0 | BG54: =BF54 -> 0 | BH54: =BG54 -> 0 | BI54: =BH54 -> 0 | BJ54: =BI54 -> 0 | BK54: =BJ54 -> 0 | BL54: =BK54 -> 0 | BM54: =BL54 -> 0 | BN54: =BM54 -> 0 | ... BQ54: =BP54 -> 0 | BS54: =BQ54 -> 0 | BT54: =BS54 -> 0 | BU54: =BT54 -> 0 | BV54: =BU54 -> 0 | BW54: =BV54 -> 0 | BX54: =BW54 -> 0 | BY54: =BX54 -> 0 | BZ54: =BY54 -> 0 | CA54: =BZ54 -> 0 | ... CD54: =CC54 -> 0 | CF54: =CD54 -> 0 | CG54: =CF54 -> 0 | CH54: =CG54 -> 0 | CI54: =CH54 -> 0 | CJ54: =CI54 -> 0 | CK54: =CJ54 -> 0 | CL54: =CK54 -> 0 | CM54: =CL54 -> 0 | CN54: =CM54 -> 0 | ... CQ54: =CP54 -> 0 | CS54: =CQ54 -> 0 | CT54: =CS54 -> 0 | CU54: =CT54 -> 0 | CV54: =CU54 -> 0 | CW54: =CV54 -> 0 | CX54: =CW54 -> 0 | CY54: =CX54 -> 0 | CZ54: =CY54 -> 0 | DA54: =CZ54 -> 0 | ... DD54: =DC54 -> 0 | DF54: =DD54 -> 0 | DG54: =DF54 -> 0 | DH54: =DG54 -> 0 | DI54: =DH54 -> 0 | DJ54: =DI54 -> 0 | DK54: =DJ54 -> 0 | DL54: =DK54 -> 0 | DM54: =DL54 -> 0 | DN54: =DM54 -> 0 | ... DQ54: =DP54 -> 0 | DS54: =SUM(F54:Q54)+SUM(S54:AD54)+SUM(AF54:AQ54)+SUM(AS54:BD54)+SUM(BF54:BQ54)+SUM(BS54:CD54)+SUM(CF54:CQ54)+SUM(CS54:DD54)+SUM(DF54:DQ54) -> 0
A55: 2 | B55: 8 | C55: =C29 -> /// | D55: =+D29 -> 0 | E55: =E29 -> 0 | G55: =F55 -> 0 | H55: =G55 -> 0 | I55: =H55 -> 0 | J55: =I55 -> 0 | K55: =J55 -> 0 | L55: =K55 -> 0 | M55: =L55 -> 0 | N55: =M55 -> 0 | ... Q55: =P55 -> 0 | S55: =Q55 -> 0 | T55: =S55 -> 0 | U55: =T55 -> 0 | V55: =U55 -> 0 | W55: =V55 -> 0 | X55: =W55 -> 0 | Y55: =X55 -> 0 | Z55: =Y55 -> 0 | AA55: =Z55 -> 0 | ... AD55: =AC55 -> 0 | AF55: =AD55 -> 0 | AG55: =AF55 -> 0 | AH55: =AG55 -> 0 | AI55: =AH55 -> 0 | AJ55: =AI55 -> 0 | AK55: =AJ55 -> 0 | AL55: =AK55 -> 0 | AM55: =AL55 -> 0 | AN55: =AM55 -> 0 | ... AQ55: =AP55 -> 0 | AS55: =AQ55 -> 0 | AT55: =AS55 -> 0 | AU55: =AT55 -> 0 | AV55: =AU55 -> 0 | AW55: =AV55 -> 0 | AX55: =AW55 -> 0 | AY55: =AX55 -> 0 | AZ55: =AY55 -> 0 | BA55: =AZ55 -> 0 | ... BD55: =BC55 -> 0 | BF55: =BD55 -> 0 | BG55: =BF55 -> 0 | BH55: =BG55 -> 0 | BI55: =BH55 -> 0 | BJ55: =BI55 -> 0 | BK55: =BJ55 -> 0 | BL55: =BK55 -> 0 | BM55: =BL55 -> 0 | BN55: =BM55 -> 0 | ... BQ55: =BP55 -> 0 | BS55: =BQ55 -> 0 | BT55: =BS55 -> 0 | BU55: =BT55 -> 0 | BV55: =BU55 -> 0 | BW55: =BV55 -> 0 | BX55: =BW55 -> 0 | BY55: =BX55 -> 0 | BZ55: =BY55 -> 0 | CA55: =BZ55 -> 0 | ... CD55: =CC55 -> 0 | CF55: =CD55 -> 0 | CG55: =CF55 -> 0 | CH55: =CG55 -> 0 | CI55: =CH55 -> 0 | CJ55: =CI55 -> 0 | CK55: =CJ55 -> 0 | CL55: =CK55 -> 0 | CM55: =CL55 -> 0 | CN55: =CM55 -> 0 | ... CQ55: =CP55 -> 0 | CS55: =CQ55 -> 0 | CT55: =CS55 -> 0 | CU55: =CT55 -> 0 | CV55: =CU55 -> 0 | CW55: =CV55 -> 0 | CX55: =CW55 -> 0 | CY55: =CX55 -> 0 | CZ55: =CY55 -> 0 | DA55: =CZ55 -> 0 | ... DD55: =DC55 -> 0 | DF55: =DD55 -> 0 | DG55: =DF55 -> 0 | DH55: =DG55 -> 0 | DI55: =DH55 -> 0 | DJ55: =DI55 -> 0 | DK55: =DJ55 -> 0 | DL55: =DK55 -> 0 | DM55: =DL55 -> 0 | DN55: =DM55 -> 0 | ... DQ55: =DP55 -> 0 | DS55: =SUM(F55:Q55)+SUM(S55:AD55)+SUM(AF55:AQ55)+SUM(AS55:BD55)+SUM(BF55:BQ55)+SUM(BS55:CD55)+SUM(CF55:CQ55)+SUM(CS55:DD55)+SUM(DF55:DQ55) -> 0
A56: 2 | B56: 9 | C56: Open | G56: =F56 -> 0 | H56: =G56 -> 0 | I56: =H56 -> 0 | J56: =I56 -> 0 | K56: =J56 -> 0 | L56: =K56 -> 0 | M56: =L56 -> 0 | N56: =M56 -> 0 | ... Q56: =P56 -> 0 | S56: =Q56 -> 0 | T56: =S56 -> 0 | U56: =T56 -> 0 | V56: =U56 -> 0 | W56: =V56 -> 0 | X56: =W56 -> 0 | Y56: =X56 -> 0 | Z56: =Y56 -> 0 | AA56: =Z56 -> 0 | ... AD56: =AC56 -> 0 | AF56: =AD56 -> 0 | AG56: =AF56 -> 0 | AH56: =AG56 -> 0 | AI56: =AH56 -> 0 | AJ56: =AI56 -> 0 | AK56: =AJ56 -> 0 | AL56: =AK56 -> 0 | AM56: =AL56 -> 0 | AN56: =AM56 -> 0 | ... AQ56: =AP56 -> 0 | AS56: =AQ56 -> 0 | AT56: =AS56 -> 0 | AU56: =AT56 -> 0 | AV56: =AU56 -> 0 | AW56: =AV56 -> 0 | AX56: =AW56 -> 0 | AY56: =AX56 -> 0 | AZ56: =AY56 -> 0 | BA56: =AZ56 -> 0 | ... BD56: =BC56 -> 0 | BF56: =BD56 -> 0 | BG56: =BF56 -> 0 | BH56: =BG56 -> 0 | BI56: =BH56 -> 0 | BJ56: =BI56 -> 0 | BK56: =BJ56 -> 0 | BL56: =BK56 -> 0 | BM56: =BL56 -> 0 | BN56: =BM56 -> 0 | ... BQ56: =BP56 -> 0 | BS56: =BQ56 -> 0 | BT56: =BS56 -> 0 | BU56: =BT56 -> 0 | BV56: =BU56 -> 0 | BW56: =BV56 -> 0 | BX56: =BW56 -> 0 | BY56: =BX56 -> 0 | BZ56: =BY56 -> 0 | CA56: =BZ56 -> 0 | ... CD56: =CC56 -> 0 | CF56: =CD56 -> 0 | CG56: =CF56 -> 0 | CH56: =CG56 -> 0 | CI56: =CH56 -> 0 | CJ56: =CI56 -> 0 | CK56: =CJ56 -> 0 | CL56: =CK56 -> 0 | CM56: =CL56 -> 0 | CN56: =CM56 -> 0 | ... CQ56: =CP56 -> 0 | CS56: =CQ56 -> 0 | CT56: =CS56 -> 0 | CU56: =CT56 -> 0 | CV56: =CU56 -> 0 | CW56: =CV56 -> 0 | CX56: =CW56 -> 0 | CY56: =CX56 -> 0 | CZ56: =CY56 -> 0 | DA56: =CZ56 -> 0 | ... DD56: =DC56 -> 0 | DF56: =DD56 -> 0 | DG56: =DF56 -> 0 | DH56: =DG56 -> 0 | DI56: =DH56 -> 0 | DJ56: =DI56 -> 0 | DK56: =DJ56 -> 0 | DL56: =DK56 -> 0 | DM56: =DL56 -> 0 | DN56: =DM56 -> 0 | ... DQ56: =DP56 -> 0 | DS56: =SUM(F56:Q56)+SUM(S56:AD56)+SUM(AF56:AQ56)+SUM(AS56:BD56)+SUM(BF56:BQ56)+SUM(BS56:CD56) -> 0
C57: Open | F57: 0 | G57: =F57 -> 0 | H57: =G57 -> 0 | I57: =H57 -> 0 | J57: =I57 -> 0 | K57: =J57 -> 0 | L57: =K57 -> 0 | M57: =L57 -> 0 | N57: =M57 -> 0 | ... Q57: =P57 -> 0 | S57: =Q57 -> 0 | T57: =S57 -> 0 | U57: =T57 -> 0 | V57: =U57 -> 0 | W57: =V57 -> 0 | X57: =W57 -> 0 | Y57: =X57 -> 0 | Z57: =Y57 -> 0 | AA57: =Z57 -> 0 | ... AD57: =AC57 -> 0 | AR57: =AD57*AR$4/12 -> 0 | BE57: =AR57*BE$4/12 -> 0 | BR57: =BE57*BR$4/12 -> 0 | CE57: =BR57*CE$4/12 -> 0 | CR57: =CE57*CR$4/12 -> 0 | DE57: =CR57*DE$4/12 -> 0 | DR57: =DE57*DR$4/12 -> 0
C58: =$C32 -> Subtotal | F58: =SUM(F35:F57) -> 0 | G58: =SUM(G35:G57) -> 0 | H58: =SUM(H35:H57) -> 0 | I58: =SUM(I35:I57) -> 0 | J58: =SUM(J35:J57) -> 0 | K58: =SUM(K35:K57) -> 0 | L58: =SUM(L35:L57) -> 0 | M58: =SUM(M35:M57) -> 0 | ... DT58: =SUM(DT35:DT57) -> 0
C60: Onsite - H1 / Extended L1
C61: =C35 -> IT/JavaNetColdFusionIT/DeveloperJavaNetColdFusion/Junior | E61: =E35 -> B2 AP1 / B2 AP2 (0.6 to 3 yrs) | G61: =F61 -> 0 | H61: =G61 -> 0 | I61: =H61 -> 0 | J61: =I61 -> 0 | K61: =J61 -> 0 | L61: =K61 -> 0 | M61: =L61 -> 0 | N61: =M61 -> 0 | ... Q61: =P61 -> 0 | T61: =S61 -> 0 | U61: =T61 -> 0 | V61: =U61 -> 0 | W61: =V61 -> 0 | X61: =W61 -> 0 | Y61: =X61 -> 0 | Z61: =Y61 -> 0 | AA61: =Z61 -> 0 | ... AD61: =AC61 -> 0 | AF61: =AD61 -> 0 | AG61: =AF61 -> 0 | AH61: =AG61 -> 0 | AI61: =AH61 -> 0 | AJ61: =AI61 -> 0 | AK61: =AJ61 -> 0 | AL61: =AK61 -> 0 | AM61: =AL61 -> 0 | AN61: =AM61 -> 0 | ... AQ61: =AP61 -> 0 | AS61: =AQ61 -> 0 | AT61: =AS61 -> 0 | AU61: =AT61 -> 0 | AV61: =AU61 -> 0 | AW61: =AV61 -> 0 | AX61: =AW61 -> 0 | AY61: =AX61 -> 0 | AZ61: =AY61 -> 0 | BA61: =AZ61 -> 0 | ... BD61: =BC61 -> 0 | BF61: =BD61 -> 0 | BG61: =BF61 -> 0 | BH61: =BG61 -> 0 | BI61: =BH61 -> 0 | BJ61: =BI61 -> 0 | BK61: =BJ61 -> 0 | BL61: =BK61 -> 0 | BM61: =BL61 -> 0 | BN61: =BM61 -> 0 | ... BQ61: =BP61 -> 0 | BS61: =BQ61 -> 0 | BT61: =BS61 -> 0 | BU61: =BT61 -> 0 | BV61: =BU61 -> 0 | BW61: =BV61 -> 0 | BX61: =BW61 -> 0 | BY61: =BX61 -> 0 | BZ61: =BY61 -> 0 | CA61: =BZ61 -> 0 | ... CD61: =CC61 -> 0 | CF61: =CD61 -> 0 | CG61: =CF61 -> 0 | CH61: =CG61 -> 0 | CI61: =CH61 -> 0 | CJ61: =CI61 -> 0 | CK61: =CJ61 -> 0 | CL61: =CK61 -> 0 | CM61: =CL61 -> 0 | CN61: =CM61 -> 0 | ... CQ61: =CP61 -> 0 | CS61: =CQ61 -> 0 | CT61: =CS61 -> 0 | CU61: =CT61 -> 0 | CV61: =CU61 -> 0 | CW61: =CV61 -> 0 | CX61: =CW61 -> 0 | CY61: =CX61 -> 0 | CZ61: =CY61 -> 0 | DA61: =CZ61 -> 0 | ... DD61: =DC61 -> 0 | DF61: =DD61 -> 0 | DG61: =DF61 -> 0 | DH61: =DG61 -> 0 | DI61: =DH61 -> 0 | DJ61: =DI61 -> 0 | DK61: =DJ61 -> 0 | DL61: =DK61 -> 0 | DM61: =DL61 -> 0 | DN61: =DM61 -> 0 | ... DQ61: =DP61 -> 0 | DS61: =SUM(F61:Q61)+SUM(S61:AD61)+SUM(AF61:AQ61)+SUM(AS61:BD61)+SUM(BF61:BQ61)+SUM(BS61:CD61) -> 0
C62: =C36 -> /// | E62: =E36 -> 0 | G62: =F62 -> 0 | H62: =G62 -> 0 | I62: =H62 -> 0 | J62: =I62 -> 0 | K62: =J62 -> 0 | L62: =K62 -> 0 | M62: =L62 -> 0 | N62: =M62 -> 0 | ... Q62: =P62 -> 0 | T62: =S62 -> 0 | U62: =T62 -> 0 | V62: =U62 -> 0 | W62: =V62 -> 0 | X62: =W62 -> 0 | Y62: =X62 -> 0 | Z62: =Y62 -> 0 | AA62: =Z62 -> 0 | ... AD62: =AC62 -> 0 | AF62: =AD62 -> 0 | AG62: =AF62 -> 0 | AH62: =AG62 -> 0 | AI62: =AH62 -> 0 | AJ62: =AI62 -> 0 | AK62: =AJ62 -> 0 | AL62: =AK62 -> 0 | AM62: =AL62 -> 0 | AN62: =AM62 -> 0 | ... AQ62: =AP62 -> 0 | AS62: =AQ62 -> 0 | AT62: =AS62 -> 0 | AU62: =AT62 -> 0 | AV62: =AU62 -> 0 | AW62: =AV62 -> 0 | AX62: =AW62 -> 0 | AY62: =AX62 -> 0 | AZ62: =AY62 -> 0 | BA62: =AZ62 -> 0 | ... BD62: =BC62 -> 0 | BF62: =BD62 -> 0 | BG62: =BF62 -> 0 | BH62: =BG62 -> 0 | BI62: =BH62 -> 0 | BJ62: =BI62 -> 0 | BK62: =BJ62 -> 0 | BL62: =BK62 -> 0 | BM62: =BL62 -> 0 | BN62: =BM62 -> 0 | ... BQ62: =BP62 -> 0 | BS62: =BQ62 -> 0 | BT62: =BS62 -> 0 | BU62: =BT62 -> 0 | BV62: =BU62 -> 0 | BW62: =BV62 -> 0 | BX62: =BW62 -> 0 | BY62: =BX62 -> 0 | BZ62: =BY62 -> 0 | CA62: =BZ62 -> 0 | ... CD62: =CC62 -> 0 | CF62: =CD62 -> 0 | CG62: =CF62 -> 0 | CH62: =CG62 -> 0 | CI62: =CH62 -> 0 | CJ62: =CI62 -> 0 | CK62: =CJ62 -> 0 | CL62: =CK62 -> 0 | CM62: =CL62 -> 0 | CN62: =CM62 -> 0 | ... CQ62: =CP62 -> 0 | CS62: =CQ62 -> 0 | CT62: =CS62 -> 0 | CU62: =CT62 -> 0 | CV62: =CU62 -> 0 | CW62: =CV62 -> 0 | CX62: =CW62 -> 0 | CY62: =CX62 -> 0 | CZ62: =CY62 -> 0 | DA62: =CZ62 -> 0 | ... DD62: =DC62 -> 0 | DF62: =DD62 -> 0 | DG62: =DF62 -> 0 | DH62: =DG62 -> 0 | DI62: =DH62 -> 0 | DJ62: =DI62 -> 0 | DK62: =DJ62 -> 0 | DL62: =DK62 -> 0 | DM62: =DL62 -> 0 | DN62: =DM62 -> 0 | ... DQ62: =DP62 -> 0 | DS62: =SUM(F62:Q62)+SUM(S62:AD62)+SUM(AF62:AQ62)+SUM(AS62:BD62)+SUM(BF62:BQ62)+SUM(BS62:CD62) -> 0
C63: =C37 -> /// | E63: =E37 -> 0 | G63: =F63 -> 0 | H63: =G63 -> 0 | I63: =H63 -> 0 | J63: =I63 -> 0 | K63: =J63 -> 0 | L63: =K63 -> 0 | M63: =L63 -> 0 | N63: =M63 -> 0 | ... Q63: =P63 -> 0 | T63: =S63 -> 0 | U63: =T63 -> 0 | V63: =U63 -> 0 | W63: =V63 -> 0 | X63: =W63 -> 0 | Y63: =X63 -> 0 | Z63: =Y63 -> 0 | AA63: =Z63 -> 0 | ... AD63: =AC63 -> 0 | AF63: =AD63 -> 0 | AG63: =AF63 -> 0 | AH63: =AG63 -> 0 | AI63: =AH63 -> 0 | AJ63: =AI63 -> 0 | AK63: =AJ63 -> 0 | AL63: =AK63 -> 0 | AM63: =AL63 -> 0 | AN63: =AM63 -> 0 | ... AQ63: =AP63 -> 0 | AS63: =AQ63 -> 0 | AT63: =AS63 -> 0 | AU63: =AT63 -> 0 | AV63: =AU63 -> 0 | AW63: =AV63 -> 0 | AX63: =AW63 -> 0 | AY63: =AX63 -> 0 | AZ63: =AY63 -> 0 | BA63: =AZ63 -> 0 | ... BD63: =BC63 -> 0 | BF63: =BD63 -> 0 | BG63: =BF63 -> 0 | BH63: =BG63 -> 0 | BI63: =BH63 -> 0 | BJ63: =BI63 -> 0 | BK63: =BJ63 -> 0 | BL63: =BK63 -> 0 | BM63: =BL63 -> 0 | BN63: =BM63 -> 0 | ... BQ63: =BP63 -> 0 | BS63: =BQ63 -> 0 | BT63: =BS63 -> 0 | BU63: =BT63 -> 0 | BV63: =BU63 -> 0 | BW63: =BV63 -> 0 | BX63: =BW63 -> 0 | BY63: =BX63 -> 0 | BZ63: =BY63 -> 0 | CA63: =BZ63 -> 0 | ... CD63: =CC63 -> 0 | CF63: =CD63 -> 0 | CG63: =CF63 -> 0 | CH63: =CG63 -> 0 | CI63: =CH63 -> 0 | CJ63: =CI63 -> 0 | CK63: =CJ63 -> 0 | CL63: =CK63 -> 0 | CM63: =CL63 -> 0 | CN63: =CM63 -> 0 | ... CQ63: =CP63 -> 0 | CS63: =CQ63 -> 0 | CT63: =CS63 -> 0 | CU63: =CT63 -> 0 | CV63: =CU63 -> 0 | CW63: =CV63 -> 0 | CX63: =CW63 -> 0 | CY63: =CX63 -> 0 | CZ63: =CY63 -> 0 | DA63: =CZ63 -> 0 | ... DD63: =DC63 -> 0 | DF63: =DD63 -> 0 | DG63: =DF63 -> 0 | DH63: =DG63 -> 0 | DI63: =DH63 -> 0 | DJ63: =DI63 -> 0 | DK63: =DJ63 -> 0 | DL63: =DK63 -> 0 | DM63: =DL63 -> 0 | DN63: =DM63 -> 0 | ... DQ63: =DP63 -> 0 | DS63: =SUM(F63:Q63)+SUM(S63:AD63)+SUM(AF63:AQ63)+SUM(AS63:BD63)+SUM(BF63:BQ63)+SUM(BS63:CD63) -> 0
C64: =C38 -> /// | E64: =E38 -> 0 | G64: =F64 -> 0 | H64: =G64 -> 0 | I64: =H64 -> 0 | J64: =I64 -> 0 | K64: =J64 -> 0 | L64: =K64 -> 0 | M64: =L64 -> 0 | N64: =M64 -> 0 | ... Q64: =P64 -> 0 | T64: =S64 -> 0 | U64: =T64 -> 0 | V64: =U64 -> 0 | W64: =V64 -> 0 | X64: =W64 -> 0 | Y64: =X64 -> 0 | Z64: =Y64 -> 0 | AA64: =Z64 -> 0 | ... AD64: =AC64 -> 0 | AF64: =AD64 -> 0 | AG64: =AF64 -> 0 | AH64: =AG64 -> 0 | AI64: =AH64 -> 0 | AJ64: =AI64 -> 0 | AK64: =AJ64 -> 0 | AL64: =AK64 -> 0 | AM64: =AL64 -> 0 | AN64: =AM64 -> 0 | ... AQ64: =AP64 -> 0 | AS64: =AQ64 -> 0 | AT64: =AS64 -> 0 | AU64: =AT64 -> 0 | AV64: =AU64 -> 0 | AW64: =AV64 -> 0 | AX64: =AW64 -> 0 | AY64: =AX64 -> 0 | AZ64: =AY64 -> 0 | BA64: =AZ64 -> 0 | ... BD64: =BC64 -> 0 | BF64: =BD64 -> 0 | BG64: =BF64 -> 0 | BH64: =BG64 -> 0 | BI64: =BH64 -> 0 | BJ64: =BI64 -> 0 | BK64: =BJ64 -> 0 | BL64: =BK64 -> 0 | BM64: =BL64 -> 0 | BN64: =BM64 -> 0 | ... BQ64: =BP64 -> 0 | BS64: =BQ64 -> 0 | BT64: =BS64 -> 0 | BU64: =BT64 -> 0 | BV64: =BU64 -> 0 | BW64: =BV64 -> 0 | BX64: =BW64 -> 0 | BY64: =BX64 -> 0 | BZ64: =BY64 -> 0 | CA64: =BZ64 -> 0 | ... CD64: =CC64 -> 0 | CF64: =CD64 -> 0 | CG64: =CF64 -> 0 | CH64: =CG64 -> 0 | CI64: =CH64 -> 0 | CJ64: =CI64 -> 0 | CK64: =CJ64 -> 0 | CL64: =CK64 -> 0 | CM64: =CL64 -> 0 | CN64: =CM64 -> 0 | ... CQ64: =CP64 -> 0 | CS64: =CQ64 -> 0 | CT64: =CS64 -> 0 | CU64: =CT64 -> 0 | CV64: =CU64 -> 0 | CW64: =CV64 -> 0 | CX64: =CW64 -> 0 | CY64: =CX64 -> 0 | CZ64: =CY64 -> 0 | DA64: =CZ64 -> 0 | ... DD64: =DC64 -> 0 | DF64: =DD64 -> 0 | DG64: =DF64 -> 0 | DH64: =DG64 -> 0 | DI64: =DH64 -> 0 | DJ64: =DI64 -> 0 | DK64: =DJ64 -> 0 | DL64: =DK64 -> 0 | DM64: =DL64 -> 0 | DN64: =DM64 -> 0 | ... DQ64: =DP64 -> 0 | DS64: =SUM(F64:Q64)+SUM(S64:AD64)+SUM(AF64:AQ64)+SUM(AS64:BD64)+SUM(BF64:BQ64)+SUM(BS64:CD64) -> 0
A65: 3 | B65: 1 | C65: =C39 -> /// | E65: =E39 -> 0 | G65: =F65 -> 0 | H65: =G65 -> 0 | I65: =H65 -> 0 | J65: =I65 -> 0 | K65: =J65 -> 0 | L65: =K65 -> 0 | M65: =L65 -> 0 | N65: =M65 -> 0 | ... Q65: =P65 -> 0 | T65: =S65 -> 0 | U65: =T65 -> 0 | V65: =U65 -> 0 | W65: =V65 -> 0 | X65: =W65 -> 0 | Y65: =X65 -> 0 | Z65: =Y65 -> 0 | AA65: =Z65 -> 0 | ... AD65: =AC65 -> 0 | AF65: =AD65 -> 0 | AG65: =AF65 -> 0 | AH65: =AG65 -> 0 | AI65: =AH65 -> 0 | AJ65: =AI65 -> 0 | AK65: =AJ65 -> 0 | AL65: =AK65 -> 0 | AM65: =AL65 -> 0 | AN65: =AM65 -> 0 | ... AQ65: =AP65 -> 0 | AS65: =AQ65 -> 0 | AT65: =AS65 -> 0 | AU65: =AT65 -> 0 | AV65: =AU65 -> 0 | AW65: =AV65 -> 0 | AX65: =AW65 -> 0 | AY65: =AX65 -> 0 | AZ65: =AY65 -> 0 | BA65: =AZ65 -> 0 | ... BD65: =BC65 -> 0 | BF65: =BD65 -> 0 | BG65: =BF65 -> 0 | BH65: =BG65 -> 0 | BI65: =BH65 -> 0 | BJ65: =BI65 -> 0 | BK65: =BJ65 -> 0 | BL65: =BK65 -> 0 | BM65: =BL65 -> 0 | BN65: =BM65 -> 0 | ... BQ65: =BP65 -> 0 | BS65: =BQ65 -> 0 | BT65: =BS65 -> 0 | BU65: =BT65 -> 0 | BV65: =BU65 -> 0 | BW65: =BV65 -> 0 | BX65: =BW65 -> 0 | BY65: =BX65 -> 0 | BZ65: =BY65 -> 0 | CA65: =BZ65 -> 0 | ... CD65: =CC65 -> 0 | CF65: =CD65 -> 0 | CG65: =CF65 -> 0 | CH65: =CG65 -> 0 | CI65: =CH65 -> 0 | CJ65: =CI65 -> 0 | CK65: =CJ65 -> 0 | CL65: =CK65 -> 0 | CM65: =CL65 -> 0 | CN65: =CM65 -> 0 | ... CQ65: =CP65 -> 0 | CS65: =CQ65 -> 0 | CT65: =CS65 -> 0 | CU65: =CT65 -> 0 | CV65: =CU65 -> 0 | CW65: =CV65 -> 0 | CX65: =CW65 -> 0 | CY65: =CX65 -> 0 | CZ65: =CY65 -> 0 | DA65: =CZ65 -> 0 | ... DD65: =DC65 -> 0 | DF65: =DD65 -> 0 | DG65: =DF65 -> 0 | DH65: =DG65 -> 0 | DI65: =DH65 -> 0 | DJ65: =DI65 -> 0 | DK65: =DJ65 -> 0 | DL65: =DK65 -> 0 | DM65: =DL65 -> 0 | DN65: =DM65 -> 0 | ... DQ65: =DP65 -> 0 | DS65: =SUM(F65:Q65)+SUM(S65:AD65)+SUM(AF65:AQ65)+SUM(AS65:BD65)+SUM(BF65:BQ65)+SUM(BS65:CD65) -> 0
C66: =C40 -> /// | E66: =E40 -> 0 | G66: =F66 -> 0 | H66: =G66 -> 0 | I66: =H66 -> 0 | J66: =I66 -> 0 | K66: =J66 -> 0 | L66: =K66 -> 0 | M66: =L66 -> 0 | N66: =M66 -> 0 | ... Q66: =P66 -> 0 | S66: =Q66 -> 0 | T66: =S66 -> 0 | U66: =T66 -> 0 | V66: =U66 -> 0 | W66: =V66 -> 0 | X66: =W66 -> 0 | Y66: =X66 -> 0 | Z66: =Y66 -> 0 | AA66: =Z66 -> 0 | ... AD66: =AC66 -> 0 | AF66: =AD66 -> 0 | AG66: =AF66 -> 0 | AH66: =AG66 -> 0 | AI66: =AH66 -> 0 | AJ66: =AI66 -> 0 | AK66: =AJ66 -> 0 | AL66: =AK66 -> 0 | AM66: =AL66 -> 0 | AN66: =AM66 -> 0 | ... AQ66: =AP66 -> 0 | AS66: =AQ66 -> 0 | AT66: =AS66 -> 0 | AU66: =AT66 -> 0 | AV66: =AU66 -> 0 | AW66: =AV66 -> 0 | AX66: =AW66 -> 0 | AY66: =AX66 -> 0 | AZ66: =AY66 -> 0 | BA66: =AZ66 -> 0 | ... BD66: =BC66 -> 0 | BF66: =BD66 -> 0 | BG66: =BF66 -> 0 | BH66: =BG66 -> 0 | BI66: =BH66 -> 0 | BJ66: =BI66 -> 0 | BK66: =BJ66 -> 0 | BL66: =BK66 -> 0 | BM66: =BL66 -> 0 | BN66: =BM66 -> 0 | ... BQ66: =BP66 -> 0 | BS66: =BQ66 -> 0 | BT66: =BS66 -> 0 | BU66: =BT66 -> 0 | BV66: =BU66 -> 0 | BW66: =BV66 -> 0 | BX66: =BW66 -> 0 | BY66: =BX66 -> 0 | BZ66: =BY66 -> 0 | CA66: =BZ66 -> 0 | ... CD66: =CC66 -> 0 | CF66: =CD66 -> 0 | CG66: =CF66 -> 0 | CH66: =CG66 -> 0 | CI66: =CH66 -> 0 | CJ66: =CI66 -> 0 | CK66: =CJ66 -> 0 | CL66: =CK66 -> 0 | CM66: =CL66 -> 0 | CN66: =CM66 -> 0 | ... CQ66: =CP66 -> 0 | CS66: =CQ66 -> 0 | CT66: =CS66 -> 0 | CU66: =CT66 -> 0 | CV66: =CU66 -> 0 | CW66: =CV66 -> 0 | CX66: =CW66 -> 0 | CY66: =CX66 -> 0 | CZ66: =CY66 -> 0 | DA66: =CZ66 -> 0 | ... DD66: =DC66 -> 0 | DF66: =DD66 -> 0 | DG66: =DF66 -> 0 | DH66: =DG66 -> 0 | DI66: =DH66 -> 0 | DJ66: =DI66 -> 0 | DK66: =DJ66 -> 0 | DL66: =DK66 -> 0 | DM66: =DL66 -> 0 | DN66: =DM66 -> 0 | ... DQ66: =DP66 -> 0 | DS66: =SUM(F66:Q66)+SUM(S66:AD66)+SUM(AF66:AQ66)+SUM(AS66:BD66)+SUM(BF66:BQ66)+SUM(BS66:CD66) -> 0
A67: 3 | B67: 2 | C67: =C41 -> /// | E67: =E41 -> 0 | G67: =F67 -> 0 | H67: =G67 -> 0 | I67: =H67 -> 0 | J67: =I67 -> 0 | K67: =J67 -> 0 | L67: =K67 -> 0 | M67: =L67 -> 0 | N67: =M67 -> 0 | ... Q67: =P67 -> 0 | S67: =Q67 -> 0 | T67: =S67 -> 0 | U67: =T67 -> 0 | V67: =U67 -> 0 | W67: =V67 -> 0 | X67: =W67 -> 0 | Y67: =X67 -> 0 | Z67: =Y67 -> 0 | AA67: =Z67 -> 0 | ... AD67: =AC67 -> 0 | AF67: =AD67 -> 0 | AG67: =AF67 -> 0 | AH67: =AG67 -> 0 | AI67: =AH67 -> 0 | AJ67: =AI67 -> 0 | AK67: =AJ67 -> 0 | AL67: =AK67 -> 0 | AM67: =AL67 -> 0 | AN67: =AM67 -> 0 | ... AQ67: =AP67 -> 0 | AS67: =AQ67 -> 0 | AT67: =AS67 -> 0 | AU67: =AT67 -> 0 | AV67: =AU67 -> 0 | AW67: =AV67 -> 0 | AX67: =AW67 -> 0 | AY67: =AX67 -> 0 | AZ67: =AY67 -> 0 | BA67: =AZ67 -> 0 | ... BD67: =BC67 -> 0 | BF67: =BD67 -> 0 | BG67: =BF67 -> 0 | BH67: =BG67 -> 0 | BI67: =BH67 -> 0 | BJ67: =BI67 -> 0 | BK67: =BJ67 -> 0 | BL67: =BK67 -> 0 | BM67: =BL67 -> 0 | BN67: =BM67 -> 0 | ... BQ67: =BP67 -> 0 | BS67: =BQ67 -> 0 | BT67: =BS67 -> 0 | BU67: =BT67 -> 0 | BV67: =BU67 -> 0 | BW67: =BV67 -> 0 | BX67: =BW67 -> 0 | BY67: =BX67 -> 0 | BZ67: =BY67 -> 0 | CA67: =BZ67 -> 0 | ... CD67: =CC67 -> 0 | CF67: =CD67 -> 0 | CG67: =CF67 -> 0 | CH67: =CG67 -> 0 | CI67: =CH67 -> 0 | CJ67: =CI67 -> 0 | CK67: =CJ67 -> 0 | CL67: =CK67 -> 0 | CM67: =CL67 -> 0 | CN67: =CM67 -> 0 | ... CQ67: =CP67 -> 0 | CS67: =CQ67 -> 0 | CT67: =CS67 -> 0 | CU67: =CT67 -> 0 | CV67: =CU67 -> 0 | CW67: =CV67 -> 0 | CX67: =CW67 -> 0 | CY67: =CX67 -> 0 | CZ67: =CY67 -> 0 | DA67: =CZ67 -> 0 | ... DD67: =DC67 -> 0 | DF67: =DD67 -> 0 | DG67: =DF67 -> 0 | DH67: =DG67 -> 0 | DI67: =DH67 -> 0 | DJ67: =DI67 -> 0 | DK67: =DJ67 -> 0 | DL67: =DK67 -> 0 | DM67: =DL67 -> 0 | DN67: =DM67 -> 0 | ... DQ67: =DP67 -> 0 | DS67: =SUM(F67:Q67)+SUM(S67:AD67)+SUM(AF67:AQ67)+SUM(AS67:BD67)+SUM(BF67:BQ67)+SUM(BS67:CD67) -> 0
C68: =C42 -> /// | E68: =E42 -> 0 | G68: =F68 -> 0 | H68: =G68 -> 0 | I68: =H68 -> 0 | J68: =I68 -> 0 | K68: =J68 -> 0 | L68: =K68 -> 0 | M68: =L68 -> 0 | N68: =M68 -> 0 | ... Q68: =P68 -> 0 | S68: =Q68 -> 0 | T68: =S68 -> 0 | U68: =T68 -> 0 | V68: =U68 -> 0 | W68: =V68 -> 0 | X68: =W68 -> 0 | Y68: =X68 -> 0 | Z68: =Y68 -> 0 | AA68: =Z68 -> 0 | ... AD68: =AC68 -> 0 | AF68: =AD68 -> 0 | AG68: =AF68 -> 0 | AH68: =AG68 -> 0 | AI68: =AH68 -> 0 | AJ68: =AI68 -> 0 | AK68: =AJ68 -> 0 | AL68: =AK68 -> 0 | AM68: =AL68 -> 0 | AN68: =AM68 -> 0 | ... AQ68: =AP68 -> 0 | AS68: =AQ68 -> 0 | AT68: =AS68 -> 0 | AU68: =AT68 -> 0 | AV68: =AU68 -> 0 | AW68: =AV68 -> 0 | AX68: =AW68 -> 0 | AY68: =AX68 -> 0 | AZ68: =AY68 -> 0 | BA68: =AZ68 -> 0 | ... BD68: =BC68 -> 0 | BF68: =BD68 -> 0 | BG68: =BF68 -> 0 | BH68: =BG68 -> 0 | BI68: =BH68 -> 0 | BJ68: =BI68 -> 0 | BK68: =BJ68 -> 0 | BL68: =BK68 -> 0 | BM68: =BL68 -> 0 | BN68: =BM68 -> 0 | ... BQ68: =BP68 -> 0 | BS68: =BQ68 -> 0 | BT68: =BS68 -> 0 | BU68: =BT68 -> 0 | BV68: =BU68 -> 0 | BW68: =BV68 -> 0 | BX68: =BW68 -> 0 | BY68: =BX68 -> 0 | BZ68: =BY68 -> 0 | CA68: =BZ68 -> 0 | ... CD68: =CC68 -> 0 | CF68: =CD68 -> 0 | CG68: =CF68 -> 0 | CH68: =CG68 -> 0 | CI68: =CH68 -> 0 | CJ68: =CI68 -> 0 | CK68: =CJ68 -> 0 | CL68: =CK68 -> 0 | CM68: =CL68 -> 0 | CN68: =CM68 -> 0 | ... CQ68: =CP68 -> 0 | CS68: =CQ68 -> 0 | CT68: =CS68 -> 0 | CU68: =CT68 -> 0 | CV68: =CU68 -> 0 | CW68: =CV68 -> 0 | CX68: =CW68 -> 0 | CY68: =CX68 -> 0 | CZ68: =CY68 -> 0 | DA68: =CZ68 -> 0 | ... DD68: =DC68 -> 0 | DF68: =DD68 -> 0 | DG68: =DF68 -> 0 | DH68: =DG68 -> 0 | DI68: =DH68 -> 0 | DJ68: =DI68 -> 0 | DK68: =DJ68 -> 0 | DL68: =DK68 -> 0 | DM68: =DL68 -> 0 | DN68: =DM68 -> 0 | ... DQ68: =DP68 -> 0 | DS68: =SUM(F68:Q68)+SUM(S68:AD68)+SUM(AF68:AQ68)+SUM(AS68:BD68)+SUM(BF68:BQ68)+SUM(BS68:CD68) -> 0
C69: =C43 -> /// | E69: =E43 -> 0 | G69: =F69 -> 0 | H69: =G69 -> 0 | I69: =H69 -> 0 | J69: =I69 -> 0 | K69: =J69 -> 0 | L69: =K69 -> 0 | M69: =L69 -> 0 | N69: =M69 -> 0 | ... Q69: =P69 -> 0 | S69: =Q69 -> 0 | T69: =S69 -> 0 | U69: =T69 -> 0 | V69: =U69 -> 0 | W69: =V69 -> 0 | X69: =W69 -> 0 | Y69: =X69 -> 0 | Z69: =Y69 -> 0 | AA69: =Z69 -> 0 | ... AD69: =AC69 -> 0 | AF69: =AD69 -> 0 | AG69: =AF69 -> 0 | AH69: =AG69 -> 0 | AI69: =AH69 -> 0 | AJ69: =AI69 -> 0 | AK69: =AJ69 -> 0 | AL69: =AK69 -> 0 | AM69: =AL69 -> 0 | AN69: =AM69 -> 0 | ... AQ69: =AP69 -> 0 | AS69: =AQ69 -> 0 | AT69: =AS69 -> 0 | AU69: =AT69 -> 0 | AV69: =AU69 -> 0 | AW69: =AV69 -> 0 | AX69: =AW69 -> 0 | AY69: =AX69 -> 0 | AZ69: =AY69 -> 0 | BA69: =AZ69 -> 0 | ... BD69: =BC69 -> 0 | BF69: =BD69 -> 0 | BG69: =BF69 -> 0 | BH69: =BG69 -> 0 | BI69: =BH69 -> 0 | BJ69: =BI69 -> 0 | BK69: =BJ69 -> 0 | BL69: =BK69 -> 0 | BM69: =BL69 -> 0 | BN69: =BM69 -> 0 | ... BQ69: =BP69 -> 0 | BS69: =BQ69 -> 0 | BT69: =BS69 -> 0 | BU69: =BT69 -> 0 | BV69: =BU69 -> 0 | BW69: =BV69 -> 0 | BX69: =BW69 -> 0 | BY69: =BX69 -> 0 | BZ69: =BY69 -> 0 | CA69: =BZ69 -> 0 | ... CD69: =CC69 -> 0 | CF69: =CD69 -> 0 | CG69: =CF69 -> 0 | CH69: =CG69 -> 0 | CI69: =CH69 -> 0 | CJ69: =CI69 -> 0 | CK69: =CJ69 -> 0 | CL69: =CK69 -> 0 | CM69: =CL69 -> 0 | CN69: =CM69 -> 0 | ... CQ69: =CP69 -> 0 | CS69: =CQ69 -> 0 | CT69: =CS69 -> 0 | CU69: =CT69 -> 0 | CV69: =CU69 -> 0 | CW69: =CV69 -> 0 | CX69: =CW69 -> 0 | CY69: =CX69 -> 0 | CZ69: =CY69 -> 0 | DA69: =CZ69 -> 0 | ... DD69: =DC69 -> 0 | DF69: =DD69 -> 0 | DG69: =DF69 -> 0 | DH69: =DG69 -> 0 | DI69: =DH69 -> 0 | DJ69: =DI69 -> 0 | DK69: =DJ69 -> 0 | DL69: =DK69 -> 0 | DM69: =DL69 -> 0 | DN69: =DM69 -> 0 | ... DQ69: =DP69 -> 0 | DS69: =SUM(F69:Q69)+SUM(S69:AD69)+SUM(AF69:AQ69)+SUM(AS69:BD69)+SUM(BF69:BQ69)+SUM(BS69:CD69) -> 0
A70: 3 | B70: 3 | C70: =C44 -> /// | E70: =E44 -> 0 | G70: =F70 -> 0 | H70: =G70 -> 0 | I70: =H70 -> 0 | J70: =I70 -> 0 | K70: =J70 -> 0 | L70: =K70 -> 0 | M70: =L70 -> 0 | N70: =M70 -> 0 | ... Q70: =P70 -> 0 | S70: =Q70 -> 0 | T70: =S70 -> 0 | U70: =T70 -> 0 | V70: =U70 -> 0 | W70: =V70 -> 0 | X70: =W70 -> 0 | Y70: =X70 -> 0 | Z70: =Y70 -> 0 | AA70: =Z70 -> 0 | ... AD70: =AC70 -> 0 | AF70: =AD70 -> 0 | AG70: =AF70 -> 0 | AH70: =AG70 -> 0 | AI70: =AH70 -> 0 | AJ70: =AI70 -> 0 | AK70: =AJ70 -> 0 | AL70: =AK70 -> 0 | AM70: =AL70 -> 0 | AN70: =AM70 -> 0 | ... AQ70: =AP70 -> 0 | AS70: =AQ70 -> 0 | AT70: =AS70 -> 0 | AU70: =AT70 -> 0 | AV70: =AU70 -> 0 | AW70: =AV70 -> 0 | AX70: =AW70 -> 0 | AY70: =AX70 -> 0 | AZ70: =AY70 -> 0 | BA70: =AZ70 -> 0 | ... BD70: =BC70 -> 0 | BF70: =BD70 -> 0 | BG70: =BF70 -> 0 | BH70: =BG70 -> 0 | BI70: =BH70 -> 0 | BJ70: =BI70 -> 0 | BK70: =BJ70 -> 0 | BL70: =BK70 -> 0 | BM70: =BL70 -> 0 | BN70: =BM70 -> 0 | ... BQ70: =BP70 -> 0 | BS70: =BQ70 -> 0 | BT70: =BS70 -> 0 | BU70: =BT70 -> 0 | BV70: =BU70 -> 0 | BW70: =BV70 -> 0 | BX70: =BW70 -> 0 | BY70: =BX70 -> 0 | BZ70: =BY70 -> 0 | CA70: =BZ70 -> 0 | ... CD70: =CC70 -> 0 | CF70: =CD70 -> 0 | CG70: =CF70 -> 0 | CH70: =CG70 -> 0 | CI70: =CH70 -> 0 | CJ70: =CI70 -> 0 | CK70: =CJ70 -> 0 | CL70: =CK70 -> 0 | CM70: =CL70 -> 0 | CN70: =CM70 -> 0 | ... CQ70: =CP70 -> 0 | CS70: =CQ70 -> 0 | CT70: =CS70 -> 0 | CU70: =CT70 -> 0 | CV70: =CU70 -> 0 | CW70: =CV70 -> 0 | CX70: =CW70 -> 0 | CY70: =CX70 -> 0 | CZ70: =CY70 -> 0 | DA70: =CZ70 -> 0 | ... DD70: =DC70 -> 0 | DF70: =DD70 -> 0 | DG70: =DF70 -> 0 | DH70: =DG70 -> 0 | DI70: =DH70 -> 0 | DJ70: =DI70 -> 0 | DK70: =DJ70 -> 0 | DL70: =DK70 -> 0 | DM70: =DL70 -> 0 | DN70: =DM70 -> 0 | ... DQ70: =DP70 -> 0 | DS70: =SUM(F70:Q70)+SUM(S70:AD70)+SUM(AF70:AQ70)+SUM(AS70:BD70)+SUM(BF70:BQ70)+SUM(BS70:CD70) -> 0
C71: =C45 -> /// | E71: =E45 -> 0 | G71: =F71 -> 0 | H71: =G71 -> 0 | I71: =H71 -> 0 | J71: =I71 -> 0 | K71: =J71 -> 0 | L71: =K71 -> 0 | M71: =L71 -> 0 | N71: =M71 -> 0 | ... Q71: =P71 -> 0 | S71: =Q71 -> 0 | T71: =S71 -> 0 | U71: =T71 -> 0 | V71: =U71 -> 0 | W71: =V71 -> 0 | X71: =W71 -> 0 | Y71: =X71 -> 0 | Z71: =Y71 -> 0 | AA71: =Z71 -> 0 | ... AD71: =AC71 -> 0 | AF71: =AD71 -> 0 | AG71: =AF71 -> 0 | AH71: =AG71 -> 0 | AI71: =AH71 -> 0 | AJ71: =AI71 -> 0 | AK71: =AJ71 -> 0 | AL71: =AK71 -> 0 | AM71: =AL71 -> 0 | AN71: =AM71 -> 0 | ... AQ71: =AP71 -> 0 | AS71: =AQ71 -> 0 | AT71: =AS71 -> 0 | AU71: =AT71 -> 0 | AV71: =AU71 -> 0 | AW71: =AV71 -> 0 | AX71: =AW71 -> 0 | AY71: =AX71 -> 0 | AZ71: =AY71 -> 0 | BA71: =AZ71 -> 0 | ... BD71: =BC71 -> 0 | BF71: =BD71 -> 0 | BG71: =BF71 -> 0 | BH71: =BG71 -> 0 | BI71: =BH71 -> 0 | BJ71: =BI71 -> 0 | BK71: =BJ71 -> 0 | BL71: =BK71 -> 0 | BM71: =BL71 -> 0 | BN71: =BM71 -> 0 | ... BQ71: =BP71 -> 0 | BS71: =BQ71 -> 0 | BT71: =BS71 -> 0 | BU71: =BT71 -> 0 | BV71: =BU71 -> 0 | BW71: =BV71 -> 0 | BX71: =BW71 -> 0 | BY71: =BX71 -> 0 | BZ71: =BY71 -> 0 | CA71: =BZ71 -> 0 | ... CD71: =CC71 -> 0 | CF71: =CD71 -> 0 | CG71: =CF71 -> 0 | CH71: =CG71 -> 0 | CI71: =CH71 -> 0 | CJ71: =CI71 -> 0 | CK71: =CJ71 -> 0 | CL71: =CK71 -> 0 | CM71: =CL71 -> 0 | CN71: =CM71 -> 0 | ... CQ71: =CP71 -> 0 | CS71: =CQ71 -> 0 | CT71: =CS71 -> 0 | CU71: =CT71 -> 0 | CV71: =CU71 -> 0 | CW71: =CV71 -> 0 | CX71: =CW71 -> 0 | CY71: =CX71 -> 0 | CZ71: =CY71 -> 0 | DA71: =CZ71 -> 0 | ... DD71: =DC71 -> 0 | DF71: =DD71 -> 0 | DG71: =DF71 -> 0 | DH71: =DG71 -> 0 | DI71: =DH71 -> 0 | DJ71: =DI71 -> 0 | DK71: =DJ71 -> 0 | DL71: =DK71 -> 0 | DM71: =DL71 -> 0 | DN71: =DM71 -> 0 | ... DQ71: =DP71 -> 0 | DS71: =SUM(F71:Q71)+SUM(S71:AD71)+SUM(AF71:AQ71)+SUM(AS71:BD71)+SUM(BF71:BQ71)+SUM(BS71:CD71) -> 0
A72: 3 | B72: 4 | C72: =C46 -> /// | E72: =E46 -> 0 | G72: =F72 -> 0 | H72: =G72 -> 0 | I72: =H72 -> 0 | J72: =I72 -> 0 | K72: =J72 -> 0 | L72: =K72 -> 0 | M72: =L72 -> 0 | N72: =M72 -> 0 | ... Q72: =P72 -> 0 | S72: =Q72 -> 0 | T72: =S72 -> 0 | U72: =T72 -> 0 | V72: =U72 -> 0 | W72: =V72 -> 0 | X72: =W72 -> 0 | Y72: =X72 -> 0 | Z72: =Y72 -> 0 | AA72: =Z72 -> 0 | ... AD72: =AC72 -> 0 | AF72: =AD72 -> 0 | AG72: =AF72 -> 0 | AH72: =AG72 -> 0 | AI72: =AH72 -> 0 | AJ72: =AI72 -> 0 | AK72: =AJ72 -> 0 | AL72: =AK72 -> 0 | AM72: =AL72 -> 0 | AN72: =AM72 -> 0 | ... AQ72: =AP72 -> 0 | AS72: =AQ72 -> 0 | AT72: =AS72 -> 0 | AU72: =AT72 -> 0 | AV72: =AU72 -> 0 | AW72: =AV72 -> 0 | AX72: =AW72 -> 0 | AY72: =AX72 -> 0 | AZ72: =AY72 -> 0 | BA72: =AZ72 -> 0 | ... BD72: =BC72 -> 0 | BF72: =BD72 -> 0 | BG72: =BF72 -> 0 | BH72: =BG72 -> 0 | BI72: =BH72 -> 0 | BJ72: =BI72 -> 0 | BK72: =BJ72 -> 0 | BL72: =BK72 -> 0 | BM72: =BL72 -> 0 | BN72: =BM72 -> 0 | ... BQ72: =BP72 -> 0 | BS72: =BQ72 -> 0 | BT72: =BS72 -> 0 | BU72: =BT72 -> 0 | BV72: =BU72 -> 0 | BW72: =BV72 -> 0 | BX72: =BW72 -> 0 | BY72: =BX72 -> 0 | BZ72: =BY72 -> 0 | CA72: =BZ72 -> 0 | ... CD72: =CC72 -> 0 | CF72: =CD72 -> 0 | CG72: =CF72 -> 0 | CH72: =CG72 -> 0 | CI72: =CH72 -> 0 | CJ72: =CI72 -> 0 | CK72: =CJ72 -> 0 | CL72: =CK72 -> 0 | CM72: =CL72 -> 0 | CN72: =CM72 -> 0 | ... CQ72: =CP72 -> 0 | CS72: =CQ72 -> 0 | CT72: =CS72 -> 0 | CU72: =CT72 -> 0 | CV72: =CU72 -> 0 | CW72: =CV72 -> 0 | CX72: =CW72 -> 0 | CY72: =CX72 -> 0 | CZ72: =CY72 -> 0 | DA72: =CZ72 -> 0 | ... DD72: =DC72 -> 0 | DF72: =DD72 -> 0 | DG72: =DF72 -> 0 | DH72: =DG72 -> 0 | DI72: =DH72 -> 0 | DJ72: =DI72 -> 0 | DK72: =DJ72 -> 0 | DL72: =DK72 -> 0 | DM72: =DL72 -> 0 | DN72: =DM72 -> 0 | ... DQ72: =DP72 -> 0 | DS72: =SUM(F72:Q72)+SUM(S72:AD72)+SUM(AF72:AQ72)+SUM(AS72:BD72)+SUM(BF72:BQ72)+SUM(BS72:CD72) -> 0
C73: =C47 -> /// | E73: =E47 -> 0 | G73: =F73 -> 0 | H73: =G73 -> 0 | I73: =H73 -> 0 | J73: =I73 -> 0 | K73: =J73 -> 0 | L73: =K73 -> 0 | M73: =L73 -> 0 | N73: =M73 -> 0 | ... Q73: =P73 -> 0 | S73: =Q73 -> 0 | T73: =S73 -> 0 | U73: =T73 -> 0 | V73: =U73 -> 0 | W73: =V73 -> 0 | X73: =W73 -> 0 | Y73: =X73 -> 0 | Z73: =Y73 -> 0 | AA73: =Z73 -> 0 | ... AD73: =AC73 -> 0 | AF73: =AD73 -> 0 | AG73: =AF73 -> 0 | AH73: =AG73 -> 0 | AI73: =AH73 -> 0 | AJ73: =AI73 -> 0 | AK73: =AJ73 -> 0 | AL73: =AK73 -> 0 | AM73: =AL73 -> 0 | AN73: =AM73 -> 0 | ... AQ73: =AP73 -> 0 | AS73: =AQ73 -> 0 | AT73: =AS73 -> 0 | AU73: =AT73 -> 0 | AV73: =AU73 -> 0 | AW73: =AV73 -> 0 | AX73: =AW73 -> 0 | AY73: =AX73 -> 0 | AZ73: =AY73 -> 0 | BA73: =AZ73 -> 0 | ... BD73: =BC73 -> 0 | BF73: =BD73 -> 0 | BG73: =BF73 -> 0 | BH73: =BG73 -> 0 | BI73: =BH73 -> 0 | BJ73: =BI73 -> 0 | BK73: =BJ73 -> 0 | BL73: =BK73 -> 0 | BM73: =BL73 -> 0 | BN73: =BM73 -> 0 | ... BQ73: =BP73 -> 0 | BS73: =BQ73 -> 0 | BT73: =BS73 -> 0 | BU73: =BT73 -> 0 | BV73: =BU73 -> 0 | BW73: =BV73 -> 0 | BX73: =BW73 -> 0 | BY73: =BX73 -> 0 | BZ73: =BY73 -> 0 | CA73: =BZ73 -> 0 | ... CD73: =CC73 -> 0 | CF73: =CD73 -> 0 | CG73: =CF73 -> 0 | CH73: =CG73 -> 0 | CI73: =CH73 -> 0 | CJ73: =CI73 -> 0 | CK73: =CJ73 -> 0 | CL73: =CK73 -> 0 | CM73: =CL73 -> 0 | CN73: =CM73 -> 0 | ... CQ73: =CP73 -> 0 | CS73: =CQ73 -> 0 | CT73: =CS73 -> 0 | CU73: =CT73 -> 0 | CV73: =CU73 -> 0 | CW73: =CV73 -> 0 | CX73: =CW73 -> 0 | CY73: =CX73 -> 0 | CZ73: =CY73 -> 0 | DA73: =CZ73 -> 0 | ... DD73: =DC73 -> 0 | DF73: =DD73 -> 0 | DG73: =DF73 -> 0 | DH73: =DG73 -> 0 | DI73: =DH73 -> 0 | DJ73: =DI73 -> 0 | DK73: =DJ73 -> 0 | DL73: =DK73 -> 0 | DM73: =DL73 -> 0 | DN73: =DM73 -> 0 | ... DQ73: =DP73 -> 0 | DS73: =SUM(F73:Q73)+SUM(S73:AD73)+SUM(AF73:AQ73)+SUM(AS73:BD73)+SUM(BF73:BQ73)+SUM(BS73:CD73) -> 0
A74: 3 | B74: 5 | C74: =C48 -> /// | E74: =E48 -> 0 | G74: =F74 -> 0 | H74: =G74 -> 0 | I74: =H74 -> 0 | J74: =I74 -> 0 | K74: =J74 -> 0 | L74: =K74 -> 0 | M74: =L74 -> 0 | N74: =M74 -> 0 | ... Q74: =P74 -> 0 | S74: =Q74 -> 0 | T74: =S74 -> 0 | U74: =T74 -> 0 | V74: =U74 -> 0 | W74: =V74 -> 0 | X74: =W74 -> 0 | Y74: =X74 -> 0 | Z74: =Y74 -> 0 | AA74: =Z74 -> 0 | ... AD74: =AC74 -> 0 | AF74: =AD74 -> 0 | AG74: =AF74 -> 0 | AH74: =AG74 -> 0 | AI74: =AH74 -> 0 | AJ74: =AI74 -> 0 | AK74: =AJ74 -> 0 | AL74: =AK74 -> 0 | AM74: =AL74 -> 0 | AN74: =AM74 -> 0 | ... AQ74: =AP74 -> 0 | AS74: =AQ74 -> 0 | AT74: =AS74 -> 0 | AU74: =AT74 -> 0 | AV74: =AU74 -> 0 | AW74: =AV74 -> 0 | AX74: =AW74 -> 0 | AY74: =AX74 -> 0 | AZ74: =AY74 -> 0 | BA74: =AZ74 -> 0 | ... BD74: =BC74 -> 0 | BF74: =BD74 -> 0 | BG74: =BF74 -> 0 | BH74: =BG74 -> 0 | BI74: =BH74 -> 0 | BJ74: =BI74 -> 0 | BK74: =BJ74 -> 0 | BL74: =BK74 -> 0 | BM74: =BL74 -> 0 | BN74: =BM74 -> 0 | ... BQ74: =BP74 -> 0 | BS74: =BQ74 -> 0 | BT74: =BS74 -> 0 | BU74: =BT74 -> 0 | BV74: =BU74 -> 0 | BW74: =BV74 -> 0 | BX74: =BW74 -> 0 | BY74: =BX74 -> 0 | BZ74: =BY74 -> 0 | CA74: =BZ74 -> 0 | ... CD74: =CC74 -> 0 | CF74: =CD74 -> 0 | CG74: =CF74 -> 0 | CH74: =CG74 -> 0 | CI74: =CH74 -> 0 | CJ74: =CI74 -> 0 | CK74: =CJ74 -> 0 | CL74: =CK74 -> 0 | CM74: =CL74 -> 0 | CN74: =CM74 -> 0 | ... CQ74: =CP74 -> 0 | CS74: =CQ74 -> 0 | CT74: =CS74 -> 0 | CU74: =CT74 -> 0 | CV74: =CU74 -> 0 | CW74: =CV74 -> 0 | CX74: =CW74 -> 0 | CY74: =CX74 -> 0 | CZ74: =CY74 -> 0 | DA74: =CZ74 -> 0 | ... DD74: =DC74 -> 0 | DF74: =DD74 -> 0 | DG74: =DF74 -> 0 | DH74: =DG74 -> 0 | DI74: =DH74 -> 0 | DJ74: =DI74 -> 0 | DK74: =DJ74 -> 0 | DL74: =DK74 -> 0 | DM74: =DL74 -> 0 | DN74: =DM74 -> 0 | ... DQ74: =DP74 -> 0 | DS74: =SUM(F74:Q74)+SUM(S74:AD74)+SUM(AF74:AQ74)+SUM(AS74:BD74)+SUM(BF74:BQ74)+SUM(BS74:CD74) -> 0
C75: =C49 -> /// | E75: =E49 -> 0 | G75: =F75 -> 0 | H75: =G75 -> 0 | I75: =H75 -> 0 | J75: =I75 -> 0 | K75: =J75 -> 0 | L75: =K75 -> 0 | M75: =L75 -> 0 | N75: =M75 -> 0 | ... Q75: =P75 -> 0 | S75: =Q75 -> 0 | T75: =S75 -> 0 | U75: =T75 -> 0 | V75: =U75 -> 0 | W75: =V75 -> 0 | X75: =W75 -> 0 | Y75: =X75 -> 0 | Z75: =Y75 -> 0 | AA75: =Z75 -> 0 | ... AD75: =AC75 -> 0 | AF75: =AD75 -> 0 | AG75: =AF75 -> 0 | AH75: =AG75 -> 0 | AI75: =AH75 -> 0 | AJ75: =AI75 -> 0 | AK75: =AJ75 -> 0 | AL75: =AK75 -> 0 | AM75: =AL75 -> 0 | AN75: =AM75 -> 0 | ... AQ75: =AP75 -> 0 | AS75: =AQ75 -> 0 | AT75: =AS75 -> 0 | AU75: =AT75 -> 0 | AV75: =AU75 -> 0 | AW75: =AV75 -> 0 | AX75: =AW75 -> 0 | AY75: =AX75 -> 0 | AZ75: =AY75 -> 0 | BA75: =AZ75 -> 0 | ... BD75: =BC75 -> 0 | BF75: =BD75 -> 0 | BG75: =BF75 -> 0 | BH75: =BG75 -> 0 | BI75: =BH75 -> 0 | BJ75: =BI75 -> 0 | BK75: =BJ75 -> 0 | BL75: =BK75 -> 0 | BM75: =BL75 -> 0 | BN75: =BM75 -> 0 | ... BQ75: =BP75 -> 0 | BS75: =BQ75 -> 0 | BT75: =BS75 -> 0 | BU75: =BT75 -> 0 | BV75: =BU75 -> 0 | BW75: =BV75 -> 0 | BX75: =BW75 -> 0 | BY75: =BX75 -> 0 | BZ75: =BY75 -> 0 | CA75: =BZ75 -> 0 | ... CD75: =CC75 -> 0 | CF75: =CD75 -> 0 | CG75: =CF75 -> 0 | CH75: =CG75 -> 0 | CI75: =CH75 -> 0 | CJ75: =CI75 -> 0 | CK75: =CJ75 -> 0 | CL75: =CK75 -> 0 | CM75: =CL75 -> 0 | CN75: =CM75 -> 0 | ... CQ75: =CP75 -> 0 | CS75: =CQ75 -> 0 | CT75: =CS75 -> 0 | CU75: =CT75 -> 0 | CV75: =CU75 -> 0 | CW75: =CV75 -> 0 | CX75: =CW75 -> 0 | CY75: =CX75 -> 0 | CZ75: =CY75 -> 0 | DA75: =CZ75 -> 0 | ... DD75: =DC75 -> 0 | DF75: =DD75 -> 0 | DG75: =DF75 -> 0 | DH75: =DG75 -> 0 | DI75: =DH75 -> 0 | DJ75: =DI75 -> 0 | DK75: =DJ75 -> 0 | DL75: =DK75 -> 0 | DM75: =DL75 -> 0 | DN75: =DM75 -> 0 | ... DQ75: =DP75 -> 0 | DS75: =SUM(F75:Q75)+SUM(S75:AD75)+SUM(AF75:AQ75)+SUM(AS75:BD75)+SUM(BF75:BQ75)+SUM(BS75:CD75) -> 0
C76: =C50 -> /// | E76: =E50 -> 0 | G76: =F76 -> 0 | H76: =G76 -> 0 | I76: =H76 -> 0 | J76: =I76 -> 0 | K76: =J76 -> 0 | L76: =K76 -> 0 | M76: =L76 -> 0 | N76: =M76 -> 0 | ... Q76: =P76 -> 0 | S76: =Q76 -> 0 | T76: =S76 -> 0 | U76: =T76 -> 0 | V76: =U76 -> 0 | W76: =V76 -> 0 | X76: =W76 -> 0 | Y76: =X76 -> 0 | Z76: =Y76 -> 0 | AA76: =Z76 -> 0 | ... AD76: =AC76 -> 0 | AF76: =AD76 -> 0 | AG76: =AF76 -> 0 | AH76: =AG76 -> 0 | AI76: =AH76 -> 0 | AJ76: =AI76 -> 0 | AK76: =AJ76 -> 0 | AL76: =AK76 -> 0 | AM76: =AL76 -> 0 | AN76: =AM76 -> 0 | ... AQ76: =AP76 -> 0 | AS76: =AQ76 -> 0 | AT76: =AS76 -> 0 | AU76: =AT76 -> 0 | AV76: =AU76 -> 0 | AW76: =AV76 -> 0 | AX76: =AW76 -> 0 | AY76: =AX76 -> 0 | AZ76: =AY76 -> 0 | BA76: =AZ76 -> 0 | ... BD76: =BC76 -> 0 | BF76: =BD76 -> 0 | BG76: =BF76 -> 0 | BH76: =BG76 -> 0 | BI76: =BH76 -> 0 | BJ76: =BI76 -> 0 | BK76: =BJ76 -> 0 | BL76: =BK76 -> 0 | BM76: =BL76 -> 0 | BN76: =BM76 -> 0 | ... BQ76: =BP76 -> 0 | BS76: =BQ76 -> 0 | BT76: =BS76 -> 0 | BU76: =BT76 -> 0 | BV76: =BU76 -> 0 | BW76: =BV76 -> 0 | BX76: =BW76 -> 0 | BY76: =BX76 -> 0 | BZ76: =BY76 -> 0 | CA76: =BZ76 -> 0 | ... CD76: =CC76 -> 0 | CF76: =CD76 -> 0 | CG76: =CF76 -> 0 | CH76: =CG76 -> 0 | CI76: =CH76 -> 0 | CJ76: =CI76 -> 0 | CK76: =CJ76 -> 0 | CL76: =CK76 -> 0 | CM76: =CL76 -> 0 | CN76: =CM76 -> 0 | ... CQ76: =CP76 -> 0 | CS76: =CQ76 -> 0 | CT76: =CS76 -> 0 | CU76: =CT76 -> 0 | CV76: =CU76 -> 0 | CW76: =CV76 -> 0 | CX76: =CW76 -> 0 | CY76: =CX76 -> 0 | CZ76: =CY76 -> 0 | DA76: =CZ76 -> 0 | ... DD76: =DC76 -> 0 | DF76: =DD76 -> 0 | DG76: =DF76 -> 0 | DH76: =DG76 -> 0 | DI76: =DH76 -> 0 | DJ76: =DI76 -> 0 | DK76: =DJ76 -> 0 | DL76: =DK76 -> 0 | DM76: =DL76 -> 0 | DN76: =DM76 -> 0 | ... DQ76: =DP76 -> 0 | DS76: =SUM(F76:Q76)+SUM(S76:AD76)+SUM(AF76:AQ76)+SUM(AS76:BD76)+SUM(BF76:BQ76)+SUM(BS76:CD76) -> 0
